Workbook

Sheet Pivot Table
A2: Row Labels | B2: Count of 100% Attendance [Aundh] | C2: Count of 100% Attendance [Kondhwa] | D2: Count of 100% Attendance [Sinhgad Road]
A3: Aarav Patil | B3: 1 | C3: 1 | D3: 1
A4: Meera Kumar | B4: 1 | C4: 1 | D4: 1
A5: daksh sharma | B5: 1 | C5: 1 | D5: 1
A6: Atharva Deshmukh | B6: 1 | C6: 1 | D6: 1
A7: Ira Kumar | B7: 1 | C7: 1 | D7: 1
A8: prem patil | B8: 1 | C8: 1 | D8: 1
A9: aryan patil | B9: 1 | C9: 1 | D9: 1
A10: Gandhar Kulkarni | B10: 1 | C10: 1 | D10: 1
A11: Ayaan Joshi | B11: 1 | C11: 1 | D11: 1
A12: Vedant Jadhav | B12: 1 | C12: 1 | D12: 1
A13: Hrishikesh Gokhale | B13: 1 | C13: 1 | D13: 1
A14: Siya Kumar | B14: 1 | C14: 1 | D14: 1
A15: Grand Total | B15: 4 | C15: 4 | D15: 4

Sheet Combined attendance
A1: Aundh Attendance | D1: Kondhwa Attendance | G1: Sinhgad Road Attendance
A2: Student Name [Aundh] | B2: Attendance [Aundh] | C2: 100% Attendance [Aundh] | D2: Student Name [Kondhwa] | E2: Attendance [Kondhwa] | F2: 100% Attendance [Kondhwa] | G2: Student Name [Sinhgad_Road] | H2: Attendance [Sinhgad_Road] | I2: 100% Attendance [Sinhgad Road]
A3: Aarav Patil | B3: {=VLOOKUP(A3:A51,Aundh!B:AM,39,0)} -> #REF! | C3: {=_xlfn._xlws.FILTER(A3:A50, B3:B50=100, "No students with 100% attendance")} -> #REF! | D3: aarav sharma | E3: {=VLOOKUP(D3:D51,Kondhwa!B:AM,39,0)} -> #REF! | F3: {=_xlfn._xlws.FILTER(D3:D50, E3:E50=100, "No students with 100% attendance")} -> #REF! | G3: daksh sharma | H3: {=VLOOKUP(G3:G51,Sinhgad_Road!B:AM,39,0)} -> #REF! | I3: {=_xlfn._xlws.FILTER(G3:G50, H3:H50=100, "No students with 100% attendance")} -> #REF!
A4: Atharva Deshmukh | B4: #REF! | D4: Aditya Kadam | E4: #REF! | G4: prem patil | H4: #REF!
A5: aryan patil | B5: #REF! | D5: Aniket Jadhav | E5: #REF! | G5: Ayaan Joshi | H5: #REF!
A6: Kabir Desai | B6: #REF! | D6: Meera Kumar | E6: #REF! | G6: ram sharma | H6: #REF!
A7: Vivaan Kulkarni | B7: #REF! | D7: Ira Kumar | E7: #REF! | G7: Anaya Joshi | H7: #REF!
A8: Reyansh Sharma | B8: #REF! | D8: Atharva Gaikwad | E8: #REF! | G8: ayra sharma | H8: #REF!
A9: Siddharth Joshi | B9: #REF! | D9: Chinmay Deo | E9: #REF! | G9: Kabir Desai | H9: #REF!
A10: Anay Shinde | B10: #REF! | D10: Aarav Patil | E10: #REF! | G10: Anaya Desai | H10: #REF!
A11: Ishaan Chavan | B11: #REF! | D11: Ira Patil | E11: #REF! | G11: Meera Patil | H11: #REF!
A12: Ira Joshi | B12: #REF! | D12: Reyansh Joshi | E12: #REF! | G12: pratik kumar | H12: #REF!
A13: Omkar Bhosale | B13: #REF! | D13: Digvijay Mohite | E13: #REF! | G13: Aarav Desai | H13: #REF!
A14: Rudra Gaikwad | B14: #REF! | D14: Durvesh Raut | E14: #REF! | G14: pratik more | H14: #REF!
A15: Vedant Jadhav | B15: #REF! | D15: Ayaan Joshi | E15: #REF! | G15: shubham pawar | H15: #REF!
... A51: Anaya Desai | B51: #REF! | D51: Siya Joshi | E51: #REF! | G51: Vivaan Joshi | H51: #REF!

Sheet Aundh
A1: Student ID | B1: Student Name | C1: Date of Birth | D1: Gender | E1: Parent Contact Number | F1: Student Email | G1: Address | H1: School/College Name | I1: Previous Academic Performance (%) | J1: Emergency Contact | K1: Course | L1: Course Duration (Months) | M1: Batch | N1: Batch Start Date | O1: Batch End Date | P1: Classroom/Room No. | Q1: Mode | R1: Session Days | S1: Subject | T1: Teacher | U1: Enrollment Date | V1: Registration Date | W1: Total Course Fees | X1: Amount Paid | Y1: Pending Amount | Z1: Discount Given | AA1: Installment Plan | AB1: Next Payment Due Date | AC1: Payment Status | AD1: Payment Method | AE1: Number of Tests Taken | AF1: Average Test Score | AG1: Top Test Score | AH1: Progress Comments | AI1: Homework Completion Rate (%) | AJ1: Total Classes Conducted | AK1: Classes Attended | AL1: Leave Notes/Remarks | AM1: Attendance (%) | AN1: Attendance Alerts Sent | AO1: Parent Feedback | AP1: Student Feedback | AQ1: Last Feedback Date | AR1: Follow-up Date | AS1: WhatsApp Opt-in | AT1: Lead Source | AU1: Counselor/Admission Handled By | AV1: Dropout Status | AW1: Reason for Leaving
A2: AU-007 | B2: Aarav Patil | C2: 2006-05-20 | D2: Female | E2: 9827095765 | F2: ira.sharma7@gmail.com | G2: 318, Aundh Pune | H2: City International School | I2: 82 | J2: 9953297386 | K2: Foundation 8-10 | L2: 6 | M2: Evening | N2: 2024-01-28 | O2: 2024-07-26 | P2: R-111 | Q2: Offline | R2: Tue-Thu-Sat | S2: Maths | T2: Preeti Desai | U2: 2024-05-20 | V2: 2024-05-15 | W2: 43018 | X2: 39256 | Y2: 3762 | Z2: 4189 | AA2: No | AB2: =RANDBETWEEN(DATE(2025,7,1),DATE(2025,12,31)) -> 46020 | AC2: Partial | AD2: UPI | AE2: 5 | AF2: 41 | AG2: 77 | AH2: Average | AI2: 81 | AJ2: 24 | AK2: 24 | AL2: Family function | AM2: 100 | AN2: Yes | AO2: 3 | AP2: 5 | AQ2: 2024-07-11 | AR2: 2024-08-09 | AS2: No | AT2: Facebook Ad | AU2: Nidhi Shah | AV2: Left | AW2: Switched institute
A3: AU-048 | B3: Atharva Deshmukh | C3: 2006-07-29 | D3: Female | E3: 9895313505 | F3: aarav.kumar48@gmail.com | G3: 937, Aundh Pune | H3: Modern College | I3: 87 | J3: 9912189875 | K3: Foundation 8-10 | L3: 3 | M3: Afternoon | N3: 2024-01-15 | O3: 2024-04-14 | P3: R-118 | Q3: Offline | R3: Mon-Wed-Fri | S3: Physics | T3: Ravi Kumar | U3: 2024-04-01 | V3: 2024-03-25 | W3: 20086 | X3: 19800 | Y3: 286 | Z3: 1952 | AA3: No | AB3: =RANDBETWEEN(DATE(2025,7,1),DATE(2025,12,31)) -> 45917 | AC3: Partial | AD3: Bank Transfer | AE3: 9 | AF3: 67 | AG3: 86 | AH3: Good | AI3: 67 | AJ3: 22 | AK3: 22 | AM3: 100 | AN3: No | AO3: 5 | AP3: 4 | AQ3: 2024-04-23 | AR3: 2024-05-06 | AS3: No | AT3: Instagram Ad | AU3: Amit Deshmukh | AV3: Left | AW3: Too far
A4: AU-015 | B4: aryan patil | C4: 2006-07-12 | D4: Female | E4: 9827032133 | F4: aarav.patil15@gmail.com | G4: 694, Aundh Pune | H4: Vidyanchal School | I4: 79 | J4: 9919617248 | K4: NEET | L4: 6 | M4: Morning | N4: 2024-01-23 | O4: 2024-07-21 | P4: R-107 | Q4: Hybrid | R4: Mon-Wed-Fri | S4: Chemistry | T4: Sneha Patil | U4: 2024-02-08 | V4: 2024-02-06 | W4: 33714 | X4: 33476 | Y4: 238 | Z4: 1249 | AA4: Yes | AB4: =RANDBETWEEN(DATE(2025,7,1),DATE(2025,12,31)) -> 45999 | AC4: Partial | AD4: Bank Transfer | AE4: 8 | AF4: 66 | AG4: 79 | AH4: Needs Improvement | AI4: 85 | AJ4: 51 | AK4: 50 | AM4: 100 | AN4: No | AO4: 2 | AP4: 5 | AQ4: 2024-03-01 | AR4: 2024-03-14 | AS4: No | AT4: Website | AU4: Amit Deshmukh | AV4: Left | AW4: Switched institute
A5: AU-044 | B5: Kabir Desai | C5: 2005-09-24 | D5: Male | E5: 9861278670 | F5: kabir.desai44@gmail.com | G5: 169, Aundh Pune | H5: D.A.V. Public School | I5: 70 | J5: 9926091051 | K5: MHT-CET | L5: 6 | M5: Morning | N5: 2024-02-11 | O5: 2024-08-09 | P5: R-120 | Q5: Hybrid | R5: Tue-Thu-Sat | S5: Chemistry | T5: Anil Sharma | U5: 2024-04-12 | V5: 2024-04-09 | W5: 26521 | X5: 25742 | Y5: 779 | Z5: 1089 | AA5: No | AB5: =RANDBETWEEN(DATE(2025,7,1),DATE(2025,12,31)) -> 45923 | AC5: Partial | AD5: UPI | AE5: 7 | AF5: 79 | AG5: 79 | AH5: Good | AI5: 78 | AJ5: 36 | AK5: 35 | AM5: 97 | AN5: Yes | AO5: 5 | AP5: 1 | AQ5: 2024-05-08 | AR5: 2024-05-31 | AS5: Yes | AT5: Instagram Ad | AU5: Amit Deshmukh | AV5: Left | AW5: Lost interest
A6: AU-017 | B6: Vivaan Kulkarni | C6: 2005-06-15 | D6: Female | E6: 9810220839 | F6: anaya.joshi17@gmail.com | G6: 751, Aundh Pune | H6: City School | I6: 75 | J6: 9963948363 | K6: NEET | L6: 12 | M6: Morning | N6: 2024-01-20 | O6: 2025-01-14 | P6: R-104 | Q6: Offline | R6: Tue-Thu-Sat | S6: Physics | T6: Anil Sharma | U6: 2024-02-24 | V6: 2024-02-24 | W6: 41229 | X6: 40571 | Y6: 658 | Z6: 4623 | AA6: Yes | AB6: =RANDBETWEEN(DATE(2025,7,1),DATE(2025,12,31)) -> 45864 | AC6: Partial | AD6: Bank Transfer | AE6: 6 | AF6: 41 | AG6: 93 | AH6: Needs Improvement | AI6: 85 | AJ6: 33 | AK6: 32 | AM6: 96 | AN6: Yes | AO6: 1 | AP6: 1 | AQ6: 2024-03-26 | AR6: 2024-04-21 | AS6: Yes | AT6: Instagram Ad | AU6: Rahul Mehta | AV6: Left | AW6: Switched institute
A7: AU-001 | B7: Reyansh Sharma | C7: 2005-01-18 | D7: Female | E7: 9855426302 | F7: reyansh.sharma1@gmail.com | G7: 463, Aundh Pune | H7: Vidyanchal School | I7: 77 | J7: 9926479089 | K7: Foundation 8-10 | L7: 12 | M7: Evening | N7: 2024-01-02 | O7: 2024-12-27 | P7: R-113 | Q7: Hybrid | R7: Tue-Thu-Sat | S7: Maths | T7: Preeti Desai | U7: 2024-04-20 | V7: 2024-04-14 | W7: 42851 | X7: 40171 | Y7: 2680 | Z7: 4474 | AA7: No | AB7: =RANDBETWEEN(DATE(2025,7,1),DATE(2025,12,31)) -> 45892 | AC7: Partial | AD7: Card | AE7: 1 | AF7: 46 | AG7: 96 | AH7: Average | AI7: 71 | AJ7: 45 | AK7: 43 | AM7: 95 | AN7: No | AO7: 2 | AP7: 4 | AQ7: 2024-05-14 | AR7: 2024-06-08 | AS7: No | AT7: Referral | AU7: Amit Deshmukh | AV7: Left | AW7: Lost interest
A8: AU-030 | B8: Siddharth Joshi | C8: 2005-04-23 | D8: Male | E8: 9895766321 | F8: aarav.desai30@gmail.com | G8: 870, Aundh Pune | H8: D.A.V. Public School | I8: 94 | J8: 9975991785 | K8: NEET | L8: 3 | M8: Afternoon | N8: 2024-01-06 | O8: 2024-04-05 | P8: R-120 | Q8: Online | R8: Mon-Wed-Fri | S8: Maths | T8: Vikram Joshi | U8: 2024-02-24 | V8: 2024-02-15 | W8: 21243 | X8: 20076 | Y8: 1167 | Z8: 3153 | AA8: Yes | AB8: =RANDBETWEEN(DATE(2025,7,1),DATE(2025,12,31)) -> 45982 | AC8: Partial | AD8: Cash | AE8: 2 | AF8: 67 | AG8: 70 | AH8: Needs Improvement | AI8: 82 | AJ8: 60 | AK8: 57 | AL8: Family function | AM8: 95 | AN8: Yes | AO8: 5 | AP8: 4 | AQ8: 2024-04-03 | AR8: 2024-04-21 | AS8: Yes | AT8: Walk-in | AU8: Rahul Mehta | AV8: Active
A9: AU-014 | B9: Anay Shinde | C9: 2006-06-06 | D9: Male | E9: 9822011112 | F9: vivaan.joshi14@gmail.com | G9: 738, Aundh Pune | H9: Modern College | I9: 62 | J9: 9953143872 | K9: JEE | L9: 12 | M9: Morning | N9: 2024-03-22 | O9: 2025-03-17 | P9: R-114 | Q9: Online | R9: Tue-Thu-Sat | S9: Biology | T9: Anil Sharma | U9: 2024-02-25 | V9: 2024-02-25 | W9: 24474 | X9: 20873 | Y9: 3601 | Z9: 4292 | AA9: No | AB9: =RANDBETWEEN(DATE(2025,7,1),DATE(2025,12,31)) -> 45930 | AC9: Partial | AD9: Card | AE9: 6 | AF9: 44 | AG9: 50 | AH9: Needs Improvement | AI9: 91 | AJ9: 34 | AK9: 32 | AM9: 94 | AN9: No | AO9: 2 | AP9: 1 | AQ9: 2024-03-16 | AR9: 2024-04-06 | AS9: No | AT9: Walk-in | AU9: Nidhi Shah | AV9: Active
A10: AU-018 | B10: Ishaan Chavan | C10: 2005-05-10 | D10: Male | E10: 9864434821 | F10: anaya.kumar18@gmail.com | G10: 551, Aundh Pune | H10: Modern College | I10: 71 | J10: 9951130048 | K10: NEET | L10: 12 | M10: Morning | N10: 2024-01-05 | O10: 2024-12-30 | P10: R-101 | Q10: Hybrid | R10: Tue-Thu-Sat | S10: Biology | T10: Anil Sharma | U10: 2024-03-06 | V10: 2024-03-05 | W10: 29689 | X10: 28607 | Y10: 1082 | Z10: 1301 | AA10: Yes | AB10: =RANDBETWEEN(DATE(2025,7,1),DATE(2025,12,31)) -> 45897 | AC10: Partial | AD10: Card | AE10: 4 | AF10: 54 | AG10: 74 | AH10: Needs Improvement | AI10: 90 | AJ10: 56 | AK10: 53 | AL10: Family function | AM10: 94 | AN10: Yes | AO10: 2 | AP10: 5 | AQ10: 2024-04-17 | AR10: 2024-05-15 | AS10: No | AT10: Instagram Ad | AU10: Amit Deshmukh | AV10: Left | AW10: Too far
A11: AU-020 | B11: Ira Joshi | C11: 2006-01-28 | D11: Male | E11: 9898616022 | F11: ira.joshi20@gmail.com | G11: 236, Aundh Pune | H11: Modern College | I11: 67 | J11: 9921755464 | K11: JEE | L11: 3 | M11: Morning | N11: 2024-03-03 | O11: 2024-06-01 | P11: R-109 | Q11: Online | R11: Tue-Thu-Sat | S11: Chemistry | T11: Anil Sharma | U11: 2024-03-12 | V11: 2024-03-10 | W11: 15521 | X11: 15338 | Y11: 183 | Z11: 1968 | AA11: No | AB11: =RANDBETWEEN(DATE(2025,7,1),DATE(2025,12,31)) -> 45994 | AC11: Partial | AD11: Bank Transfer | AE11: 5 | AF11: 81 | AG11: 87 | AH11: Average | AI11: 77 | AJ11: 56 | AK11: 53 | AL11: Sick leave | AM11: 94 | AN11: Yes | AO11: 2 | AP11: 4 | AQ11: 2024-04-25 | AR11: 2024-05-05 | AS11: No | AT11: Website | AU11: Amit Deshmukh | AV11: Left | AW11: Switched institute
A12: AU-047 | B12: Omkar Bhosale | C12: 2005-11-14 | D12: Male | E12: 9886591060 | F12: riya.patil47@gmail.com | G12: 113, Aundh Pune | H12: Vidyanchal School | I12: 76 | J12: 9978630854 | K12: JEE | L12: 6 | M12: Morning | N12: 2024-04-04 | O12: 2024-10-01 | P12: R-111 | Q12: Hybrid | R12: Mon-Wed-Fri | S12: Physics | T12: Vikram Joshi | U12: 2024-02-12 | V12: 2024-02-02 | W12: 47666 | X12: 47504 | Y12: 162 | Z12: 365 | AA12: Yes | AB12: =RANDBETWEEN(DATE(2025,7,1),DATE(2025,12,31)) -> 45953 | AC12: Partial | AD12: Bank Transfer | AE12: 6 | AF12: 73 | AG12: 82 | AH12: Good | AI12: 75 | AJ12: 25 | AK12: 23 | AL12: Family function | AM12: 92 | AN12: Yes | AO12: 4 | AP12: 3 | AQ12: 2024-03-15 | AR12: 2024-04-01 | AS12: No | AT12: Walk-in | AU12: Amit Deshmukh | AV12: Left | AW12: Too far
A13: AU-028 | B13: Rudra Gaikwad | C13: 2006-06-28 | D13: Female | E13: 9814694076 | F13: meera.joshi28@gmail.com | G13: 113, Aundh Pune | H13: Modern College | I13: 84 | J13: 9969698577 | K13: JEE | L13: 12 | M13: Morning | N13: 2024-01-11 | O13: 2025-01-05 | P13: R-102 | Q13: Hybrid | R13: Mon-Wed-Fri | S13: Physics | T13: Vikram Joshi | U13: 2024-02-11 | V13: 2024-02-04 | W13: 31688 | X13: 31188 | Y13: 500 | Z13: 1442 | AA13: No | AB13: =RANDBETWEEN(DATE(2025,7,1),DATE(2025,12,31)) -> 45859 | AC13: Partial | AD13: Cash | AE13: 10 | AF13: 71 | AG13: 91 | AH13: Good | AI13: 80 | AJ13: 24 | AK13: 22 | AM13: 91 | AN13: No | AO13: 3 | AP13: 3 | AQ13: 2024-04-05 | AR13: 2024-05-01 | AS13: Yes | AT13: Instagram Ad | AU13: Amit Deshmukh | AV13: Left | AW13: Too far
A14: AU-043 | B14: Vedant Jadhav | C14: 2005-05-30 | D14: Male | E14: 9827525677 | F14: ayaan.joshi43@gmail.com | G14: 318, Aundh Pune | H14: Spicer Higher Secondary School | I14: 93 | J14: 9973127650 | K14: Foundation 8-10 | L14: 3 | M14: Morning | N14: 2024-03-23 | O14: 2024-06-21 | P14: R-116 | Q14: Hybrid | R14: Mon-Wed-Fri | S14: Physics | T14: Sneha Patil | U14: 2024-03-18 | V14: 2024-03-18 | W14: 33476 | X14: 32565 | Y14: 911 | Z14: 922 | AA14: Yes | AB14: =RANDBETWEEN(DATE(2025,7,1),DATE(2025,12,31)) -> 45883 | AC14: Partial | AD14: Bank Transfer | AE14: 8 | AF14: 50 | AG14: 75 | AH14: Good | AI14: 94 | AJ14: 37 | AK14: 34 | AL14: Sick leave | AM14: 100 | AN14: Yes | AO14: 1 | AP14: 4 | AQ14: 2024-04-19 | AR14: 2024-04-29 | AS14: Yes | AT14: Website | AU14: Rahul Mehta | AV14: Left | AW14: Lost interest
A15: AU-031 | B15: Vivaan Joshi | C15: 2005-04-09 | D15: Male | E15: 9885303785 | F15: vivaan.joshi31@gmail.com | G15: 460, Aundh Pune | H15: City International School | I15: 75 | J15: 9990322781 | K15: Foundation 8-10 | L15: 12 | M15: Evening | N15: 2024-02-15 | O15: 2025-02-09 | P15: R-103 | Q15: Hybrid | R15: Tue-Thu-Sat | S15: Chemistry | T15: Preeti Desai | U15: 2024-02-17 | V15: 2024-02-14 | W15: 42334 | X15: 40547 | Y15: 1787 | Z15: 4132 | AA15: Yes | AB15: =RANDBETWEEN(DATE(2025,7,1),DATE(2025,12,31)) -> 45917 | AC15: Partial | AD15: Bank Transfer | AE15: 7 | AF15: 53 | AG15: 85 | AH15: Average | AI15: 98 | AJ15: 20 | AK15: 18 | AM15: 90 | AN15: No | AO15: 3 | AP15: 5 | AQ15: 2024-03-30 | AR15: 2024-04-26 | AS15: Yes | AT15: Walk-in | AU15: Nidhi Shah | AV15: Left | AW15: Lost interest
A16: AU-006 | B16: Meera Desai | C16: 2006-05-16 | D16: Male | E16: 9820367740 | F16: meera.desai6@gmail.com | G16: 368, Aundh Pune | H16: Spicer Higher Secondary School | I16: 89 | J16: 9952336944 | K16: MHT-CET | L16: 3 | M16: Morning | N16: 2024-03-12 | O16: 2024-06-10 | P16: R-120 | Q16: Offline | R16: Mon-Wed-Fri | S16: Biology | T16: Preeti Desai | U16: 2024-03-06 | V16: 2024-02-28 | W16: 40557 | X16: 40142 | Y16: 415 | Z16: 1522 | AA16: Yes | AB16: =RANDBETWEEN(DATE(2025,7,1),DATE(2025,12,31)) -> 46009 | AC16: Partial | AD16: Cash | AE16: 4 | AF16: 69 | AG16: 93 | AH16: Good | AI16: 61 | AJ16: 52 | AK16: 46 | AL16: Family function | AM16: 88 | AN16: No | AO16: 2 | AP16: 2 | AQ16: 2024-03-27 | AR16: 2024-04-22 | AS16: Yes | AT16: Facebook Ad | AU16: Rahul Mehta | AV16: Active
A17: AU-033 | B17: Kabir Patil | C17: 2005-06-09 | D17: Male | E17: 9845974289 | F17: kabir.patil33@gmail.com | G17: 395, Aundh Pune | H17: Modern College | I17: 93 | J17: 9934055823 | K17: MHT-CET | L17: 3 | M17: Morning | N17: 2024-02-01 | O17: 2024-05-01 | P17: R-112 | Q17: Online | R17: Mon-Wed-Fri | S17: Biology | T17: Vikram Joshi | U17: 2024-02-21 | V17: 2024-02-11 | W17: 21123 | X17: 20086 | Y17: 1037 | Z17: 2663 | AA17: No | AB17: =RANDBETWEEN(DATE(2025,7,1),DATE(2025,12,31)) -> 45952 | AC17: Partial | AD17: UPI | AE17: 2 | AF17: 40 | AG17: 68 | AH17: Good | AI17: 97 | AJ17: 48 | AK17: 42 | AL17: Sick leave | AM17: 87 | AN17: No | AO17: 5 | AP17: 1 | AQ17: 2024-04-05 | AR17: 2024-04-27 | AS17: No | AT17: Instagram Ad | AU17: Nidhi Shah | AV17: Left | AW17: Switched institute
A18: AU-024 | B18: Meera Sharma | C18: 2006-02-20 | D18: Male | E18: 9871747241 | F18: meera.sharma24@gmail.com | G18: 209, Aundh Pune | H18: Modern College | I18: 67 | J18: 9937156335 | K18: MHT-CET | L18: 3 | M18: Morning | N18: 2024-02-19 | O18: 2024-05-19 | P18: R-103 | Q18: Hybrid | R18: Tue-Thu-Sat | S18: Maths | T18: Preeti Desai | U18: 2024-05-10 | V18: 2024-05-09 | W18: 36359 | X18: 34507 | Y18: 1852 | Z18: 2266 | AA18: Yes | AB18: =RANDBETWEEN(DATE(2025,7,1),DATE(2025,12,31)) -> 45892 | AC18: Partial | AD18: Bank Transfer | AE18: 4 | AF18: 48 | AG18: 54 | AH18: Average | AI18: 72 | AJ18: 23 | AK18: 20 | AL18: Sick leave | AM18: 86 | AN18: No | AO18: 1 | AP18: 4 | AQ18: 2024-07-09 | AR18: 2024-08-03 | AS18: Yes | AT18: Instagram Ad | AU18: Nidhi Shah | AV18: Left | AW18: Lost interest
A19: AU-019 | B19: Aarav Desai | C19: 2006-02-07 | D19: Male | E19: 9888818798 | F19: aarav.desai19@gmail.com | G19: 894, Aundh Pune | H19: City International School | I19: 70 | J19: 9941695896 | K19: MHT-CET | L19: 12 | M19: Evening | N19: 2024-03-25 | O19: 2025-03-20 | P19: R-107 | Q19: Offline | R19: Mon-Wed-Fri | S19: Maths | T19: Sneha Patil | U19: 2024-04-27 | V19: 2024-04-26 | W19: 17919 | X19: 17530 | Y19: 389 | Z19: 511 | AA19: Yes | AB19: =RANDBETWEEN(DATE(2025,7,1),DATE(2025,12,31)) -> 45981 | AC19: Partial | AD19: Bank Transfer | AE19: 8 | AF19: 53 | AG19: 86 | AH19: Good | AI19: 82 | AJ19: 28 | AK19: 24 | AL19: Sick leave | AM19: 85 | AN19: Yes | AO19: 2 | AP19: 3 | AQ19: 2024-06-10 | AR19: 2024-07-03 | AS19: No | AT19: Instagram Ad | AU19: Nidhi Shah | AV19: Active
A20: AU-010 | B20: Vivaan Patil | C20: 2006-04-24 | D20: Male | E20: 9852635954 | F20: vivaan.patil10@gmail.com | G20: 189, Aundh Pune | H20: Vidyanchal School | I20: 64 | J20: 9951085984 | K20: Foundation 8-10 | L20: 3 | M20: Evening | N20: 2024-03-16 | O20: 2024-06-14 | P20: R-108 | Q20: Online | R20: Mon-Wed-Fri | S20: English | T20: Vikram Joshi | U20: 2024-05-08 | V20: 2024-05-08 | W20: 43563 | X20: 43281 | Y20: 282 | Z20: 3482 | AA20: Yes | AB20: =RANDBETWEEN(DATE(2025,7,1),DATE(2025,12,31)) -> 45989 | AC20: Partial | AD20: Bank Transfer | AE20: 9 | AF20: 81 | AG20: 91 | AH20: Needs Improvement | AI20: 97 | AJ20: 28 | AK20: 23 | AL20: Family function | AM20: 82 | AN20: No | AO20: 4 | AP20: 4 | AQ20: 2024-06-03 | AR20: 2024-06-14 | AS20: No | AT20: Website | AU20: Nidhi Shah | AV20: Active
A21: AU-002 | B21: manish sisodia | C21: 2005-09-11 | D21: Female | E21: 9856784978 | F21: aarav.kumar2@gmail.com | G21: 445, Aundh Pune | H21: City School | I21: 73 | J21: 9982991179 | K21: Foundation 8-10 | L21: 6 | M21: Morning | N21: 2024-01-15 | O21: 2024-07-13 | P21: R-102 | Q21: Hybrid | R21: Tue-Thu-Sat | S21: Maths | T21: Preeti Desai | U21: 2024-04-18 | V21: 2024-04-12 | W21: 27267 | X21: 25250 | Y21: 2017 | Z21: 3626 | AA21: No | AB21: =RANDBETWEEN(DATE(2025,7,1),DATE(2025,12,31)) -> 45871 | AC21: Partial | AD21: Bank Transfer | AE21: 6 | AF21: 75 | AG21: 77 | AH21: Good | AI21: 94 | AJ21: 21 | AK21: 17 | AL21: Family function | AM21: 80 | AN21: Yes | AO21: 3 | AP21: 4 | AQ21: 2024-05-08 | AR21: 2024-05-27 | AS21: No | AT21: Instagram Ad | AU21: Amit Deshmukh | AV21: Left | AW21: Switched institute
A22: AU-026 | B22: Kabir Joshi | C22: 2005-10-12 | D22: Male | E22: 9839141596 | F22: kabir.joshi26@gmail.com | G22: 681, Aundh Pune | H22: Modern College | I22: 92 | J22: 9967762687 | K22: JEE | L22: 3 | M22: Evening | N22: 2024-02-24 | O22: 2024-05-24 | P22: R-110 | Q22: Online | R22: Tue-Thu-Sat | S22: Chemistry | T22: Preeti Desai | U22: 2024-05-26 | V22: 2024-05-18 | W22: 38039 | X22: 34261 | Y22: 3778 | Z22: 4859 | AA22: No | AB22: =RANDBETWEEN(DATE(2025,7,1),DATE(2025,12,31)) -> 45897 | AC22: Partial | AD22: Cash | AE22: 8 | AF22: 49 | AG22: 68 | AH22: Needs Improvement | AI22: 84 | AJ22: 51 | AK22: 41 | AM22: 80 | AN22: No | AO22: 3 | AP22: 5 | AQ22: 2024-07-21 | AR22: 2024-08-15 | AS22: Yes | AT22: Walk-in | AU22: Rahul Mehta | AV22: Active
A23: AU-003 | B23: Tejas Pawar | C23: 2006-06-27 | D23: Male | E23: 9847094337 | F23: riya.joshi3@gmail.com | G23: 723, Aundh Pune | H23: City School | I23: 61 | J23: 9967496922 | K23: Crash Course | L23: 6 | M23: Afternoon | N23: 2024-01-22 | O23: 2024-07-20 | P23: R-119 | Q23: Offline | R23: Tue-Thu-Sat | S23: Biology | T23: Vikram Joshi | U23: 2024-05-28 | V23: 2024-05-19 | W23: 29239 | X23: 28279 | Y23: 960 | Z23: 1156 | AA23: No | AB23: =RANDBETWEEN(DATE(2025,7,1),DATE(2025,12,31)) -> 45945 | AC23: Partial | AD23: Cash | AE23: 5 | AF23: 63 | AG23: 64 | AH23: Average | AI23: 68 | AJ23: 54 | AK23: 43 | AL23: Sick leave | AM23: 79 | AN23: Yes | AO23: 1 | AP23: 5 | AQ23: 2024-07-11 | AR23: 2024-07-27 | AS23: Yes | AT23: Website | AU23: Nidhi Shah | AV23: Left | AW23: Switched institute
A24: AU-016 | B24: Anaya Joshi | C24: 2006-08-04 | D24: Male | E24: 9883268727 | F24: anaya.joshi16@gmail.com | G24: 245, Aundh Pune | H24: Modern College | I24: 90 | J24: 9982569341 | K24: Foundation 8-10 | L24: 3 | M24: Afternoon | N24: 2024-01-08 | O24: 2024-04-07 | P24: R-110 | Q24: Hybrid | R24: Tue-Thu-Sat | S24: English | T24: Sneha Patil | U24: 2024-04-13 | V24: 2024-04-11 | W24: 30207 | X24: 28610 | Y24: 1597 | Z24: 1889 | AA24: Yes | AB24: =RANDBETWEEN(DATE(2025,7,1),DATE(2025,12,31)) -> 45864 | AC24: Partial | AD24: Bank Transfer | AE24: 7 | AF24: 52 | AG24: 87 | AH24: Average | AI24: 72 | AJ24: 50 | AK24: 39 | AM24: 78 | AN24: Yes | AO24: 4 | AP24: 3 | AQ24: 2024-05-30 | AR24: 2024-06-25 | AS24: Yes | AT24: Website | AU24: Amit Deshmukh | AV24: Left | AW24: Lost interest
A25: AU-038 | B25: Hriday Limaye | C25: 2006-06-21 | D25: Male | E25: 9822514259 | F25: ayaan.sharma38@gmail.com | G25: 217, Aundh Pune | H25: Modern College | I25: 79 | J25: 9960114318 | K25: NEET | L25: 12 | M25: Evening | N25: 2024-01-22 | O25: 2025-01-16 | P25: R-115 | Q25: Offline | R25: Mon-Wed-Fri | S25: Maths | T25: Vikram Joshi | U25: 2024-05-15 | V25: 2024-05-09 | W25: 45733 | X25: 41468 | Y25: 4265 | Z25: 4465 | AA25: Yes | AB25: =RANDBETWEEN(DATE(2025,7,1),DATE(2025,12,31)) -> 45896 | AC25: Partial | AD25: Bank Transfer | AE25: 5 | AF25: 51 | AG25: 58 | AH25: Average | AI25: 65 | AJ25: 56 | AK25: 44 | AM25: 78 | AN25: No | AO25: 1 | AP25: 3 | AQ25: 2024-07-13 | AR25: 2024-07-25 | AS25: No | AT25: Website | AU25: Nidhi Shah | AV25: Active
A26: AU-008 | B26: Meera Joshi | C26: 2006-06-23 | D26: Female | E26: 9822355416 | F26: meera.joshi8@gmail.com | G26: 589, Aundh Pune | H26: Vidyanchal School | I26: 88 | J26: 9995712675 | K26: Crash Course | L26: 3 | M26: Afternoon | N26: 2024-03-22 | O26: 2024-06-20 | P26: R-105 | Q26: Online | R26: Tue-Thu-Sat | S26: Physics | T26: Sneha Patil | U26: 2024-03-15 | V26: 2024-03-14 | W26: 40970 | X26: 39997 | Y26: 973 | Z26: 2197 | AA26: No | AB26: =RANDBETWEEN(DATE(2025,7,1),DATE(2025,12,31)) -> 45945 | AC26: Partial | AD26: Bank Transfer | AE26: 6 | AF26: 90 | AG26: 99 | AH26: Average | AI26: 72 | AJ26: 33 | AK26: 25 | AL26: Family function | AM26: 75 | AN26: Yes | AO26: 3 | AP26: 5 | AQ26: 2024-04-08 | AR26: 2024-04-21 | AS26: No | AT26: Referral | AU26: Rahul Mehta | AV26: Active
A27: AU-009 | B27: Aryan Apte | C27: 2006-05-21 | D27: Male | E27: 9888752606 | F27: aarav.kumar9@gmail.com | G27: 276, Aundh Pune | H27: City International School | I27: 73 | J27: 9967525295 | K27: Foundation 8-10 | L27: 12 | M27: Afternoon | N27: 2024-03-04 | O27: 2025-02-27 | P27: R-105 | Q27: Online | R27: Mon-Wed-Fri | S27: Chemistry | T27: Vikram Joshi | U27: 2024-03-06 | V27: 2024-03-01 | W27: 21161 | X27: 19825 | Y27: 1336 | Z27: 3988 | AA27: No | AB27: =RANDBETWEEN(DATE(2025,7,1),DATE(2025,12,31)) -> 45993 | AC27: Partial | AD27: UPI | AE27: 8 | AF27: 68 | AG27: 83 | AH27: Good | AI27: 99 | AJ27: 56 | AK27: 41 | AM27: 73 | AN27: No | AO27: 2 | AP27: 5 | AQ27: 2024-04-22 | AR27: 2024-05-21 | AS27: Yes | AT27: Website | AU27: Amit Deshmukh | AV27: Active
A28: AU-027 | B28: Siya Desai | C28: 2006-04-22 | D28: Male | E28: 9816439415 | F28: siya.desai27@gmail.com | G28: 969, Aundh Pune | H28: Modern College | I28: 78 | J28: 9925998150 | K28: Crash Course | L28: 6 | M28: Afternoon | N28: 2024-02-02 | O28: 2024-07-31 | P28: R-114 | Q28: Online | R28: Tue-Thu-Sat | S28: Chemistry | T28: Sneha Patil | U28: 2024-03-16 | V28: 2024-03-14 | W28: 45981 | X28: 45836 | Y28: 145 | Z28: 3623 | AA28: Yes | AB28: =RANDBETWEEN(DATE(2025,7,1),DATE(2025,12,31)) -> 45912 | AC28: Partial | AD28: Cash | AE28: 8 | AF28: 74 | AG28: 94 | AH28: Needs Improvement | AI28: 63 | AJ28: 34 | AK28: 25 | AM28: 73 | AN28: No | AO28: 4 | AP28: 5 | AQ28: 2024-05-05 | AR28: 2024-06-04 | AS28: Yes | AT28: Facebook Ad | AU28: Nidhi Shah | AV28: Left | AW28: Switched institute
A29: AU-035 | B29: Ira Sharma | C29: 2006-03-25 | D29: Male | E29: 9861555077 | F29: ira.sharma35@gmail.com | G29: 102, Aundh Pune | H29: D.A.V. Public School | I29: 94 | J29: 9954095883 | K29: MHT-CET | L29: 3 | M29: Afternoon | N29: 2024-02-22 | O29: 2024-05-22 | P29: R-102 | Q29: Hybrid | R29: Mon-Wed-Fri | S29: Physics | T29: Anil Sharma | U29: 2024-04-11 | V29: 2024-04-09 | W29: 29344 | X29: 27076 | Y29: 2268 | Z29: 4754 | AA29: No | AB29: =RANDBETWEEN(DATE(2025,7,1),DATE(2025,12,31)) -> 45947 | AC29: Partial | AD29: Cash | AE29: 8 | AF29: 48 | AG29: 96 | AH29: Needs Improvement | AI29: 100 | AJ29: 60 | AK29: 44 | AL29: Sick leave | AM29: 73 | AN29: Yes | AO29: 4 | AP29: 2 | AQ29: 2024-05-20 | AR29: 2024-06-07 | AS29: Yes | AT29: Website | AU29: Rahul Mehta | AV29: Active
A30: AU-012 | B30: Kunal Godbole | C30: 2006-01-14 | D30: Female | E30: 9861968735 | F30: ayaan.sharma12@gmail.com | G30: 336, Aundh Pune | H30: City School | I30: 63 | J30: 9939854108 | K30: JEE | L30: 12 | M30: Evening | N30: 2024-02-27 | O30: 2025-02-21 | P30: R-112 | Q30: Online | R30: Mon-Wed-Fri | S30: Biology | T30: Vikram Joshi | U30: 2024-02-06 | V30: 2024-02-03 | W30: 47685 | X30: 47563 | Y30: 122 | Z30: 663 | AA30: No | AB30: =RANDBETWEEN(DATE(2025,7,1),DATE(2025,12,31)) -> 45844 | AC30: Partial | AD30: UPI | AE30: 9 | AF30: 76 | AG30: 78 | AH30: Needs Improvement | AI30: 98 | AJ30: 59 | AK30: 43 | AL30: Family function | AM30: 72 | AN30: No | AO30: 4 | AP30: 2 | AQ30: 2024-03-03 | AR30: 2024-03-13 | AS30: Yes | AT30: Website | AU30: Nidhi Shah | AV30: Left | AW30: Switched institute
A31: AU-013 | B31: Meera Patil | C31: 2005-12-01 | D31: Male | E31: 9817700186 | F31: meera.patil13@gmail.com | G31: 589, Aundh Pune | H31: D.A.V. Public School | I31: 71 | J31: 9931778745 | K31: MHT-CET | L31: 12 | M31: Morning | N31: 2024-01-24 | O31: 2025-01-18 | P31: R-112 | Q31: Online | R31: Mon-Wed-Fri | S31: Maths | T31: Ravi Kumar | U31: 2024-03-04 | V31: 2024-02-25 | W31: 19992 | X31: 16844 | Y31: 3148 | Z31: 3877 | AA31: Yes | AB31: =RANDBETWEEN(DATE(2025,7,1),DATE(2025,12,31)) -> 45885 | AC31: Partial | AD31: Bank Transfer | AE31: 6 | AF31: 82 | AG31: 99 | AH31: Needs Improvement | AI31: 73 | AJ31: 37 | AK31: 27 | AL31: Sick leave | AM31: 72 | AN31: Yes | AO31: 4 | AP31: 3 | AQ31: 2024-04-30 | AR31: 2024-05-28 | AS31: No | AT31: Instagram Ad | AU31: Nidhi Shah | AV31: Left | AW31: Too far
A32: AU-042 | B32: Ira Patil | C32: 2005-01-20 | D32: Male | E32: 9829100757 | F32: ira.patil42@gmail.com | G32: 450, Aundh Pune | H32: Spicer Higher Secondary School | I32: 76 | J32: 9993814827 | K32: Crash Course | L32: 3 | M32: Evening | N32: 2024-03-16 | O32: 2024-06-14 | P32: R-118 | Q32: Offline | R32: Mon-Wed-Fri | S32: Physics | T32: Vikram Joshi | U32: 2024-05-27 | V32: 2024-05-21 | W32: 41685 | X32: 41195 | Y32: 490 | Z32: 4889 | AA32: No | AB32: =RANDBETWEEN(DATE(2025,7,1),DATE(2025,12,31)) -> 45872 | AC32: Partial | AD32: UPI | AE32: 1 | AF32: 62 | AG32: 98 | AH32: Average | AI32: 67 | AJ32: 55 | AK32: 39 | AL32: Sick leave | AM32: 70 | AN32: No | AO32: 2 | AP32: 2 | AQ32: 2024-07-09 | AR32: 2024-08-08 | AS32: No | AT32: Instagram Ad | AU32: Nidhi Shah | AV32: Left | AW32: Switched institute
A33: AU-011 | B33: Riya Patil | C33: 2006-04-17 | D33: Male | E33: 9887840907 | F33: riya.patil11@gmail.com | G33: 792, Aundh Pune | H33: Spicer Higher Secondary School | I33: 66 | J33: 9932763392 | K33: JEE | L33: 6 | M33: Morning | N33: 2024-04-07 | O33: 2024-10-04 | P33: R-110 | Q33: Online | R33: Mon-Wed-Fri | S33: Physics | T33: Preeti Desai | U33: 2024-02-15 | V33: 2024-02-08 | W33: 20936 | X33: 18272 | Y33: 2664 | Z33: 2870 | AA33: No | AB33: =RANDBETWEEN(DATE(2025,7,1),DATE(2025,12,31)) -> 45860 | AC33: Partial | AD33: UPI | AE33: 10 | AF33: 49 | AG33: 76 | AH33: Average | AI33: 96 | AJ33: 38 | AK33: 25 | AM33: 65 | AN33: No | AO33: 1 | AP33: 5 | AQ33: 2024-03-10 | AR33: 2024-03-31 | AS33: Yes | AT33: Website | AU33: Amit Deshmukh | AV33: Left | AW33: Lost interest
A34: AU-032 | B34: Pranav Gadgil | C34: 2005-12-18 | D34: Male | E34: 9856821801 | F34: riya.joshi32@gmail.com | G34: 130, Aundh Pune | H34: Modern College | I34: 80 | J34: 9967122501 | K34: Foundation 8-10 | L34: 3 | M34: Morning | N34: 2024-04-04 | O34: 2024-07-03 | P34: R-117 | Q34: Offline | R34: Mon-Wed-Fri | S34: Maths | T34: Anil Sharma | U34: 2024-02-11 | V34: 2024-02-11 | W34: 47410 | X34: 46718 | Y34: 692 | Z34: 2379 | AA34: Yes | AB34: =RANDBETWEEN(DATE(2025,7,1),DATE(2025,12,31)) -> 45948 | AC34: Partial | AD34: Cash | AE34: 10 | AF34: 76 | AG34: 77 | AH34: Good | AI34: 88 | AJ34: 36 | AK34: 22 | AM34: 61 | AN34: Yes | AO34: 3 | AP34: 2 | AQ34: 2024-04-02 | AR34: 2024-05-02 | AS34: No | AT34: Referral | AU34: Amit Deshmukh | AV34: Left | AW34: Too far
A35: AU-022 | B35: Saurabh Ranade | C35: 2005-01-03 | D35: Male | E35: 9859987035 | F35: ayaan.kumar22@gmail.com | G35: 625, Aundh Pune | H35: Modern College | I35: 65 | J35: 9918907790 | K35: Foundation 8-10 | L35: 12 | M35: Morning | N35: 2024-02-25 | O35: 2025-02-19 | P35: R-106 | Q35: Online | R35: Mon-Wed-Fri | S35: Biology | T35: Anil Sharma | U35: 2024-03-13 | V35: 2024-03-11 | W35: 29550 | X35: 28618 | Y35: 932 | Z35: 3302 | AA35: Yes | AB35: =RANDBETWEEN(DATE(2025,7,1),DATE(2025,12,31)) -> 45942 | AC35: Partial | AD35: Bank Transfer | AE35: 8 | AF35: 45 | AG35: 54 | AH35: Good | AI35: 78 | AJ35: 38 | AK35: 23 | AL35: Family function | AM35: 60 | AN35: Yes | AO35: 3 | AP35: 1 | AQ35: 2024-05-10 | AR35: 2024-06-09 | AS35: No | AT35: Referral | AU35: Amit Deshmukh | AV35: Left | AW35: Switched institute
A36: AU-045 | B36: Riya Joshi | C36: 2005-08-15 | D36: Male | E36: 9837045769 | F36: riya.joshi45@gmail.com | G36: 968, Aundh Pune | H36: Modern College | I36: 63 | J36: 9990130107 | K36: Foundation 8-10 | L36: 6 | M36: Afternoon | N36: 2024-01-30 | O36: 2024-07-28 | P36: R-103 | Q36: Hybrid | R36: Tue-Thu-Sat | S36: Physics | T36: Ravi Kumar | U36: 2024-02-18 | V36: 2024-02-18 | W36: 19785 | X36: 18254 | Y36: 1531 | Z36: 2562 | AA36: No | AB36: =RANDBETWEEN(DATE(2025,7,1),DATE(2025,12,31)) -> 45862 | AC36: Partial | AD36: Card | AE36: 2 | AF36: 45 | AG36: 65 | AH36: Needs Improvement | AI36: 73 | AJ36: 37 | AK36: 22 | AL36: Sick leave | AM36: 59 | AN36: Yes | AO36: 4 | AP36: 1 | AQ36: 2024-03-14 | AR36: 2024-03-30 | AS36: Yes | AT36: Website | AU36: Rahul Mehta | AV36: Active
A37: AU-021 | B37: Aarav Kumar | C37: 2005-07-20 | D37: Female | E37: 9869774216 | F37: aarav.kumar21@gmail.com | G37: 513, Aundh Pune | H37: Spicer Higher Secondary School | I37: 65 | J37: 9919070144 | K37: NEET | L37: 3 | M37: Afternoon | N37: 2024-02-21 | O37: 2024-05-21 | P37: R-107 | Q37: Online | R37: Tue-Thu-Sat | S37: Biology | T37: Anil Sharma | U37: 2024-03-06 | V37: 2024-03-02 | W37: 32976 | X37: 32180 | Y37: 796 | Z37: 2727 | AA37: Yes | AB37: =RANDBETWEEN(DATE(2025,7,1),DATE(2025,12,31)) -> 45903 | AC37: Partial | AD37: Cash | AE37: 5 | AF37: 55 | AG37: 55 | AH37: Good | AI37: 63 | AJ37: 54 | AK37: 31 | AL37: Family function | AM37: 57 | AN37: No | AO37: 4 | AP37: 2 | AQ37: 2024-05-04 | AR37: 2024-06-03 | AS37: Yes | AT37: Instagram Ad | AU37: Rahul Mehta | AV37: Active
A38: AU-034 | B38: Ayaan Joshi | C38: 2005-08-05 | D38: Female | E38: 9858291899 | F38: ayaan.joshi34@gmail.com | G38: 776, Aundh Pune | H38: Vidyanchal School | I38: 69 | J38: 9924142404 | K38: Crash Course | L38: 12 | M38: Evening | N38: 2024-02-13 | O38: 2025-02-07 | P38: R-111 | Q38: Offline | R38: Tue-Thu-Sat | S38: Physics | T38: Vikram Joshi | U38: 2024-05-02 | V38: 2024-04-22 | W38: 28619 | X38: 25381 | Y38: 3238 | Z38: 3240 | AA38: No | AB38: =RANDBETWEEN(DATE(2025,7,1),DATE(2025,12,31)) -> 45963 | AC38: Partial | AD38: Bank Transfer | AE38: 6 | AF38: 85 | AG38: 88 | AH38: Needs Improvement | AI38: 83 | AJ38: 26 | AK38: 15 | AL38: Family function | AM38: 57 | AN38: No | AO38: 5 | AP38: 4 | AQ38: 2024-06-01 | AR38: 2024-07-01 | AS38: Yes | AT38: Walk-in | AU38: Rahul Mehta | AV38: Left | AW38: Switched institute
A39: AU-050 | B39: Aarav Sharma | C39: 2006-05-20 | D39: Male | E39: 9892575113 | F39: aarav.sharma50@gmail.com | G39: 160, Aundh Pune | H39: D.A.V. Public School | I39: 83 | J39: 9949987246 | K39: JEE | L39: 3 | M39: Evening | N39: 2024-02-06 | O39: 2024-05-06 | P39: R-108 | Q39: Offline | R39: Tue-Thu-Sat | S39: Chemistry | T39: Ravi Kumar | U39: 2024-03-18 | V39: 2024-03-14 | W39: 38119 | X39: 38089 | Y39: 30 | Z39: 878 | AA39: Yes | AB39: =RANDBETWEEN(DATE(2025,7,1),DATE(2025,12,31)) -> 45959 | AC39: Partial | AD39: Card | AE39: 5 | AF39: 49 | AG39: 86 | AH39: Good | AI39: 62 | AJ39: 33 | AK39: 19 | AL39: Family function | AM39: 57 | AN39: No | AO39: 4 | AP39: 1 | AQ39: 2024-04-26 | AR39: 2024-05-24 | AS39: No | AT39: Instagram Ad | AU39: Amit Deshmukh | AV39: Active
A40: AU-039 | B40: Anaya Sharma | C40: 2005-06-08 | D40: Female | E40: 9832258449 | F40: anaya.sharma39@gmail.com | G40: 746, Aundh Pune | H40: City International School | I40: 82 | J40: 9990085925 | K40: Foundation 8-10 | L40: 12 | M40: Evening | N40: 2024-01-12 | O40: 2025-01-06 | P40: R-103 | Q40: Online | R40: Tue-Thu-Sat | S40: Physics | T40: Sneha Patil | U40: 2024-03-01 | V40: 2024-02-26 | W40: 39856 | X40: 38099 | Y40: 1757 | Z40: 4355 | AA40: Yes | AB40: =RANDBETWEEN(DATE(2025,7,1),DATE(2025,12,31)) -> 45958 | AC40: Partial | AD40: Bank Transfer | AE40: 3 | AF40: 54 | AG40: 62 | AH40: Average | AI40: 80 | AJ40: 35 | AK40: 19 | AL40: Sick leave | AM40: 54 | AN40: Yes | AO40: 5 | AP40: 3 | AQ40: 2024-04-22 | AR40: 2024-05-20 | AS40: No | AT40: Referral | AU40: Nidhi Shah | AV40: Left | AW40: Lost interest
A41: AU-025 | B41: Ira Kumar | C41: 2006-05-06 | D41: Female | E41: 9850568987 | F41: ira.kumar25@gmail.com | G41: 628, Aundh Pune | H41: Vidyanchal School | I41: 75 | J41: 9972283041 | K41: Foundation 8-10 | L41: 3 | M41: Afternoon | N41: 2024-03-23 | O41: 2024-06-21 | P41: R-105 | Q41: Offline | R41: Tue-Thu-Sat | S41: Chemistry | T41: Ravi Kumar | U41: 2024-02-08 | V41: 2024-02-03 | W41: 27463 | X41: 25008 | Y41: 2455 | Z41: 2660 | AA41: Yes | AB41: =RANDBETWEEN(DATE(2025,7,1),DATE(2025,12,31)) -> 45921 | AC41: Partial | AD41: Card | AE41: 9 | AF41: 71 | AG41: 98 | AH41: Good | AI41: 97 | AJ41: 44 | AK41: 23 | AM41: 52 | AN41: Yes | AO41: 1 | AP41: 1 | AQ41: 2024-02-28 | AR41: 2024-03-13 | AS41: Yes | AT41: Website | AU41: Rahul Mehta | AV41: Active
A42: AU-037 | B42: Ayaan Sharma | C42: 2005-01-08 | D42: Male | E42: 9846464786 | F42: ayaan.sharma37@gmail.com | G42: 471, Aundh Pune | H42: Modern College | I42: 69 | J42: 9970462439 | K42: NEET | L42: 3 | M42: Morning | N42: 2024-02-25 | O42: 2024-05-25 | P42: R-106 | Q42: Offline | R42: Mon-Wed-Fri | S42: Physics | T42: Ravi Kumar | U42: 2024-04-25 | V42: 2024-04-15 | W42: 16996 | X42: 16468 | Y42: 528 | Z42: 3946 | AA42: No | AB42: =RANDBETWEEN(DATE(2025,7,1),DATE(2025,12,31)) -> 45943 | AC42: Partial | AD42: Cash | AE42: 8 | AF42: 73 | AG42: 91 | AH42: Needs Improvement | AI42: 78 | AJ42: 42 | AK42: 21 | AL42: Sick leave | AM42: 50 | AN42: Yes | AO42: 1 | AP42: 3 | AQ42: 2024-05-26 | AR42: 2024-06-08 | AS42: Yes | AT42: Website | AU42: Nidhi Shah | AV42: Active
A43: AU-040 | B43: Anaya Kumar | C43: 2005-04-11 | D43: Male | E43: 9837559454 | F43: anaya.kumar40@gmail.com | G43: 169, Aundh Pune | H43: City School | I43: 60 | J43: 9945760111 | K43: NEET | L43: 3 | M43: Evening | N43: 2024-03-04 | O43: 2024-06-02 | P43: R-114 | Q43: Hybrid | R43: Mon-Wed-Fri | S43: Biology | T43: Vikram Joshi | U43: 2024-04-15 | V43: 2024-04-06 | W43: 31109 | X43: 29623 | Y43: 1486 | Z43: 2133 | AA43: No | AB43: =RANDBETWEEN(DATE(2025,7,1),DATE(2025,12,31)) -> 45906 | AC43: Partial | AD43: Bank Transfer | AE43: 8 | AF43: 64 | AG43: 84 | AH43: Needs Improvement | AI43: 93 | AJ43: 58 | AK43: 27 | AL43: Family function | AM43: 46 | AN43: Yes | AO43: 1 | AP43: 2 | AQ43: 2024-06-07 | AR43: 2024-06-20 | AS43: Yes | AT43: Instagram Ad | AU43: Amit Deshmukh | AV43: Active
A44: AU-004 | B44: Reyansh Joshi | C44: 2006-08-11 | D44: Male | E44: 9828538761 | F44: reyansh.joshi4@gmail.com | G44: 815, Aundh Pune | H44: Modern College | I44: 95 | J44: 9969518889 | K44: Crash Course | L44: 12 | M44: Morning | N44: 2024-03-25 | O44: 2025-03-20 | P44: R-109 | Q44: Offline | R44: Mon-Wed-Fri | S44: Physics | T44: Anil Sharma | U44: 2024-05-26 | V44: 2024-05-21 | W44: 18800 | X44: 15778 | Y44: 3022 | Z44: 4161 | AA44: No | AB44: =RANDBETWEEN(DATE(2025,7,1),DATE(2025,12,31)) -> 46003 | AC44: Partial | AD44: Card | AE44: 5 | AF44: 73 | AG44: 88 | AH44: Good | AI44: 75 | AJ44: 58 | AK44: 26 | AL44: Family function | AM44: 44 | AN44: Yes | AO44: 4 | AP44: 3 | AQ44: 2024-06-28 | AR44: 2024-07-23 | AS44: No | AT44: Referral | AU44: Amit Deshmukh | AV44: Active
A45: AU-023 | B45: Ayaan Kumar | C45: 2005-08-20 | D45: Female | E45: 9851052997 | F45: ayaan.kumar23@gmail.com | G45: 540, Aundh Pune | H45: Modern College | I45: 68 | J45: 9989857993 | K45: NEET | L45: 6 | M45: Evening | N45: 2024-03-23 | O45: 2024-09-19 | P45: R-117 | Q45: Offline | R45: Tue-Thu-Sat | S45: Chemistry | T45: Preeti Desai | U45: 2024-03-29 | V45: 2024-03-21 | W45: 29689 | X45: 29635 | Y45: 54 | Z45: 3842 | AA45: No | AB45: =RANDBETWEEN(DATE(2025,7,1),DATE(2025,12,31)) -> 45914 | AC45: Partial | AD45: Cash | AE45: 6 | AF45: 82 | AG45: 94 | AH45: Needs Improvement | AI45: 67 | AJ45: 60 | AK45: 26 | AL45: Sick leave | AM45: 43 | AN45: No | AO45: 3 | AP45: 2 | AQ45: 2024-05-10 | AR45: 2024-06-02 | AS45: Yes | AT45: Referral | AU45: Rahul Mehta | AV45: Left | AW45: Lost interest
A46: AU-036 | B46: Samarth Gokhale | C46: 2005-05-06 | D46: Male | E46: 9898471683 | F46: reyansh.desai36@gmail.com | G46: 555, Aundh Pune | H46: City School | I46: 91 | J46: 9928312643 | K46: Crash Course | L46: 3 | M46: Afternoon | N46: 2024-03-03 | O46: 2024-06-01 | P46: R-119 | Q46: Online | R46: Mon-Wed-Fri | S46: Biology | T46: Sneha Patil | U46: 2024-05-15 | V46: 2024-05-09 | W46: 45585 | X46: 44073 | Y46: 1512 | Z46: 3674 | AA46: No | AB46: =RANDBETWEEN(DATE(2025,7,1),DATE(2025,12,31)) -> 45870 | AC46: Partial | AD46: Card | AE46: 6 | AF46: 46 | AG46: 49 | AH46: Average | AI46: 100 | AJ46: 46 | AK46: 20 | AL46: Family function | AM46: 43 | AN46: No | AO46: 2 | AP46: 2 | AQ46: 2024-06-19 | AR46: 2024-07-08 | AS46: Yes | AT46: Instagram Ad | AU46: Nidhi Shah | AV46: Active
A47: AU-029 | B47: Madhav Bapat | C47: 2006-08-02 | D47: Male | E47: 9863730140 | F47: anaya.patil29@gmail.com | G47: 207, Aundh Pune | H47: D.A.V. Public School | I47: 85 | J47: 9981383868 | K47: MHT-CET | L47: 12 | M47: Afternoon | N47: 2024-01-22 | O47: 2025-01-16 | P47: R-114 | Q47: Offline | R47: Mon-Wed-Fri | S47: Chemistry | T47: Sneha Patil | U47: 2024-02-17 | V47: 2024-02-15 | W47: 37907 | X47: 37497 | Y47: 410 | Z47: 3915 | AA47: No | AB47: =RANDBETWEEN(DATE(2025,7,1),DATE(2025,12,31)) -> 45983 | AC47: Partial | AD47: Bank Transfer | AE47: 5 | AF47: 58 | AG47: 74 | AH47: Average | AI47: 84 | AJ47: 38 | AK47: 16 | AL47: Sick leave | AM47: 42 | AN47: No | AO47: 5 | AP47: 2 | AQ47: 2024-04-11 | AR47: 2024-04-23 | AS47: No | AT47: Facebook Ad | AU47: Rahul Mehta | AV47: Active
A48: AU-046 | B48: Anaya Patil | C48: 2005-08-03 | D48: Male | E48: 9888106798 | F48: anaya.patil46@gmail.com | G48: 269, Aundh Pune | H48: Vidyanchal School | I48: 94 | J48: 9919781136 | K48: NEET | L48: 12 | M48: Morning | N48: 2024-03-01 | O48: 2025-02-24 | P48: R-114 | Q48: Offline | R48: Tue-Thu-Sat | S48: Chemistry | T48: Sneha Patil | U48: 2024-02-11 | V48: 2024-02-02 | W48: 36727 | X48: 35337 | Y48: 1390 | Z48: 4276 | AA48: Yes | AB48: =RANDBETWEEN(DATE(2025,7,1),DATE(2025,12,31)) -> 45980 | AC48: Partial | AD48: Cash | AE48: 3 | AF48: 71 | AG48: 88 | AH48: Average | AI48: 71 | AJ48: 44 | AK48: 18 | AL48: Family function | AM48: 40 | AN48: Yes | AO48: 2 | AP48: 1 | AQ48: 2024-04-11 | AR48: 2024-04-25 | AS48: No | AT48: Facebook Ad | AU48: Rahul Mehta | AV48: Active
A49: AU-005 | B49: Aaditya Kar | C49: 2005-05-12 | D49: Female | E49: 9817741407 | F49: anaya.desai5@gmail.com | G49: 559, Aundh Pune | H49: D.A.V. Public School | I49: 95 | J49: 9955609370 | K49: Foundation 8-10 | L49: 3 | M49: Evening | N49: 2024-02-27 | O49: 2024-05-27 | P49: R-119 | Q49: Hybrid | R49: Mon-Wed-Fri | S49: Physics | T49: Vikram Joshi | U49: 2024-03-06 | V49: 2024-03-06 | W49: 49463 | X49: 49078 | Y49: 385 | Z49: 1250 | AA49: No | AB49: =RANDBETWEEN(DATE(2025,7,1),DATE(2025,12,31)) -> 45912 | AC49: Partial | AD49: Cash | AE49: 5 | AF49: 86 | AG49: 96 | AH49: Average | AI49: 80 | AJ49: 47 | AK49: 17 | AL49: Sick leave | AM49: 36 | AN49: No | AO49: 4 | AP49: 4 | AQ49: 2024-04-30 | AR49: 2024-05-22 | AS49: Yes | AT49: Website | AU49: Rahul Mehta | AV49: Left | AW49: Lost interest
A50: AU-041 | B50: Anaya Desai | C50: 2005-02-27 | D50: Male | E50: 9858081282 | F50: anaya.desai41@gmail.com | G50: 300, Aundh Pune | H50: City School | I50: 84 | J50: 9921181487 | K50: JEE | L50: 3 | M50: Evening | N50: 2024-03-18 | O50: 2024-06-16 | P50: R-116 | Q50: Hybrid | R50: Tue-Thu-Sat | S50: Chemistry | T50: Preeti Desai | U50: 2024-03-28 | V50: 2024-03-18 | W50: 35441 | X50: 34902 | Y50: 539 | Z50: 3148 | AA50: No | AB50: =RANDBETWEEN(DATE(2025,7,1),DATE(2025,12,31)) -> 45967 | AC50: Partial | AD50: Bank Transfer | AE50: 5 | AF50: 62 | AG50: 71 | AH50: Needs Improvement | AI50: 91 | AJ50: 56 | AK50: 18 | AL50: Sick leave | AM50: 32 | AN50: Yes | AO50: 5 | AP50: 4 | AQ50: 2024-04-20 | AR50: 2024-05-08 | AS50: No | AT50: Walk-in | AU50: Nidhi Shah | AV50: Active
A51: AU-049 | B51: Reyansh Desai | C51: 2005-02-08 | D51: Male | E51: 9824864102 | F51: reyansh.desai49@gmail.com | G51: 228, Aundh Pune | H51: Modern College | I51: 61 | J51: 9996736981 | K51: MHT-CET | L51: 3 | M51: Morning | N51: 2024-02-24 | O51: 2024-05-24 | P51: R-103 | Q51: Offline | R51: Mon-Wed-Fri | S51: Chemistry | T51: Preeti Desai | U51: 2024-04-09 | V51: 2024-04-05 | W51: 22307 | X51: 21738 | Y51: 569 | Z51: 659 | AA51: No | AB51: =RANDBETWEEN(DATE(2025,7,1),DATE(2025,12,31)) -> 45858 | AC51: Partial | AD51: UPI | AE51: 10 | AF51: 47 | AG51: 51 | AH51: Average | AI51: 61 | AJ51: 57 | AK51: 16 | AM51: 28 | AN51: No | AO51: 3 | AP51: 2 | AQ51: 2024-05-02 | AR51: 2024-05-24 | AS51: No | AT51: Referral | AU51: Nidhi Shah | AV51: Left | AW51: Lost interest

Sheet Master Sheet
A1: Student ID | B1: Student Name | C1: Date of Birth | D1: Gender | E1: Parent Contact Number | F1: Student Email | G1: Address | H1: School/College Name | I1: Previous Academic Performance (%) | J1: Emergency Contact | K1: Course | L1: Course Duration (Months) | M1: Batch | N1: Batch Start Date | O1: Batch End Date | P1: Classroom/Room No. | Q1: Mode | R1: Session Days | S1: Subject | T1: Teacher | U1: Enrollment Date | V1: Registration Date | W1: Total Course Fees | X1: Amount Paid | Y1: Pending Amount | Z1: Discount Given | AA1: Installment Plan | AB1: Next Payment Due Date | AC1: Payment Status | AD1: Payment Method | AE1: Number of Tests Taken | AF1: Average Test Score | AG1: Top Test Score | AH1: Progress Comments | AI1: Homework Completion Rate (%) | AJ1: Total Classes Conducted | AK1: Classes Attended | AL1: Leave Notes/Remarks | AM1: Attendance (%) | AN1: Attendance Alerts Sent | AO1: Parent Feedback | AP1: Student Feedback | AQ1: Last Feedback Date | AR1: Follow-up Date | AS1: WhatsApp Opt-in | AT1: Lead Source | AU1: Counselor/Admission Handled By | AV1: Dropout Status | AW1: Reason for Leaving | AX1: Branch
A2: AU-007 | B2: Aarav Patil | C2: 2006-05-20 | D2: Female | E2: 9827095765 | F2: ira.sharma7@gmail.com | G2: atul apts, aundh, pune | H2: City International School | I2: 82 | J2: 9953297386 | K2: Foundation 8-10 | L2: 6 | M2: Evening | N2: 2024-01-28 | O2: 2024-07-26 | P2: R-111 | Q2: Offline | R2: Tue-Thu-Sat | S2: Maths | T2: Preeti Desai | U2: 2024-05-20 | V2: 2024-05-15 | W2: 43018 | X2: 39256 | Y2: 3762 | Z2: 4189 | AA2: No | AB2: =RANDBETWEEN(DATE(2025,7,1),DATE(2025,12,31)) -> 45872 | AC2: Partial | AD2: UPI | AE2: 5 | AF2: 41 | AG2: 77 | AH2: Average | AI2: 81 | AJ2: 24 | AK2: 24 | AL2: Family function | AM2: 100 | AN2: Yes | AO2: 3 | AP2: 5 | AQ2: 2024-07-11 | AR2: 2024-08-09 | AS2: No | AT2: Facebook Ad | AU2: Nidhi Shah | AV2: Left | AW2: Switched institute | AX2: =IF(LEFT(A2,2)="AU","Aundh",IF(LEFT(A2,2)="KO","Kondhwa","Sinhgad Road")) -> Aundh
A3: AU-048 | B3: Atharva Deshmukh | C3: 2006-07-29 | D3: Female | E3: 9895313505 | F3: aarav.kumar48@gmail.com | G3: 937, Aundh Pune | H3: Modern College | I3: 87 | J3: 9912189875 | K3: Foundation 8-10 | L3: 3 | M3: Afternoon | N3: 2024-01-15 | O3: 2024-04-14 | P3: R-118 | Q3: Offline | R3: Mon-Wed-Fri | S3: Physics | T3: Ravi Kumar | U3: 2024-04-01 | V3: 2024-03-25 | W3: 20086 | X3: 19800 | Y3: 286 | Z3: 1952 | AA3: No | AB3: =RANDBETWEEN(DATE(2025,7,1),DATE(2025,12,31)) -> 46011 | AC3: Partial | AD3: Bank Transfer | AE3: 9 | AF3: 67 | AG3: 86 | AH3: Good | AI3: 67 | AJ3: 22 | AK3: 22 | AM3: 100 | AN3: No | AO3: 5 | AP3: 4 | AQ3: 2024-04-23 | AR3: 2024-05-06 | AS3: No | AT3: Instagram Ad | AU3: Amit Deshmukh | AV3: Left | AW3: Too far | AX3: =IF(LEFT(A3,2)="AU","Aundh",IF(LEFT(A3,2)="KO","Kondhwa","Sinhgad Road")) -> Aundh
A4: AU-015 | B4: aryan patil | C4: 2006-07-12 | D4: Female | E4: 9827032133 | F4: aarav.patil15@gmail.com | G4: 694, Aundh Pune | H4: Vidyanchal School | I4: 79 | J4: 9919617248 | K4: NEET | L4: 6 | M4: Morning | N4: 2024-01-23 | O4: 2024-07-21 | P4: R-107 | Q4: Hybrid | R4: Mon-Wed-Fri | S4: Chemistry | T4: Sneha Patil | U4: 2024-02-08 | V4: 2024-02-06 | W4: 33714 | X4: 33476 | Y4: 238 | Z4: 1249 | AA4: Yes | AB4: =RANDBETWEEN(DATE(2025,7,1),DATE(2025,12,31)) -> 45883 | AC4: Partial | AD4: Bank Transfer | AE4: 8 | AF4: 66 | AG4: 79 | AH4: Needs Improvement | AI4: 85 | AJ4: 51 | AK4: 50 | AM4: 100 | AN4: No | AO4: 2 | AP4: 5 | AQ4: 2024-03-01 | AR4: 2024-03-14 | AS4: No | AT4: Website | AU4: Amit Deshmukh | AV4: Left | AW4: Switched institute | AX4: =IF(LEFT(A4,2)="AU","Aundh",IF(LEFT(A4,2)="KO","Kondhwa","Sinhgad Road")) -> Aundh
A5: AU-044 | B5: Kabir Desai | C5: 2005-09-24 | D5: Male | E5: 9861278670 | F5: kabir.desai44@gmail.com | G5: 169, Aundh Pune | H5: D.A.V. Public School | I5: 70 | J5: 9926091051 | K5: MHT-CET | L5: 6 | M5: Morning | N5: 2024-02-11 | O5: 2024-08-09 | P5: R-120 | Q5: Hybrid | R5: Tue-Thu-Sat | S5: Chemistry | T5: Anil Sharma | U5: 2024-04-12 | V5: 2024-04-09 | W5: 26521 | X5: 25742 | Y5: 779 | Z5: 1089 | AA5: No | AB5: =RANDBETWEEN(DATE(2025,7,1),DATE(2025,12,31)) -> 45909 | AC5: Partial | AD5: UPI | AE5: 7 | AF5: 79 | AG5: 79 | AH5: Good | AI5: 78 | AJ5: 36 | AK5: 35 | AM5: 97 | AN5: Yes | AO5: 5 | AP5: 1 | AQ5: 2024-05-08 | AR5: 2024-05-31 | AS5: Yes | AT5: Instagram Ad | AU5: Amit Deshmukh | AV5: Left | AW5: Lost interest | AX5: =IF(LEFT(A5,2)="AU","Aundh",IF(LEFT(A5,2)="KO","Kondhwa","Sinhgad Road")) -> Aundh
A6: AU-017 | B6: Vivaan Kulkarni | C6: 2005-06-15 | D6: Female | E6: 9810220839 | F6: anaya.joshi17@gmail.com | G6: 751, Aundh Pune | H6: City School | I6: 75 | J6: 9963948363 | K6: NEET | L6: 12 | M6: Morning | N6: 2024-01-20 | O6: 2025-01-14 | P6: R-104 | Q6: Offline | R6: Tue-Thu-Sat | S6: Physics | T6: Anil Sharma | U6: 2024-02-24 | V6: 2024-02-24 | W6: 41229 | X6: 40571 | Y6: 658 | Z6: 4623 | AA6: Yes | AB6: =RANDBETWEEN(DATE(2025,7,1),DATE(2025,12,31)) -> 45948 | AC6: Partial | AD6: Bank Transfer | AE6: 6 | AF6: 41 | AG6: 93 | AH6: Needs Improvement | AI6: 85 | AJ6: 33 | AK6: 32 | AM6: 96 | AN6: Yes | AO6: 1 | AP6: 1 | AQ6: 2024-03-26 | AR6: 2024-04-21 | AS6: Yes | AT6: Instagram Ad | AU6: Rahul Mehta | AV6: Left | AW6: Switched institute | AX6: =IF(LEFT(A6,2)="AU","Aundh",IF(LEFT(A6,2)="KO","Kondhwa","Sinhgad Road")) -> Aundh
A7: AU-001 | B7: Reyansh Sharma | C7: 2005-01-18 | D7: Female | E7: 9855426302 | F7: reyansh.sharma1@gmail.com | G7: 463, Aundh Pune | H7: Vidyanchal School | I7: 77 | J7: 9926479089 | K7: Foundation 8-10 | L7: 12 | M7: Evening | N7: 2024-01-02 | O7: 2024-12-27 | P7: R-113 | Q7: Hybrid | R7: Tue-Thu-Sat | S7: Maths | T7: Preeti Desai | U7: 2024-04-20 | V7: 2024-04-14 | W7: 42851 | X7: 40171 | Y7: 2680 | Z7: 4474 | AA7: No | AB7: =RANDBETWEEN(DATE(2025,7,1),DATE(2025,12,31)) -> 45849 | AC7: Partial | AD7: Card | AE7: 1 | AF7: 46 | AG7: 96 | AH7: Average | AI7: 71 | AJ7: 45 | AK7: 43 | AM7: 95 | AN7: No | AO7: 2 | AP7: 4 | AQ7: 2024-05-14 | AR7: 2024-06-08 | AS7: No | AT7: Referral | AU7: Amit Deshmukh | AV7: Left | AW7: Lost interest | AX7: =IF(LEFT(A7,2)="AU","Aundh",IF(LEFT(A7,2)="KO","Kondhwa","Sinhgad Road")) -> Aundh
A8: AU-030 | B8: Siddharth Joshi | C8: 2005-04-23 | D8: Male | E8: 9895766321 | F8: aarav.desai30@gmail.com | G8: 870, Aundh Pune | H8: D.A.V. Public School | I8: 94 | J8: 9975991785 | K8: NEET | L8: 3 | M8: Afternoon | N8: 2024-01-06 | O8: 2024-04-05 | P8: R-120 | Q8: Online | R8: Mon-Wed-Fri | S8: Maths | T8: Vikram Joshi | U8: 2024-02-24 | V8: 2024-02-15 | W8: 21243 | X8: 20076 | Y8: 1167 | Z8: 3153 | AA8: Yes | AB8: =RANDBETWEEN(DATE(2025,7,1),DATE(2025,12,31)) -> 45958 | AC8: Partial | AD8: Cash | AE8: 2 | AF8: 67 | AG8: 70 | AH8: Needs Improvement | AI8: 82 | AJ8: 60 | AK8: 57 | AL8: Family function | AM8: 95 | AN8: Yes | AO8: 5 | AP8: 4 | AQ8: 2024-04-03 | AR8: 2024-04-21 | AS8: Yes | AT8: Walk-in | AU8: Rahul Mehta | AV8: Active | AX8: =IF(LEFT(A8,2)="AU","Aundh",IF(LEFT(A8,2)="KO","Kondhwa","Sinhgad Road")) -> Aundh
A9: AU-014 | B9: Anay Shinde | C9: 2006-06-06 | D9: Male | E9: 9822011112 | F9: vivaan.joshi14@gmail.com | G9: 738, Aundh Pune | H9: Modern College | I9: 62 | J9: 9953143872 | K9: JEE | L9: 12 | M9: Morning | N9: 2024-03-22 | O9: 2025-03-17 | P9: R-114 | Q9: Online | R9: Tue-Thu-Sat | S9: Biology | T9: Anil Sharma | U9: 2024-02-25 | V9: 2024-02-25 | W9: 24474 | X9: 20873 | Y9: 3601 | Z9: 4292 | AA9: No | AB9: =RANDBETWEEN(DATE(2025,7,1),DATE(2025,12,31)) -> 45968 | AC9: Partial | AD9: Card | AE9: 6 | AF9: 44 | AG9: 50 | AH9: Needs Improvement | AI9: 91 | AJ9: 34 | AK9: 32 | AM9: 94 | AN9: No | AO9: 2 | AP9: 1 | AQ9: 2024-03-16 | AR9: 2024-04-06 | AS9: No | AT9: Walk-in | AU9: Nidhi Shah | AV9: Active | AX9: =IF(LEFT(A9,2)="AU","Aundh",IF(LEFT(A9,2)="KO","Kondhwa","Sinhgad Road")) -> Aundh
A10: AU-018 | B10: Ishaan Chavan | C10: 2005-05-10 | D10: Male | E10: 9864434821 | F10: anaya.kumar18@gmail.com | G10: 551, Aundh Pune | H10: Modern College | I10: 71 | J10: 9951130048 | K10: NEET | L10: 12 | M10: Morning | N10: 2024-01-05 | O10: 2024-12-30 | P10: R-101 | Q10: Hybrid | R10: Tue-Thu-Sat | S10: Biology | T10: Anil Sharma | U10: 2024-03-06 | V10: 2024-03-05 | W10: 29689 | X10: 28607 | Y10: 1082 | Z10: 1301 | AA10: Yes | AB10: =RANDBETWEEN(DATE(2025,7,1),DATE(2025,12,31)) -> 45903 | AC10: Partial | AD10: Card | AE10: 4 | AF10: 54 | AG10: 74 | AH10: Needs Improvement | AI10: 90 | AJ10: 56 | AK10: 53 | AL10: Family function | AM10: 94 | AN10: Yes | AO10: 2 | AP10: 5 | AQ10: 2024-04-17 | AR10: 2024-05-15 | AS10: No | AT10: Instagram Ad | AU10: Amit Deshmukh | AV10: Left | AW10: Too far | AX10: =IF(LEFT(A10,2)="AU","Aundh",IF(LEFT(A10,2)="KO","Kondhwa","Sinhgad Road")) -> Aundh
A11: AU-020 | B11: Ira Joshi | C11: 2006-01-28 | D11: Male | E11: 9898616022 | F11: ira.joshi20@gmail.com | G11: 236, Aundh Pune | H11: Modern College | I11: 67 | J11: 9921755464 | K11: JEE | L11: 3 | M11: Morning | N11: 2024-03-03 | O11: 2024-06-01 | P11: R-109 | Q11: Online | R11: Tue-Thu-Sat | S11: Chemistry | T11: Anil Sharma | U11: 2024-03-12 | V11: 2024-03-10 | W11: 15521 | X11: 15338 | Y11: 183 | Z11: 1968 | AA11: No | AB11: =RANDBETWEEN(DATE(2025,7,1),DATE(2025,12,31)) -> 45948 | AC11: Partial | AD11: Bank Transfer | AE11: 5 | AF11: 81 | AG11: 87 | AH11: Average | AI11: 77 | AJ11: 56 | AK11: 53 | AL11: Sick leave | AM11: 94 | AN11: Yes | AO11: 2 | AP11: 4 | AQ11: 2024-04-25 | AR11: 2024-05-05 | AS11: No | AT11: Website | AU11: Amit Deshmukh | AV11: Left | AW11: Switched institute | AX11: =IF(LEFT(A11,2)="AU","Aundh",IF(LEFT(A11,2)="KO","Kondhwa","Sinhgad Road")) -> Aundh
A12: AU-047 | B12: Omkar Bhosale | C12: 2005-11-14 | D12: Male | E12: 9886591060 | F12: riya.patil47@gmail.com | G12: 113, Aundh Pune | H12: Vidyanchal School | I12: 76 | J12: 9978630854 | K12: JEE | L12: 6 | M12: Morning | N12: 2024-04-04 | O12: 2024-10-01 | P12: R-111 | Q12: Hybrid | R12: Mon-Wed-Fri | S12: Physics | T12: Vikram Joshi | U12: 2024-02-12 | V12: 2024-02-02 | W12: 47666 | X12: 47504 | Y12: 162 | Z12: 365 | AA12: Yes | AB12: =RANDBETWEEN(DATE(2025,7,1),DATE(2025,12,31)) -> 45925 | AC12: Partial | AD12: Bank Transfer | AE12: 6 | AF12: 73 | AG12: 82 | AH12: Good | AI12: 75 | AJ12: 25 | AK12: 23 | AL12: Family function | AM12: 92 | AN12: Yes | AO12: 4 | AP12: 3 | AQ12: 2024-03-15 | AR12: 2024-04-01 | AS12: No | AT12: Walk-in | AU12: Amit Deshmukh | AV12: Left | AW12: Too far | AX12: =IF(LEFT(A12,2)="AU","Aundh",IF(LEFT(A12,2)="KO","Kondhwa","Sinhgad Road")) -> Aundh
A13: AU-028 | B13: Rudra Gaikwad | C13: 2006-06-28 | D13: Female | E13: 9814694076 | F13: meera.joshi28@gmail.com | G13: 113, Aundh Pune | H13: Modern College | I13: 84 | J13: 9969698577 | K13: JEE | L13: 12 | M13: Morning | N13: 2024-01-11 | O13: 2025-01-05 | P13: R-102 | Q13: Hybrid | R13: Mon-Wed-Fri | S13: Physics | T13: Vikram Joshi | U13: 2024-02-11 | V13: 2024-02-04 | W13: 31688 | X13: 31188 | Y13: 500 | Z13: 1442 | AA13: No | AB13: =RANDBETWEEN(DATE(2025,7,1),DATE(2025,12,31)) -> 45895 | AC13: Partial | AD13: Cash | AE13: 10 | AF13: 71 | AG13: 91 | AH13: Good | AI13: 80 | AJ13: 24 | AK13: 22 | AM13: 91 | AN13: No | AO13: 3 | AP13: 3 | AQ13: 2024-04-05 | AR13: 2024-05-01 | AS13: Yes | AT13: Instagram Ad | AU13: Amit Deshmukh | AV13: Left | AW13: Too far | AX13: =IF(LEFT(A13,2)="AU","Aundh",IF(LEFT(A13,2)="KO","Kondhwa","Sinhgad Road")) -> Aundh
A14: AU-043 | B14: Vedant Jadhav | C14: 2005-05-30 | D14: Male | E14: 9827525677 | F14: ayaan.joshi43@gmail.com | G14: 318, Aundh Pune | H14: Spicer Higher Secondary School | I14: 93 | J14: 9973127650 | K14: Foundation 8-10 | L14: 3 | M14: Morning | N14: 2024-03-23 | O14: 2024-06-21 | P14: R-116 | Q14: Hybrid | R14: Mon-Wed-Fri | S14: Physics | T14: Sneha Patil | U14: 2024-03-18 | V14: 2024-03-18 | W14: 33476 | X14: 32565 | Y14: 911 | Z14: 922 | AA14: Yes | AB14: =RANDBETWEEN(DATE(2025,7,1),DATE(2025,12,31)) -> 45963 | AC14: Partial | AD14: Bank Transfer | AE14: 8 | AF14: 50 | AG14: 75 | AH14: Good | AI14: 94 | AJ14: 37 | AK14: 34 | AL14: Sick leave | AM14: 100 | AN14: Yes | AO14: 1 | AP14: 4 | AQ14: 2024-04-19 | AR14: 2024-04-29 | AS14: Yes | AT14: Website | AU14: Rahul Mehta | AV14: Left | AW14: Lost interest | AX14: =IF(LEFT(A14,2)="AU","Aundh",IF(LEFT(A14,2)="KO","Kondhwa","Sinhgad Road")) -> Aundh
A15: AU-031 | B15: Vivaan Joshi | C15: 2005-04-09 | D15: Male | E15: 9885303785 | F15: vivaan.joshi31@gmail.com | G15: 460, Aundh Pune | H15: City International School | I15: 75 | J15: 9990322781 | K15: Foundation 8-10 | L15: 12 | M15: Evening | N15: 2024-02-15 | O15: 2025-02-09 | P15: R-103 | Q15: Hybrid | R15: Tue-Thu-Sat | S15: Chemistry | T15: Preeti Desai | U15: 2024-02-17 | V15: 2024-02-14 | W15: 42334 | X15: 40547 | Y15: 1787 | Z15: 4132 | AA15: Yes | AB15: =RANDBETWEEN(DATE(2025,7,1),DATE(2025,12,31)) -> 46022 | AC15: Partial | AD15: Bank Transfer | AE15: 7 | AF15: 53 | AG15: 85 | AH15: Average | AI15: 98 | AJ15: 20 | AK15: 18 | AM15: 90 | AN15: No | AO15: 3 | AP15: 5 | AQ15: 2024-03-30 | AR15: 2024-04-26 | AS15: Yes | AT15: Walk-in | AU15: Nidhi Shah | AV15: Left | AW15: Lost interest | AX15: =IF(LEFT(A15,2)="AU","Aundh",IF(LEFT(A15,2)="KO","Kondhwa","Sinhgad Road")) -> Aundh
A16: AU-006 | B16: Meera Desai | C16: 2006-05-16 | D16: Male | E16: 9820367740 | F16: meera.desai6@gmail.com | G16: 368, Aundh Pune | H16: Spicer Higher Secondary School | I16: 89 | J16: 9952336944 | K16: MHT-CET | L16: 3 | M16: Morning | N16: 2024-03-12 | O16: 2024-06-10 | P16: R-120 | Q16: Offline | R16: Mon-Wed-Fri | S16: Biology | T16: Preeti Desai | U16: 2024-03-06 | V16: 2024-02-28 | W16: 40557 | X16: 40142 | Y16: 415 | Z16: 1522 | AA16: Yes | AB16: =RANDBETWEEN(DATE(2025,7,1),DATE(2025,12,31)) -> 45999 | AC16: Partial | AD16: Cash | AE16: 4 | AF16: 69 | AG16: 93 | AH16: Good | AI16: 61 | AJ16: 52 | AK16: 46 | AL16: Family function | AM16: 88 | AN16: No | AO16: 2 | AP16: 2 | AQ16: 2024-03-27 | AR16: 2024-04-22 | AS16: Yes | AT16: Facebook Ad | AU16: Rahul Mehta | AV16: Active | AX16: =IF(LEFT(A16,2)="AU","Aundh",IF(LEFT(A16,2)="KO","Kondhwa","Sinhgad Road")) -> Aundh
A17: AU-033 | B17: Kabir Patil | C17: 2005-06-09 | D17: Male | E17: 9845974289 | F17: kabir.patil33@gmail.com | G17: 395, Aundh Pune | H17: Modern College | I17: 93 | J17: 9934055823 | K17: MHT-CET | L17: 3 | M17: Morning | N17: 2024-02-01 | O17: 2024-05-01 | P17: R-112 | Q17: Online | R17: Mon-Wed-Fri | S17: Biology | T17: Vikram Joshi | U17: 2024-02-21 | V17: 2024-02-11 | W17: 21123 | X17: 20086 | Y17: 1037 | Z17: 2663 | AA17: No | AB17: =RANDBETWEEN(DATE(2025,7,1),DATE(2025,12,31)) -> 45841 | AC17: Partial | AD17: UPI | AE17: 2 | AF17: 40 | AG17: 68 | AH17: Good | AI17: 97 | AJ17: 48 | AK17: 42 | AL17: Sick leave | AM17: 87 | AN17: No | AO17: 5 | AP17: 1 | AQ17: 2024-04-05 | AR17: 2024-04-27 | AS17: No | AT17: Instagram Ad | AU17: Nidhi Shah | AV17: Left | AW17: Switched institute | AX17: =IF(LEFT(A17,2)="AU","Aundh",IF(LEFT(A17,2)="KO","Kondhwa","Sinhgad Road")) -> Aundh
A18: AU-024 | B18: Meera Sharma | C18: 2006-02-20 | D18: Male | E18: 9871747241 | F18: meera.sharma24@gmail.com | G18: 209, Aundh Pune | H18: Modern College | I18: 67 | J18: 9937156335 | K18: MHT-CET | L18: 3 | M18: Morning | N18: 2024-02-19 | O18: 2024-05-19 | P18: R-103 | Q18: Hybrid | R18: Tue-Thu-Sat | S18: Maths | T18: Preeti Desai | U18: 2024-05-10 | V18: 2024-05-09 | W18: 36359 | X18: 34507 | Y18: 1852 | Z18: 2266 | AA18: Yes | AB18: =RANDBETWEEN(DATE(2025,7,1),DATE(2025,12,31)) -> 45879 | AC18: Partial | AD18: Bank Transfer | AE18: 4 | AF18: 48 | AG18: 54 | AH18: Average | AI18: 72 | AJ18: 23 | AK18: 20 | AL18: Sick leave | AM18: 86 | AN18: No | AO18: 1 | AP18: 4 | AQ18: 2024-07-09 | AR18: 2024-08-03 | AS18: Yes | AT18: Instagram Ad | AU18: Nidhi Shah | AV18: Left | AW18: Lost interest | AX18: =IF(LEFT(A18,2)="AU","Aundh",IF(LEFT(A18,2)="KO","Kondhwa","Sinhgad Road")) -> Aundh
A19: AU-019 | B19: Aarav Desai | C19: 2006-02-07 | D19: Male | E19: 9888818798 | F19: aarav.desai19@gmail.com | G19: 894, Aundh Pune | H19: City International School | I19: 70 | J19: 9941695896 | K19: MHT-CET | L19: 12 | M19: Evening | N19: 2024-03-25 | O19: 2025-03-20 | P19: R-107 | Q19: Offline | R19: Mon-Wed-Fri | S19: Maths | T19: Sneha Patil | U19: 2024-04-27 | V19: 2024-04-26 | W19: 17919 | X19: 17530 | Y19: 389 | Z19: 511 | AA19: Yes | AB19: =RANDBETWEEN(DATE(2025,7,1),DATE(2025,12,31)) -> 45994 | AC19: Partial | AD19: Bank Transfer | AE19: 8 | AF19: 53 | AG19: 86 | AH19: Good | AI19: 82 | AJ19: 28 | AK19: 24 | AL19: Sick leave | AM19: 85 | AN19: Yes | AO19: 2 | AP19: 3 | AQ19: 2024-06-10 | AR19: 2024-07-03 | AS19: No | AT19: Instagram Ad | AU19: Nidhi Shah | AV19: Active | AX19: =IF(LEFT(A19,2)="AU","Aundh",IF(LEFT(A19,2)="KO","Kondhwa","Sinhgad Road")) -> Aundh
A20: AU-010 | B20: Vivaan Patil | C20: 2006-04-24 | D20: Male | E20: 9852635954 | F20: vivaan.patil10@gmail.com | G20: 189, Aundh Pune | H20: Vidyanchal School | I20: 64 | J20: 9951085984 | K20: Foundation 8-10 | L20: 3 | M20: Evening | N20: 2024-03-16 | O20: 2024-06-14 | P20: R-108 | Q20: Online | R20: Mon-Wed-Fri | S20: English | T20: Vikram Joshi | U20: 2024-05-08 | V20: 2024-05-08 | W20: 43563 | X20: 43281 | Y20: 282 | Z20: 3482 | AA20: Yes | AB20: =RANDBETWEEN(DATE(2025,7,1),DATE(2025,12,31)) -> 45918 | AC20: Partial | AD20: Bank Transfer | AE20: 9 | AF20: 81 | AG20: 91 | AH20: Needs Improvement | AI20: 97 | AJ20: 28 | AK20: 23 | AL20: Family function | AM20: 82 | AN20: No | AO20: 4 | AP20: 4 | AQ20: 2024-06-03 | AR20: 2024-06-14 | AS20: No | AT20: Website | AU20: Nidhi Shah | AV20: Active | AX20: =IF(LEFT(A20,2)="AU","Aundh",IF(LEFT(A20,2)="KO","Kondhwa","Sinhgad Road")) -> Aundh
A21: AU-002 | B21: manish sisodia | C21: 2005-09-11 | D21: Female | E21: 9856784978 | F21: aarav.kumar2@gmail.com | G21: 445, Aundh Pune | H21: City School | I21: 73 | J21: 9982991179 | K21: Foundation 8-10 | L21: 6 | M21: Morning | N21: 2024-01-15 | O21: 2024-07-13 | P21: R-102 | Q21: Hybrid | R21: Tue-Thu-Sat | S21: Maths | T21: Preeti Desai | U21: 2024-04-18 | V21: 2024-04-12 | W21: 27267 | X21: 25250 | Y21: 2017 | Z21: 3626 | AA21: No | AB21: =RANDBETWEEN(DATE(2025,7,1),DATE(2025,12,31)) -> 45936 | AC21: Partial | AD21: Bank Transfer | AE21: 6 | AF21: 75 | AG21: 77 | AH21: Good | AI21: 94 | AJ21: 21 | AK21: 17 | AL21: Family function | AM21: 80 | AN21: Yes | AO21: 3 | AP21: 4 | AQ21: 2024-05-08 | AR21: 2024-05-27 | AS21: No | AT21: Instagram Ad | AU21: Amit Deshmukh | AV21: Left | AW21: Switched institute | AX21: =IF(LEFT(A21,2)="AU","Aundh",IF(LEFT(A21,2)="KO","Kondhwa","Sinhgad Road")) -> Aundh
A22: AU-026 | B22: Kabir Joshi | C22: 2005-10-12 | D22: Male | E22: 9839141596 | F22: kabir.joshi26@gmail.com | G22: 681, Aundh Pune | H22: Modern College | I22: 92 | J22: 9967762687 | K22: JEE | L22: 3 | M22: Evening | N22: 2024-02-24 | O22: 2024-05-24 | P22: R-110 | Q22: Online | R22: Tue-Thu-Sat | S22: Chemistry | T22: Preeti Desai | U22: 2024-05-26 | V22: 2024-05-18 | W22: 38039 | X22: 34261 | Y22: 3778 | Z22: 4859 | AA22: No | AB22: =RANDBETWEEN(DATE(2025,7,1),DATE(2025,12,31)) -> 45992 | AC22: Partial | AD22: Cash | AE22: 8 | AF22: 49 | AG22: 68 | AH22: Needs Improvement | AI22: 84 | AJ22: 51 | AK22: 41 | AM22: 80 | AN22: No | AO22: 3 | AP22: 5 | AQ22: 2024-07-21 | AR22: 2024-08-15 | AS22: Yes | AT22: Walk-in | AU22: Rahul Mehta | AV22: Active | AX22: =IF(LEFT(A22,2)="AU","Aundh",IF(LEFT(A22,2)="KO","Kondhwa","Sinhgad Road")) -> Aundh
A23: AU-003 | B23: Tejas Pawar | C23: 2006-06-27 | D23: Male | E23: 9847094337 | F23: riya.joshi3@gmail.com | G23: 723, Aundh Pune | H23: City School | I23: 61 | J23: 9967496922 | K23: Crash Course | L23: 6 | M23: Afternoon | N23: 2024-01-22 | O23: 2024-07-20 | P23: R-119 | Q23: Offline | R23: Tue-Thu-Sat | S23: Biology | T23: Vikram Joshi | U23: 2024-05-28 | V23: 2024-05-19 | W23: 29239 | X23: 28279 | Y23: 960 | Z23: 1156 | AA23: No | AB23: =RANDBETWEEN(DATE(2025,7,1),DATE(2025,12,31)) -> 45976 | AC23: Partial | AD23: Cash | AE23: 5 | AF23: 63 | AG23: 64 | AH23: Average | AI23: 68 | AJ23: 54 | AK23: 43 | AL23: Sick leave | AM23: 79 | AN23: Yes | AO23: 1 | AP23: 5 | AQ23: 2024-07-11 | AR23: 2024-07-27 | AS23: Yes | AT23: Website | AU23: Nidhi Shah | AV23: Left | AW23: Switched institute | AX23: =IF(LEFT(A23,2)="AU","Aundh",IF(LEFT(A23,2)="KO","Kondhwa","Sinhgad Road")) -> Aundh
A24: AU-016 | B24: Anaya Joshi | C24: 2006-08-04 | D24: Male | E24: 9883268727 | F24: anaya.joshi16@gmail.com | G24: 245, Aundh Pune | H24: Modern College | I24: 90 | J24: 9982569341 | K24: Foundation 8-10 | L24: 3 | M24: Afternoon | N24: 2024-01-08 | O24: 2024-04-07 | P24: R-110 | Q24: Hybrid | R24: Tue-Thu-Sat | S24: English | T24: Sneha Patil | U24: 2024-04-13 | V24: 2024-04-11 | W24: 30207 | X24: 28610 | Y24: 1597 | Z24: 1889 | AA24: Yes | AB24: =RANDBETWEEN(DATE(2025,7,1),DATE(2025,12,31)) -> 45985 | AC24: Partial | AD24: Bank Transfer | AE24: 7 | AF24: 52 | AG24: 87 | AH24: Average | AI24: 72 | AJ24: 50 | AK24: 39 | AM24: 78 | AN24: Yes | AO24: 4 | AP24: 3 | AQ24: 2024-05-30 | AR24: 2024-06-25 | AS24: Yes | AT24: Website | AU24: Amit Deshmukh | AV24: Left | AW24: Lost interest | AX24: =IF(LEFT(A24,2)="AU","Aundh",IF(LEFT(A24,2)="KO","Kondhwa","Sinhgad Road")) -> Aundh
A25: AU-038 | B25: Hriday Limaye | C25: 2006-06-21 | D25: Male | E25: 9822514259 | F25: ayaan.sharma38@gmail.com | G25: 217, Aundh Pune | H25: Modern College | I25: 79 | J25: 9960114318 | K25: NEET | L25: 12 | M25: Evening | N25: 2024-01-22 | O25: 2025-01-16 | P25: R-115 | Q25: Offline | R25: Mon-Wed-Fri | S25: Maths | T25: Vikram Joshi | U25: 2024-05-15 | V25: 2024-05-09 | W25: 45733 | X25: 41468 | Y25: 4265 | Z25: 4465 | AA25: Yes | AB25: =RANDBETWEEN(DATE(2025,7,1),DATE(2025,12,31)) -> 45988 | AC25: Partial | AD25: Bank Transfer | AE25: 5 | AF25: 51 | AG25: 58 | AH25: Average | AI25: 65 | AJ25: 56 | AK25: 44 | AM25: 78 | AN25: No | AO25: 1 | AP25: 3 | AQ25: 2024-07-13 | AR25: 2024-07-25 | AS25: No | AT25: Website | AU25: Nidhi Shah | AV25: Active | AX25: =IF(LEFT(A25,2)="AU","Aundh",IF(LEFT(A25,2)="KO","Kondhwa","Sinhgad Road")) -> Aundh
A26: AU-008 | B26: Meera Joshi | C26: 2006-06-23 | D26: Female | E26: 9822355416 | F26: meera.joshi8@gmail.com | G26: 589, Aundh Pune | H26: Vidyanchal School | I26: 88 | J26: 9995712675 | K26: Crash Course | L26: 3 | M26: Afternoon | N26: 2024-03-22 | O26: 2024-06-20 | P26: R-105 | Q26: Online | R26: Tue-Thu-Sat | S26: Physics | T26: Sneha Patil | U26: 2024-03-15 | V26: 2024-03-14 | W26: 40970 | X26: 39997 | Y26: 973 | Z26: 2197 | AA26: No | AB26: =RANDBETWEEN(DATE(2025,7,1),DATE(2025,12,31)) -> 45914 | AC26: Partial | AD26: Bank Transfer | AE26: 6 | AF26: 90 | AG26: 99 | AH26: Average | AI26: 72 | AJ26: 33 | AK26: 25 | AL26: Family function | AM26: 75 | AN26: Yes | AO26: 3 | AP26: 5 | AQ26: 2024-04-08 | AR26: 2024-04-21 | AS26: No | AT26: Referral | AU26: Rahul Mehta | AV26: Active | AX26: =IF(LEFT(A26,2)="AU","Aundh",IF(LEFT(A26,2)="KO","Kondhwa","Sinhgad Road")) -> Aundh
A27: AU-009 | B27: Aryan Apte | C27: 2006-05-21 | D27: Male | E27: 9888752606 | F27: aarav.kumar9@gmail.com | G27: 276, Aundh Pune | H27: City International School | I27: 73 | J27: 9967525295 | K27: Foundation 8-10 | L27: 12 | M27: Afternoon | N27: 2024-03-04 | O27: 2025-02-27 | P27: R-105 | Q27: Online | R27: Mon-Wed-Fri | S27: Chemistry | T27: Vikram Joshi | U27: 2024-03-06 | V27: 2024-03-01 | W27: 21161 | X27: 19825 | Y27: 1336 | Z27: 3988 | AA27: No | AB27: =RANDBETWEEN(DATE(2025,7,1),DATE(2025,12,31)) -> 45987 | AC27: Partial | AD27: UPI | AE27: 8 | AF27: 68 | AG27: 83 | AH27: Good | AI27: 99 | AJ27: 56 | AK27: 41 | AM27: 73 | AN27: No | AO27: 2 | AP27: 5 | AQ27: 2024-04-22 | AR27: 2024-05-21 | AS27: Yes | AT27: Website | AU27: Amit Deshmukh | AV27: Active | AX27: =IF(LEFT(A27,2)="AU","Aundh",IF(LEFT(A27,2)="KO","Kondhwa","Sinhgad Road")) -> Aundh
A28: AU-027 | B28: Siya Desai | C28: 2006-04-22 | D28: Male | E28: 9816439415 | F28: siya.desai27@gmail.com | G28: 969, Aundh Pune | H28: Modern College | I28: 78 | J28: 9925998150 | K28: Crash Course | L28: 6 | M28: Afternoon | N28: 2024-02-02 | O28: 2024-07-31 | P28: R-114 | Q28: Online | R28: Tue-Thu-Sat | S28: Chemistry | T28: Sneha Patil | U28: 2024-03-16 | V28: 2024-03-14 | W28: 45981 | X28: 45836 | Y28: 145 | Z28: 3623 | AA28: Yes | AB28: =RANDBETWEEN(DATE(2025,7,1),DATE(2025,12,31)) -> 45902 | AC28: Partial | AD28: Cash | AE28: 8 | AF28: 74 | AG28: 94 | AH28: Needs Improvement | AI28: 63 | AJ28: 34 | AK28: 25 | AM28: 73 | AN28: No | AO28: 4 | AP28: 5 | AQ28: 2024-05-05 | AR28: 2024-06-04 | AS28: Yes | AT28: Facebook Ad | AU28: Nidhi Shah | AV28: Left | AW28: Switched institute | AX28: =IF(LEFT(A28,2)="AU","Aundh",IF(LEFT(A28,2)="KO","Kondhwa","Sinhgad Road")) -> Aundh
A29: AU-035 | B29: Ira Sharma | C29: 2006-03-25 | D29: Male | E29: 9861555077 | F29: ira.sharma35@gmail.com | G29: 102, Aundh Pune | H29: D.A.V. Public School | I29: 94 | J29: 9954095883 | K29: MHT-CET | L29: 3 | M29: Afternoon | N29: 2024-02-22 | O29: 2024-05-22 | P29: R-102 | Q29: Hybrid | R29: Mon-Wed-Fri | S29: Physics | T29: Anil Sharma | U29: 2024-04-11 | V29: 2024-04-09 | W29: 29344 | X29: 27076 | Y29: 2268 | Z29: 4754 | AA29: No | AB29: =RANDBETWEEN(DATE(2025,7,1),DATE(2025,12,31)) -> 45846 | AC29: Partial | AD29: Cash | AE29: 8 | AF29: 48 | AG29: 96 | AH29: Needs Improvement | AI29: 100 | AJ29: 60 | AK29: 44 | AL29: Sick leave | AM29: 73 | AN29: Yes | AO29: 4 | AP29: 2 | AQ29: 2024-05-20 | AR29: 2024-06-07 | AS29: Yes | AT29: Website | AU29: Rahul Mehta | AV29: Active | AX29: =IF(LEFT(A29,2)="AU","Aundh",IF(LEFT(A29,2)="KO","Kondhwa","Sinhgad Road")) -> Aundh
A30: AU-012 | B30: Kunal Godbole | C30: 2006-01-14 | D30: Female | E30: 9861968735 | F30: ayaan.sharma12@gmail.com | G30: 336, Aundh Pune | H30: City School | I30: 63 | J30: 9939854108 | K30: JEE | L30: 12 | M30: Evening | N30: 2024-02-27 | O30: 2025-02-21 | P30: R-112 | Q30: Online | R30: Mon-Wed-Fri | S30: Biology | T30: Vikram Joshi | U30: 2024-02-06 | V30: 2024-02-03 | W30: 47685 | X30: 47563 | Y30: 122 | Z30: 663 | AA30: No | AB30: =RANDBETWEEN(DATE(2025,7,1),DATE(2025,12,31)) -> 45905 | AC30: Partial | AD30: UPI | AE30: 9 | AF30: 76 | AG30: 78 | AH30: Needs Improvement | AI30: 98 | AJ30: 59 | AK30: 43 | AL30: Family function | AM30: 72 | AN30: No | AO30: 4 | AP30: 2 | AQ30: 2024-03-03 | AR30: 2024-03-13 | AS30: Yes | AT30: Website | AU30: Nidhi Shah | AV30: Left | AW30: Switched institute | AX30: =IF(LEFT(A30,2)="AU","Aundh",IF(LEFT(A30,2)="KO","Kondhwa","Sinhgad Road")) -> Aundh
A31: AU-013 | B31: Meera Patil | C31: 2005-12-01 | D31: Male | E31: 9817700186 | F31: meera.patil13@gmail.com | G31: 589, Aundh Pune | H31: D.A.V. Public School | I31: 71 | J31: 9931778745 | K31: MHT-CET | L31: 12 | M31: Morning | N31: 2024-01-24 | O31: 2025-01-18 | P31: R-112 | Q31: Online | R31: Mon-Wed-Fri | S31: Maths | T31: Ravi Kumar | U31: 2024-03-04 | V31: 2024-02-25 | W31: 19992 | X31: 16844 | Y31: 3148 | Z31: 3877 | AA31: Yes | AB31: =RANDBETWEEN(DATE(2025,7,1),DATE(2025,12,31)) -> 46015 | AC31: Partial | AD31: Bank Transfer | AE31: 6 | AF31: 82 | AG31: 99 | AH31: Needs Improvement | AI31: 73 | AJ31: 37 | AK31: 27 | AL31: Sick leave | AM31: 72 | AN31: Yes | AO31: 4 | AP31: 3 | AQ31: 2024-04-30 | AR31: 2024-05-28 | AS31: No | AT31: Instagram Ad | AU31: Nidhi Shah | AV31: Left | AW31: Too far | AX31: =IF(LEFT(A31,2)="AU","Aundh",IF(LEFT(A31,2)="KO","Kondhwa","Sinhgad Road")) -> Aundh
A32: AU-042 | B32: Ira Patil | C32: 2005-01-20 | D32: Male | E32: 9829100757 | F32: ira.patil42@gmail.com | G32: 450, Aundh Pune | H32: Spicer Higher Secondary School | I32: 76 | J32: 9993814827 | K32: Crash Course | L32: 3 | M32: Evening | N32: 2024-03-16 | O32: 2024-06-14 | P32: R-118 | Q32: Offline | R32: Mon-Wed-Fri | S32: Physics | T32: Vikram Joshi | U32: 2024-05-27 | V32: 2024-05-21 | W32: 41685 | X32: 41195 | Y32: 490 | Z32: 4889 | AA32: No | AB32: =RANDBETWEEN(DATE(2025,7,1),DATE(2025,12,31)) -> 45902 | AC32: Partial | AD32: UPI | AE32: 1 | AF32: 62 | AG32: 98 | AH32: Average | AI32: 67 | AJ32: 55 | AK32: 39 | AL32: Sick leave | AM32: 70 | AN32: No | AO32: 2 | AP32: 2 | AQ32: 2024-07-09 | AR32: 2024-08-08 | AS32: No | AT32: Instagram Ad | AU32: Nidhi Shah | AV32: Left | AW32: Switched institute | AX32: =IF(LEFT(A32,2)="AU","Aundh",IF(LEFT(A32,2)="KO","Kondhwa","Sinhgad Road")) -> Aundh
A33: AU-011 | B33: Riya Patil | C33: 2006-04-17 | D33: Male | E33: 9887840907 | F33: riya.patil11@gmail.com | G33: 792, Aundh Pune | H33: Spicer Higher Secondary School | I33: 66 | J33: 9932763392 | K33: JEE | L33: 6 | M33: Morning | N33: 2024-04-07 | O33: 2024-10-04 | P33: R-110 | Q33: Online | R33: Mon-Wed-Fri | S33: Physics | T33: Preeti Desai | U33: 2024-02-15 | V33: 2024-02-08 | W33: 20936 | X33: 18272 | Y33: 2664 | Z33: 2870 | AA33: No | AB33: =RANDBETWEEN(DATE(2025,7,1),DATE(2025,12,31)) -> 45970 | AC33: Partial | AD33: UPI | AE33: 10 | AF33: 49 | AG33: 76 | AH33: Average | AI33: 96 | AJ33: 38 | AK33: 25 | AM33: 65 | AN33: No | AO33: 1 | AP33: 5 | AQ33: 2024-03-10 | AR33: 2024-03-31 | AS33: Yes | AT33: Website | AU33: Amit Deshmukh | AV33: Left | AW33: Lost interest | AX33: =IF(LEFT(A33,2)="AU","Aundh",IF(LEFT(A33,2)="KO","Kondhwa","Sinhgad Road")) -> Aundh
A34: AU-032 | B34: Pranav Gadgil | C34: 2005-12-18 | D34: Male | E34: 9856821801 | F34: riya.joshi32@gmail.com | G34: 130, Aundh Pune | H34: Modern College | I34: 80 | J34: 9967122501 | K34: Foundation 8-10 | L34: 3 | M34: Morning | N34: 2024-04-04 | O34: 2024-07-03 | P34: R-117 | Q34: Offline | R34: Mon-Wed-Fri | S34: Maths | T34: Anil Sharma | U34: 2024-02-11 | V34: 2024-02-11 | W34: 47410 | X34: 46718 | Y34: 692 | Z34: 2379 | AA34: Yes | AB34: =RANDBETWEEN(DATE(2025,7,1),DATE(2025,12,31)) -> 45915 | AC34: Partial | AD34: Cash | AE34: 10 | AF34: 76 | AG34: 77 | AH34: Good | AI34: 88 | AJ34: 36 | AK34: 22 | AM34: 61 | AN34: Yes | AO34: 3 | AP34: 2 | AQ34: 2024-04-02 | AR34: 2024-05-02 | AS34: No | AT34: Referral | AU34: Amit Deshmukh | AV34: Left | AW34: Too far | AX34: =IF(LEFT(A34,2)="AU","Aundh",IF(LEFT(A34,2)="KO","Kondhwa","Sinhgad Road")) -> Aundh
A35: AU-022 | B35: Saurabh Ranade | C35: 2005-01-03 | D35: Male | E35: 9859987035 | F35: ayaan.kumar22@gmail.com | G35: 625, Aundh Pune | H35: Modern College | I35: 65 | J35: 9918907790 | K35: Foundation 8-10 | L35: 12 | M35: Morning | N35: 2024-02-25 | O35: 2025-02-19 | P35: R-106 | Q35: Online | R35: Mon-Wed-Fri | S35: Biology | T35: Anil Sharma | U35: 2024-03-13 | V35: 2024-03-11 | W35: 29550 | X35: 28618 | Y35: 932 | Z35: 3302 | AA35: Yes | AB35: =RANDBETWEEN(DATE(2025,7,1),DATE(2025,12,31)) -> 45940 | AC35: Partial | AD35: Bank Transfer | AE35: 8 | AF35: 45 | AG35: 54 | AH35: Good | AI35: 78 | AJ35: 38 | AK35: 23 | AL35: Family function | AM35: 60 | AN35: Yes | AO35: 3 | AP35: 1 | AQ35: 2024-05-10 | AR35: 2024-06-09 | AS35: No | AT35: Referral | AU35: Amit Deshmukh | AV35: Left | AW35: Switched institute | AX35: =IF(LEFT(A35,2)="AU","Aundh",IF(LEFT(A35,2)="KO","Kondhwa","Sinhgad Road")) -> Aundh
A36: AU-045 | B36: Riya Joshi | C36: 2005-08-15 | D36: Male | E36: 9837045769 | F36: riya.joshi45@gmail.com | G36: 968, Aundh Pune | H36: Modern College | I36: 63 | J36: 9990130107 | K36: Foundation 8-10 | L36: 6 | M36: Afternoon | N36: 2024-01-30 | O36: 2024-07-28 | P36: R-103 | Q36: Hybrid | R36: Tue-Thu-Sat | S36: Physics | T36: Ravi Kumar | U36: 2024-02-18 | V36: 2024-02-18 | W36: 19785 | X36: 18254 | Y36: 1531 | Z36: 2562 | AA36: No | AB36: =RANDBETWEEN(DATE(2025,7,1),DATE(2025,12,31)) -> 45959 | AC36: Partial | AD36: Card | AE36: 2 | AF36: 45 | AG36: 65 | AH36: Needs Improvement | AI36: 73 | AJ36: 37 | AK36: 22 | AL36: Sick leave | AM36: 59 | AN36: Yes | AO36: 4 | AP36: 1 | AQ36: 2024-03-14 | AR36: 2024-03-30 | AS36: Yes | AT36: Website | AU36: Rahul Mehta | AV36: Active | AX36: =IF(LEFT(A36,2)="AU","Aundh",IF(LEFT(A36,2)="KO","Kondhwa","Sinhgad Road")) -> Aundh
A37: AU-021 | B37: Aarav Kumar | C37: 2005-07-20 | D37: Female | E37: 9869774216 | F37: aarav.kumar21@gmail.com | G37: 513, Aundh Pune | H37: Spicer Higher Secondary School | I37: 65 | J37: 9919070144 | K37: NEET | L37: 3 | M37: Afternoon | N37: 2024-02-21 | O37: 2024-05-21 | P37: R-107 | Q37: Online | R37: Tue-Thu-Sat | S37: Biology | T37: Anil Sharma | U37: 2024-03-06 | V37: 2024-03-02 | W37: 32976 | X37: 32180 | Y37: 796 | Z37: 2727 | AA37: Yes | AB37: =RANDBETWEEN(DATE(2025,7,1),DATE(2025,12,31)) -> 45982 | AC37: Partial | AD37: Cash | AE37: 5 | AF37: 55 | AG37: 55 | AH37: Good | AI37: 63 | AJ37: 54 | AK37: 31 | AL37: Family function | AM37: 57 | AN37: No | AO37: 4 | AP37: 2 | AQ37: 2024-05-04 | AR37: 2024-06-03 | AS37: Yes | AT37: Instagram Ad | AU37: Rahul Mehta | AV37: Active | AX37: =IF(LEFT(A37,2)="AU","Aundh",IF(LEFT(A37,2)="KO","Kondhwa","Sinhgad Road")) -> Aundh
A38: AU-034 | B38: Ayaan Joshi | C38: 2005-08-05 | D38: Female | E38: 9858291899 | F38: ayaan.joshi34@gmail.com | G38: 776, Aundh Pune | H38: Vidyanchal School | I38: 69 | J38: 9924142404 | K38: Crash Course | L38: 12 | M38: Evening | N38: 2024-02-13 | O38: 2025-02-07 | P38: R-111 | Q38: Offline | R38: Tue-Thu-Sat | S38: Physics | T38: Vikram Joshi | U38: 2024-05-02 | V38: 2024-04-22 | W38: 28619 | X38: 25381 | Y38: 3238 | Z38: 3240 | AA38: No | AB38: =RANDBETWEEN(DATE(2025,7,1),DATE(2025,12,31)) -> 45925 | AC38: Partial | AD38: Bank Transfer | AE38: 6 | AF38: 85 | AG38: 88 | AH38: Needs Improvement | AI38: 83 | AJ38: 26 | AK38: 15 | AL38: Family function | AM38: 57 | AN38: No | AO38: 5 | AP38: 4 | AQ38: 2024-06-01 | AR38: 2024-07-01 | AS38: Yes | AT38: Walk-in | AU38: Rahul Mehta | AV38: Left | AW38: Switched institute | AX38: =IF(LEFT(A38,2)="AU","Aundh",IF(LEFT(A38,2)="KO","Kondhwa","Sinhgad Road")) -> Aundh
A39: AU-050 | B39: Aarav Sharma | C39: 2006-05-20 | D39: Male | E39: 9892575113 | F39: aarav.sharma50@gmail.com | G39: 160, Aundh Pune | H39: D.A.V. Public School | I39: 83 | J39: 9949987246 | K39: JEE | L39: 3 | M39: Evening | N39: 2024-02-06 | O39: 2024-05-06 | P39: R-108 | Q39: Offline | R39: Tue-Thu-Sat | S39: Chemistry | T39: Ravi Kumar | U39: 2024-03-18 | V39: 2024-03-14 | W39: 38119 | X39: 38089 | Y39: 30 | Z39: 878 | AA39: Yes | AB39: =RANDBETWEEN(DATE(2025,7,1),DATE(2025,12,31)) -> 46000 | AC39: Partial | AD39: Card | AE39: 5 | AF39: 49 | AG39: 86 | AH39: Good | AI39: 62 | AJ39: 33 | AK39: 19 | AL39: Family function | AM39: 57 | AN39: No | AO39: 4 | AP39: 1 | AQ39: 2024-04-26 | AR39: 2024-05-24 | AS39: No | AT39: Instagram Ad | AU39: Amit Deshmukh | AV39: Active | AX39: =IF(LEFT(A39,2)="AU","Aundh",IF(LEFT(A39,2)="KO","Kondhwa","Sinhgad Road")) -> Aundh
A40: AU-039 | B40: Anaya Sharma | C40: 2005-06-08 | D40: Female | E40: 9832258449 | F40: anaya.sharma39@gmail.com | G40: 746, Aundh Pune | H40: City International School | I40: 82 | J40: 9990085925 | K40: Foundation 8-10 | L40: 12 | M40: Evening | N40: 2024-01-12 | O40: 2025-01-06 | P40: R-103 | Q40: Online | R40: Tue-Thu-Sat | S40: Physics | T40: Sneha Patil | U40: 2024-03-01 | V40: 2024-02-26 | W40: 39856 | X40: 38099 | Y40: 1757 | Z40: 4355 | AA40: Yes | AB40: =RANDBETWEEN(DATE(2025,7,1),DATE(2025,12,31)) -> 46006 | AC40: Partial | AD40: Bank Transfer | AE40: 3 | AF40: 54 | AG40: 62 | AH40: Average | AI40: 80 | AJ40: 35 | AK40: 19 | AL40: Sick leave | AM40: 54 | AN40: Yes | AO40: 5 | AP40: 3 | AQ40: 2024-04-22 | AR40: 2024-05-20 | AS40: No | AT40: Referral | AU40: Nidhi Shah | AV40: Left | AW40: Lost interest | AX40: =IF(LEFT(A40,2)="AU","Aundh",IF(LEFT(A40,2)="KO","Kondhwa","Sinhgad Road")) -> Aundh
A41: AU-025 | B41: Ira Kumar | C41: 2006-05-06 | D41: Female | E41: 9850568987 | F41: ira.kumar25@gmail.com | G41: 628, Aundh Pune | H41: Vidyanchal School | I41: 75 | J41: 9972283041 | K41: Foundation 8-10 | L41: 3 | M41: Afternoon | N41: 2024-03-23 | O41: 2024-06-21 | P41: R-105 | Q41: Offline | R41: Tue-Thu-Sat | S41: Chemistry | T41: Ravi Kumar | U41: 2024-02-08 | V41: 2024-02-03 | W41: 27463 | X41: 25008 | Y41: 2455 | Z41: 2660 | AA41: Yes | AB41: =RANDBETWEEN(DATE(2025,7,1),DATE(2025,12,31)) -> 45878 | AC41: Partial | AD41: Card | AE41: 9 | AF41: 71 | AG41: 98 | AH41: Good | AI41: 97 | AJ41: 44 | AK41: 23 | AM41: 52 | AN41: Yes | AO41: 1 | AP41: 1 | AQ41: 2024-02-28 | AR41: 2024-03-13 | AS41: Yes | AT41: Website | AU41: Rahul Mehta | AV41: Active | AX41: =IF(LEFT(A41,2)="AU","Aundh",IF(LEFT(A41,2)="KO","Kondhwa","Sinhgad Road")) -> Aundh
A42: AU-037 | B42: Ayaan Sharma | C42: 2005-01-08 | D42: Male | E42: 9846464786 | F42: ayaan.sharma37@gmail.com | G42: 471, Aundh Pune | H42: Modern College | I42: 69 | J42: 9970462439 | K42: NEET | L42: 3 | M42: Morning | N42: 2024-02-25 | O42: 2024-05-25 | P42: R-106 | Q42: Offline | R42: Mon-Wed-Fri | S42: Physics | T42: Ravi Kumar | U42: 2024-04-25 | V42: 2024-04-15 | W42: 16996 | X42: 16468 | Y42: 528 | Z42: 3946 | AA42: No | AB42: =RANDBETWEEN(DATE(2025,7,1),DATE(2025,12,31)) -> 45853 | AC42: Partial | AD42: Cash | AE42: 8 | AF42: 73 | AG42: 91 | AH42: Needs Improvement | AI42: 78 | AJ42: 42 | AK42: 21 | AL42: Sick leave | AM42: 50 | AN42: Yes | AO42: 1 | AP42: 3 | AQ42: 2024-05-26 | AR42: 2024-06-08 | AS42: Yes | AT42: Website | AU42: Nidhi Shah | AV42: Active | AX42: =IF(LEFT(A42,2)="AU","Aundh",IF(LEFT(A42,2)="KO","Kondhwa","Sinhgad Road")) -> Aundh
A43: AU-040 | B43: Anaya Kumar | C43: 2005-04-11 | D43: Male | E43: 9837559454 | F43: anaya.kumar40@gmail.com | G43: 169, Aundh Pune | H43: City School | I43: 60 | J43: 9945760111 | K43: NEET | L43: 3 | M43: Evening | N43: 2024-03-04 | O43: 2024-06-02 | P43: R-114 | Q43: Hybrid | R43: Mon-Wed-Fri | S43: Biology | T43: Vikram Joshi | U43: 2024-04-15 | V43: 2024-04-06 | W43: 31109 | X43: 29623 | Y43: 1486 | Z43: 2133 | AA43: No | AB43: =RANDBETWEEN(DATE(2025,7,1),DATE(2025,12,31)) -> 45882 | AC43: Partial | AD43: Bank Transfer | AE43: 8 | AF43: 64 | AG43: 84 | AH43: Needs Improvement | AI43: 93 | AJ43: 58 | AK43: 27 | AL43: Family function | AM43: 46 | AN43: Yes | AO43: 1 | AP43: 2 | AQ43: 2024-06-07 | AR43: 2024-06-20 | AS43: Yes | AT43: Instagram Ad | AU43: Amit Deshmukh | AV43: Active | AX43: =IF(LEFT(A43,2)="AU","Aundh",IF(LEFT(A43,2)="KO","Kondhwa","Sinhgad Road")) -> Aundh
A44: AU-004 | B44: Reyansh Joshi | C44: 2006-08-11 | D44: Male | E44: 9828538761 | F44: reyansh.joshi4@gmail.com | G44: 815, Aundh Pune | H44: Modern College | I44: 95 | J44: 9969518889 | K44: Crash Course | L44: 12 | M44: Morning | N44: 2024-03-25 | O44: 2025-03-20 | P44: R-109 | Q44: Offline | R44: Mon-Wed-Fri | S44: Physics | T44: Anil Sharma | U44: 2024-05-26 | V44: 2024-05-21 | W44: 18800 | X44: 15778 | Y44: 3022 | Z44: 4161 | AA44: No | AB44: =RANDBETWEEN(DATE(2025,7,1),DATE(2025,12,31)) -> 45876 | AC44: Partial | AD44: Card | AE44: 5 | AF44: 73 | AG44: 88 | AH44: Good | AI44: 75 | AJ44: 58 | AK44: 26 | AL44: Family function | AM44: 44 | AN44: Yes | AO44: 4 | AP44: 3 | AQ44: 2024-06-28 | AR44: 2024-07-23 | AS44: No | AT44: Referral | AU44: Amit Deshmukh | AV44: Active | AX44: =IF(LEFT(A44,2)="AU","Aundh",IF(LEFT(A44,2)="KO","Kondhwa","Sinhgad Road")) -> Aundh
A45: AU-023 | B45: Ayaan Kumar | C45: 2005-08-20 | D45: Female | E45: 9851052997 | F45: ayaan.kumar23@gmail.com | G45: 540, Aundh Pune | H45: Modern College | I45: 68 | J45: 9989857993 | K45: NEET | L45: 6 | M45: Evening | N45: 2024-03-23 | O45: 2024-09-19 | P45: R-117 | Q45: Offline | R45: Tue-Thu-Sat | S45: Chemistry | T45: Preeti Desai | U45: 2024-03-29 | V45: 2024-03-21 | W45: 29689 | X45: 29635 | Y45: 54 | Z45: 3842 | AA45: No | AB45: =RANDBETWEEN(DATE(2025,7,1),DATE(2025,12,31)) -> 46018 | AC45: Partial | AD45: Cash | AE45: 6 | AF45: 82 | AG45: 94 | AH45: Needs Improvement | AI45: 67 | AJ45: 60 | AK45: 26 | AL45: Sick leave | AM45: 43 | AN45: No | AO45: 3 | AP45: 2 | AQ45: 2024-05-10 | AR45: 2024-06-02 | AS45: Yes | AT45: Referral | AU45: Rahul Mehta | AV45: Left | AW45: Lost interest | AX45: =IF(LEFT(A45,2)="AU","Aundh",IF(LEFT(A45,2)="KO","Kondhwa","Sinhgad Road")) -> Aundh
A46: AU-036 | B46: Samarth Gokhale | C46: 2005-05-06 | D46: Male | E46: 9898471683 | F46: reyansh.desai36@gmail.com | G46: 555, Aundh Pune | H46: City School | I46: 91 | J46: 9928312643 | K46: Crash Course | L46: 3 | M46: Afternoon | N46: 2024-03-03 | O46: 2024-06-01 | P46: R-119 | Q46: Online | R46: Mon-Wed-Fri | S46: Biology | T46: Sneha Patil | U46: 2024-05-15 | V46: 2024-05-09 | W46: 45585 | X46: 44073 | Y46: 1512 | Z46: 3674 | AA46: No | AB46: =RANDBETWEEN(DATE(2025,7,1),DATE(2025,12,31)) -> 46020 | AC46: Partial | AD46: Card | AE46: 6 | AF46: 46 | AG46: 49 | AH46: Average | AI46: 100 | AJ46: 46 | AK46: 20 | AL46: Family function | AM46: 43 | AN46: No | AO46: 2 | AP46: 2 | AQ46: 2024-06-19 | AR46: 2024-07-08 | AS46: Yes | AT46: Instagram Ad | AU46: Nidhi Shah | AV46: Active | AX46: =IF(LEFT(A46,2)="AU","Aundh",IF(LEFT(A46,2)="KO","Kondhwa","Sinhgad Road")) -> Aundh
A47: AU-029 | B47: Madhav Bapat | C47: 2006-08-02 | D47: Male | E47: 9863730140 | F47: anaya.patil29@gmail.com | G47: 207, Aundh Pune | H47: D.A.V. Public School | I47: 85 | J47: 9981383868 | K47: MHT-CET | L47: 12 | M47: Afternoon | N47: 2024-01-22 | O47: 2025-01-16 | P47: R-114 | Q47: Offline | R47: Mon-Wed-Fri | S47: Chemistry | T47: Sneha Patil | U47: 2024-02-17 | V47: 2024-02-15 | W47: 37907 | X47: 37497 | Y47: 410 | Z47: 3915 | AA47: No | AB47: =RANDBETWEEN(DATE(2025,7,1),DATE(2025,12,31)) -> 46011 | AC47: Partial | AD47: Bank Transfer | AE47: 5 | AF47: 58 | AG47: 74 | AH47: Average | AI47: 84 | AJ47: 38 | AK47: 16 | AL47: Sick leave | AM47: 42 | AN47: No | AO47: 5 | AP47: 2 | AQ47: 2024-04-11 | AR47: 2024-04-23 | AS47: No | AT47: Facebook Ad | AU47: Rahul Mehta | AV47: Active | AX47: =IF(LEFT(A47,2)="AU","Aundh",IF(LEFT(A47,2)="KO","Kondhwa","Sinhgad Road")) -> Aundh
A48: AU-046 | B48: Anaya Patil | C48: 2005-08-03 | D48: Male | E48: 9888106798 | F48: anaya.patil46@gmail.com | G48: 269, Aundh Pune | H48: Vidyanchal School | I48: 94 | J48: 9919781136 | K48: NEET | L48: 12 | M48: Morning | N48: 2024-03-01 | O48: 2025-02-24 | P48: R-114 | Q48: Offline | R48: Tue-Thu-Sat | S48: Chemistry | T48: Sneha Patil | U48: 2024-02-11 | V48: 2024-02-02 | W48: 36727 | X48: 35337 | Y48: 1390 | Z48: 4276 | AA48: Yes | AB48: =RANDBETWEEN(DATE(2025,7,1),DATE(2025,12,31)) -> 45880 | AC48: Partial | AD48: Cash | AE48: 3 | AF48: 71 | AG48: 88 | AH48: Average | AI48: 71 | AJ48: 44 | AK48: 18 | AL48: Family function | AM48: 40 | AN48: Yes | AO48: 2 | AP48: 1 | AQ48: 2024-04-11 | AR48: 2024-04-25 | AS48: No | AT48: Facebook Ad | AU48: Rahul Mehta | AV48: Active | AX48: =IF(LEFT(A48,2)="AU","Aundh",IF(LEFT(A48,2)="KO","Kondhwa","Sinhgad Road")) -> Aundh
A49: AU-005 | B49: Aaditya Kar | C49: 2005-05-12 | D49: Female | E49: 9817741407 | F49: anaya.desai5@gmail.com | G49: 559, Aundh Pune | H49: D.A.V. Public School | I49: 95 | J49: 9955609370 | K49: Foundation 8-10 | L49: 3 | M49: Evening | N49: 2024-02-27 | O49: 2024-05-27 | P49: R-119 | Q49: Hybrid | R49: Mon-Wed-Fri | S49: Physics | T49: Vikram Joshi | U49: 2024-03-06 | V49: 2024-03-06 | W49: 49463 | X49: 49078 | Y49: 385 | Z49: 1250 | AA49: No | AB49: =RANDBETWEEN(DATE(2025,7,1),DATE(2025,12,31)) -> 45982 | AC49: Partial | AD49: Cash | AE49: 5 | AF49: 86 | AG49: 96 | AH49: Average | AI49: 80 | AJ49: 47 | AK49: 17 | AL49: Sick leave | AM49: 36 | AN49: No | AO49: 4 | AP49: 4 | AQ49: 2024-04-30 | AR49: 2024-05-22 | AS49: Yes | AT49: Website | AU49: Rahul Mehta | AV49: Left | AW49: Lost interest | AX49: =IF(LEFT(A49,2)="AU","Aundh",IF(LEFT(A49,2)="KO","Kondhwa","Sinhgad Road")) -> Aundh
A50: AU-041 | B50: Anaya Desai | C50: 2005-02-27 | D50: Male | E50: 9858081282 | F50: anaya.desai41@gmail.com | G50: 300, Aundh Pune | H50: City School | I50: 84 | J50: 9921181487 | K50: JEE | L50: 3 | M50: Evening | N50: 2024-03-18 | O50: 2024-06-16 | P50: R-116 | Q50: Hybrid | R50: Tue-Thu-Sat | S50: Chemistry | T50: Preeti Desai | U50: 2024-03-28 | V50: 2024-03-18 | W50: 35441 | X50: 34902 | Y50: 539 | Z50: 3148 | AA50: No | AB50: =RANDBETWEEN(DATE(2025,7,1),DATE(2025,12,31)) -> 45925 | AC50: Partial | AD50: Bank Transfer | AE50: 5 | AF50: 62 | AG50: 71 | AH50: Needs Improvement | AI50: 91 | AJ50: 56 | AK50: 18 | AL50: Sick leave | AM50: 32 | AN50: Yes | AO50: 5 | AP50: 4 | AQ50: 2024-04-20 | AR50: 2024-05-08 | AS50: No | AT50: Walk-in | AU50: Nidhi Shah | AV50: Active | AX50: =IF(LEFT(A50,2)="AU","Aundh",IF(LEFT(A50,2)="KO","Kondhwa","Sinhgad Road")) -> Aundh
A51: AU-049 | B51: Reyansh Desai | C51: 2005-02-08 | D51: Male | E51: 9824864102 | F51: reyansh.desai49@gmail.com | G51: 228, Aundh Pune | H51: Modern College | I51: 61 | J51: 9996736981 | K51: MHT-CET | L51: 3 | M51: Morning | N51: 2024-02-24 | O51: 2024-05-24 | P51: R-103 | Q51: Offline | R51: Mon-Wed-Fri | S51: Chemistry | T51: Preeti Desai | U51: 2024-04-09 | V51: 2024-04-05 | W51: 22307 | X51: 21738 | Y51: 569 | Z51: 659 | AA51: No | AB51: =RANDBETWEEN(DATE(2025,7,1),DATE(2025,12,31)) -> 45849 | AC51: Partial | AD51: UPI | AE51: 10 | AF51: 47 | AG51: 51 | AH51: Average | AI51: 61 | AJ51: 57 | AK51: 16 | AM51: 28 | AN51: No | AO51: 3 | AP51: 2 | AQ51: 2024-05-02 | AR51: 2024-05-24 | AS51: No | AT51: Referral | AU51: Nidhi Shah | AV51: Left | AW51: Lost interest | AX51: =IF(LEFT(A51,2)="AU","Aundh",IF(LEFT(A51,2)="KO","Kondhwa","Sinhgad Road")) -> Aundh
A52: KO-001 | B52: aarav sharma | C52: 2006-01-24 | D52: Male | E52: 9820516378 | F52: ira.sharma1@gmail.com | G52: 135, Kondhwa Pune | H52: City School | I52: 75 | J52: 9960630401 | K52: JEE | L52: 3 | M52: Evening | N52: 2024-03-29 | O52: 2024-06-27 | P52: R-116 | Q52: Online | R52: Mon-Wed-Fri | S52: Maths | T52: Vikram Joshi | U52: 2024-04-07 | V52: 2024-03-28 | W52: 19153 | X52: 18645 | Y52: 508 | Z52: 533 | AA52: No | AC52: Partial | AD52: UPI | AE52: 4 | AF52: 80 | AG52: 85 | AH52: Good | AI52: 87 | AJ52: 28 | AK52: 21 | AL52: Family function | AM52: 75 | AN52: Yes | AO52: 5 | AP52: 3 | AQ52: 2024-04-29 | AR52: 2024-05-10 | AS52: No | AT52: Referral | AU52: Amit Deshmukh | AV52: Active | AX52: =IF(LEFT(A52,2)="AU","Aundh",IF(LEFT(A52,2)="KO","Kondhwa","Sinhgad Road")) -> Kondhwa
A53: KO-002 | B53: Aditya Kadam | C53: 2006-03-17 | D53: Female | E53: 9878822987 | F53: ayaan.kumar2@gmail.com | G53: 854, Kondhwa Pune | H53: Modern College | I53: 68 | J53: 9923127405 | K53: Crash Course | L53: 6 | M53: Afternoon | N53: 2024-01-21 | O53: 2024-07-19 | P53: R-107 | Q53: Online | R53: Tue-Thu-Sat | S53: English | T53: Sneha Patil | U53: 2024-03-13 | V53: 2024-03-05 | W53: 37083 | X53: 35376 | Y53: 1707 | Z53: 1810 | AA53: Yes | AB53: 2024-04-12 | AC53: Partial | AD53: Bank Transfer | AE53: 1 | AF53: 45 | AG53: 49 | AH53: Good | AI53: 91 | AJ53: 32 | AK53: 24 | AM53: 75 | AN53: Yes | AO53: 5 | AP53: 5 | AQ53: 2024-04-15 | AR53: 2024-05-12 | AS53: Yes | AT53: Walk-in | AU53: Nidhi Shah | AV53: Active | AX53: =IF(LEFT(A53,2)="AU","Aundh",IF(LEFT(A53,2)="KO","Kondhwa","Sinhgad Road")) -> Kondhwa
A54: KO-003 | B54: Aniket Jadhav | C54: 2005-12-11 | D54: Female | E54: 9883855337 | F54: kabir.desai3@gmail.com | G54: 938, Kondhwa Pune | H54: National School | I54: 71 | J54: 9937531545 | K54: NEET | L54: 6 | M54: Morning | N54: 2024-02-09 | O54: 2024-08-07 | P54: R-112 | Q54: Online | R54: Mon-Wed-Fri | S54: English | T54: Ravi Kumar | U54: 2024-03-09 | V54: 2024-03-09 | W54: 27152 | X54: 27006 | Y54: 146 | Z54: 201 | AA54: Yes | AB54: 2024-04-08 | AC54: Partial | AD54: UPI | AE54: 7 | AF54: 67 | AG54: 83 | AH54: Good | AI54: 70 | AJ54: 44 | AK54: 33 | AL54: Sick leave | AM54: 75 | AN54: No | AO54: 1 | AP54: 3 | AQ54: 2024-05-01 | AR54: 2024-05-28 | AS54: Yes | AT54: Website | AU54: Amit Deshmukh | AV54: Active | AX54: =IF(LEFT(A54,2)="AU","Aundh",IF(LEFT(A54,2)="KO","Kondhwa","Sinhgad Road")) -> Kondhwa
A55: KO-004 | B55: Meera Kumar | C55: 2005-01-23 | D55: Other | E55: 9813465115 | F55: meera.kumar4@gmail.com | G55: 632, Kondhwa Pune | H55: Vibgyor High School | I55: 73 | J55: 9962086928 | K55: Foundation 8-10 | L55: 12 | M55: Evening | N55: 2024-01-31 | O55: 2025-01-25 | P55: R-104 | Q55: Offline | R55: Mon-Wed-Fri | S55: Physics | T55: Ravi Kumar | U55: 2024-03-06 | V55: 2024-02-25 | W55: 43597 | X55: 42766 | Y55: 831 | Z55: 4331 | AA55: No | AC55: Partial | AD55: Card | AE55: 3 | AF55: 80 | AG55: 89 | AH55: Good | AI55: 65 | AJ55: 44 | AK55: 44 | AL55: Family function | AM55: 100 | AN55: No | AO55: 4 | AP55: 4 | AQ55: 2024-04-21 | AR55: 2024-05-02 | AS55: Yes | AT55: Website | AU55: Rahul Mehta | AV55: Left | AW55: Switched institute | AX55: =IF(LEFT(A55,2)="AU","Aundh",IF(LEFT(A55,2)="KO","Kondhwa","Sinhgad Road")) -> Kondhwa
A56: KO-005 | B56: Ira Kumar | C56: 2005-12-08 | D56: Female | E56: 9840533164 | F56: ira.kumar5@gmail.com | G56: 108, Kondhwa Pune | H56: Vibgyor High School | I56: 83 | J56: 9956227162 | K56: MHT-CET | L56: 12 | M56: Morning | N56: 2024-02-09 | O56: 2025-02-03 | P56: R-101 | Q56: Hybrid | R56: Mon-Wed-Fri | S56: English | T56: Preeti Desai | U56: 2024-03-12 | V56: 2024-03-11 | W56: 40999 | X56: 40345 | Y56: 654 | Z56: 737 | AA56: Yes | AB56: 2024-04-11 | AC56: Partial | AD56: UPI | AE56: 4 | AF56: 65 | AG56: 67 | AH56: Good | AI56: 71 | AJ56: 20 | AK56: 20 | AM56: 100 | AN56: Yes | AO56: 5 | AP56: 5 | AQ56: 2024-04-26 | AR56: 2024-05-23 | AS56: No | AT56: Referral | AU56: Nidhi Shah | AV56: Active | AX56: =IF(LEFT(A56,2)="AU","Aundh",IF(LEFT(A56,2)="KO","Kondhwa","Sinhgad Road")) -> Kondhwa
A57: KO-006 | B57: Atharva Gaikwad | C57: 2006-03-01 | D57: Male | E57: 9866100060 | F57: kabir.joshi6@gmail.com | G57: 773, Kondhwa Pune | H57: City School | I57: 84 | J57: 9919487688 | K57: Crash Course | L57: 6 | M57: Evening | N57: 2024-02-14 | O57: 2024-08-12 | P57: R-106 | Q57: Offline | R57: Tue-Thu-Sat | S57: Physics | T57: Sneha Patil | U57: 2024-02-04 | V57: 2024-01-28 | W57: 43066 | X57: 41360 | Y57: 1706 | Z57: 4896 | AA57: Yes | AB57: 2024-03-05 | AC57: Partial | AD57: Card | AE57: 8 | AF57: 70 | AG57: 83 | AH57: Good | AI57: 76 | AJ57: 60 | AK57: 37 | AL57: Family function | AM57: 61 | AN57: Yes | AO57: 2 | AP57: 3 | AQ57: 2024-03-19 | AR57: 2024-04-12 | AS57: Yes | AT57: Walk-in | AU57: Amit Deshmukh | AV57: Active | AX57: =IF(LEFT(A57,2)="AU","Aundh",IF(LEFT(A57,2)="KO","Kondhwa","Sinhgad Road")) -> Kondhwa
A58: KO-007 | B58: Chinmay Deo | C58: 2005-12-31 | D58: Other | E58: 9847917980 | F58: aarav.joshi7@gmail.com | G58: 436, Kondhwa Pune | H58: Modern College | I58: 82 | J58: 9918783761 | K58: JEE | L58: 3 | M58: Morning | N58: 2024-02-09 | O58: 2024-05-09 | P58: R-119 | Q58: Hybrid | R58: Mon-Wed-Fri | S58: Biology | T58: Vikram Joshi | U58: 2024-02-06 | V58: 2024-02-06 | W58: 36223 | X58: 34524 | Y58: 1699 | Z58: 2380 | AA58: No | AC58: Partial | AD58: Card | AE58: 7 | AF58: 71 | AG58: 97 | AH58: Needs Improvement | AI58: 97 | AJ58: 56 | AK58: 35 | AL58: Family function | AM58: 62 | AN58: Yes | AO58: 3 | AP58: 1 | AQ58: 2024-03-18 | AR58: 2024-04-06 | AS58: Yes | AT58: Facebook Ad | AU58: Nidhi Shah | AV58: Active | AX58: =IF(LEFT(A58,2)="AU","Aundh",IF(LEFT(A58,2)="KO","Kondhwa","Sinhgad Road")) -> Kondhwa
A59: KO-008 | B59: Aarav Patil | C59: 2005-01-05 | D59: Other | E59: 9815707436 | F59: aarav.patil8@gmail.com | G59: 568, Kondhwa Pune | H59: Modern College | I59: 75 | J59: 9974940573 | K59: NEET | L59: 6 | M59: Afternoon | N59: 2024-02-15 | O59: 2024-08-13 | P59: R-114 | Q59: Hybrid | R59: Mon-Wed-Fri | S59: English | T59: Vikram Joshi | U59: 2024-03-21 | V59: 2024-03-16 | W59: 32353 | X59: 29995 | Y59: 2358 | Z59: 2960 | AA59: Yes | AB59: 2024-04-20 | AC59: Partial | AD59: Card | AE59: 3 | AF59: 54 | AG59: 69 | AH59: Needs Improvement | AI59: 65 | AJ59: 53 | AK59: 33 | AL59: Sick leave | AM59: 62 | AN59: No | AO59: 5 | AP59: 1 | AQ59: 2024-05-09 | AR59: 2024-05-21 | AS59: No | AT59: Referral | AU59: Rahul Mehta | AV59: Active | AX59: =IF(LEFT(A59,2)="AU","Aundh",IF(LEFT(A59,2)="KO","Kondhwa","Sinhgad Road")) -> Kondhwa
A60: KO-009 | B60: Ira Patil | C60: 2006-03-08 | D60: Other | E60: 9811132840 | F60: ira.patil9@gmail.com | G60: 341, Kondhwa Pune | H60: City School | I60: 63 | J60: 9931242109 | K60: Foundation 8-10 | L60: 3 | M60: Evening | N60: 2024-04-01 | O60: 2024-06-30 | P60: R-106 | Q60: Offline | R60: Tue-Thu-Sat | S60: Chemistry | T60: Vikram Joshi | U60: 2024-04-09 | V60: 2024-04-08 | W60: 21182 | X60: 19925 | Y60: 1257 | Z60: 3889 | AA60: No | AC60: Partial | AD60: UPI | AE60: 10 | AF60: 82 | AG60: 98 | AH60: Average | AI60: 86 | AJ60: 35 | AK60: 32 | AL60: Family function | AM60: 91 | AN60: Yes | AO60: 2 | AP60: 4 | AQ60: 2024-06-03 | AR60: 2024-06-24 | AS60: Yes | AT60: Walk-in | AU60: Rahul Mehta | AV60: Left | AW60: Too far | AX60: =IF(LEFT(A60,2)="AU","Aundh",IF(LEFT(A60,2)="KO","Kondhwa","Sinhgad Road")) -> Kondhwa
A61: KO-010 | B61: Reyansh Joshi | C61: 2005-04-30 | D61: Female | E61: 9838109437 | F61: reyansh.joshi10@gmail.com | G61: 491, Kondhwa Pune | H61: City School | I61: 92 | J61: 9915632601 | K61: MHT-CET | L61: 6 | M61: Afternoon | N61: 2024-01-09 | O61: 2024-07-07 | P61: R-114 | Q61: Offline | R61: Tue-Thu-Sat | S61: Chemistry | T61: Anil Sharma | U61: 2024-05-26 | V61: 2024-05-16 | W61: 40487 | X61: 40461 | Y61: 26 | Z61: 2041 | AA61: No | AC61: Partial | AD61: UPI | AE61: 5 | AF61: 84 | AG61: 88 | AH61: Average | AI61: 80 | AJ61: 38 | AK61: 30 | AL61: Family function | AM61: 78 | AN61: No | AO61: 4 | AP61: 1 | AQ61: 2024-07-12 | AR61: 2024-08-09 | AS61: No | AT61: Referral | AU61: Amit Deshmukh | AV61: Left | AW61: Lost interest | AX61: =IF(LEFT(A61,2)="AU","Aundh",IF(LEFT(A61,2)="KO","Kondhwa","Sinhgad Road")) -> Kondhwa
A62: KO-011 | B62: Digvijay Mohite | C62: 2005-04-07 | D62: Other | E62: 9897268494 | F62: anaya.kumar11@gmail.com | G62: 505, Kondhwa Pune | H62: Vibgyor High School | I62: 71 | J62: 9947129787 | K62: MHT-CET | L62: 3 | M62: Morning | N62: 2024-01-27 | O62: 2024-04-26 | P62: R-106 | Q62: Hybrid | R62: Tue-Thu-Sat | S62: Physics | T62: Anil Sharma | U62: 2024-03-23 | V62: 2024-03-17 | W62: 29023 | X62: 28414 | Y62: 609 | Z62: 1370 | AA62: No | AC62: Partial | AD62: Bank Transfer | AE62: 6 | AF62: 87 | AG62: 92 | AH62: Good | AI62: 98 | AJ62: 24 | AK62: 22 | AL62: Sick leave | AM62: 91 | AN62: Yes | AO62: 1 | AP62: 5 | AQ62: 2024-04-20 | AR62: 2024-05-20 | AS62: Yes | AT62: Instagram Ad | AU62: Rahul Mehta | AV62: Active | AX62: =IF(LEFT(A62,2)="AU","Aundh",IF(LEFT(A62,2)="KO","Kondhwa","Sinhgad Road")) -> Kondhwa
A63: KO-012 | B63: Durvesh Raut | C63: 2006-02-27 | D63: Other | E63: 9842419650 | F63: kabir.kumar12@gmail.com | G63: 752, Kondhwa Pune | H63: Pearl Drop School | I63: 80 | J63: 9971241216 | K63: NEET | L63: 12 | M63: Morning | N63: 2024-03-23 | O63: 2025-03-18 | P63: R-105 | Q63: Offline | R63: Tue-Thu-Sat | S63: Chemistry | T63: Ravi Kumar | U63: 2024-02-25 | V63: 2024-02-20 | W63: 49929 | X63: 49526 | Y63: 403 | Z63: 3120 | AA63: No | AC63: Partial | AD63: Card | AE63: 6 | AF63: 78 | AG63: 94 | AH63: Needs Improvement | AI63: 61 | AJ63: 45 | AK63: 17 | AL63: Sick leave | AM63: 37 | AN63: No | AO63: 5 | AP63: 4 | AQ63: 2024-04-19 | AR63: 2024-05-04 | AS63: Yes | AT63: Instagram Ad | AU63: Amit Deshmukh | AV63: Left | AW63: Too far | AX63: =IF(LEFT(A63,2)="AU","Aundh",IF(LEFT(A63,2)="KO","Kondhwa","Sinhgad Road")) -> Kondhwa
A64: KO-013 | B64: Ayaan Joshi | C64: 2006-05-08 | D64: Female | E64: 9888835695 | F64: ayaan.joshi13@gmail.com | G64: 483, Kondhwa Pune | H64: City School | I64: 88 | J64: 9994913704 | K64: JEE | L64: 6 | M64: Afternoon | N64: 2024-02-26 | O64: 2024-08-24 | P64: R-102 | Q64: Online | R64: Mon-Wed-Fri | S64: Maths | T64: Ravi Kumar | U64: 2024-03-04 | V64: 2024-03-03 | W64: 24675 | X64: 23682 | Y64: 993 | Z64: 4194 | AA64: Yes | AB64: 2024-04-03 | AC64: Partial | AD64: Card | AE64: 10 | AF64: 87 | AG64: 90 | AH64: Needs Improvement | AI64: 91 | AJ64: 36 | AK64: 15 | AM64: 41 | AN64: No | AO64: 5 | AP64: 3 | AQ64: 2024-04-20 | AR64: 2024-05-05 | AS64: No | AT64: Facebook Ad | AU64: Amit Deshmukh | AV64: Active | AX64: =IF(LEFT(A64,2)="AU","Aundh",IF(LEFT(A64,2)="KO","Kondhwa","Sinhgad Road")) -> Kondhwa
A65: KO-014 | B65: Gandhar Kulkarni | C65: 2006-04-06 | D65: Other | E65: 9838598523 | F65: vivaan.joshi14@gmail.com | G65: 918, Kondhwa Pune | H65: National School | I65: 85 | J65: 9991414065 | K65: Foundation 8-10 | L65: 3 | M65: Evening | N65: 2024-02-03 | O65: 2024-05-03 | P65: R-103 | Q65: Hybrid | R65: Mon-Wed-Fri | S65: English | T65: Sneha Patil | U65: 2024-05-30 | V65: 2024-05-30 | W65: 45065 | X65: 40719 | Y65: 4346 | Z65: 4930 | AA65: Yes | AB65: 2024-06-29 | AC65: Partial | AD65: Cash | AE65: 7 | AF65: 76 | AG65: 99 | AH65: Average | AI65: 63 | AJ65: 51 | AK65: 20 | AM65: 100 | AN65: Yes | AO65: 3 | AP65: 5 | AQ65: 2024-07-17 | AR65: 2024-08-04 | AS65: Yes | AT65: Website | AU65: Nidhi Shah | AV65: Active | AX65: =IF(LEFT(A65,2)="AU","Aundh",IF(LEFT(A65,2)="KO","Kondhwa","Sinhgad Road")) -> Kondhwa
A66: KO-015 | B66: Hrishikesh Gokhale | C66: 2005-11-12 | D66: Other | E66: 9813103166 | F66: ira.sharma15@gmail.com | G66: 765, Kondhwa Pune | H66: National School | I66: 79 | J66: 9957663747 | K66: MHT-CET | L66: 12 | M66: Evening | N66: 2024-02-09 | O66: 2025-02-03 | P66: R-105 | Q66: Online | R66: Tue-Thu-Sat | S66: Biology | T66: Anil Sharma | U66: 2024-02-12 | V66: 2024-02-04 | W66: 35116 | X66: 32648 | Y66: 2468 | Z66: 3991 | AA66: Yes | AB66: 2024-03-13 | AC66: Partial | AD66: Bank Transfer | AE66: 8 | AF66: 90 | AG66: 96 | AH66: Good | AI66: 80 | AJ66: 36 | AK66: 36 | AL66: Family function | AM66: 100 | AN66: Yes | AO66: 3 | AP66: 5 | AQ66: 2024-03-25 | AR66: 2024-04-08 | AS66: No | AT66: Facebook Ad | AU66: Amit Deshmukh | AV66: Left | AW66: Lost interest | AX66: =IF(LEFT(A66,2)="AU","Aundh",IF(LEFT(A66,2)="KO","Kondhwa","Sinhgad Road")) -> Kondhwa
A67: KO-016 | B67: Jayant Apte | C67: 2006-03-14 | D67: Female | E67: 9882431812 | F67: aarav.joshi16@gmail.com | G67: 659, Kondhwa Pune | H67: Modern College | I67: 80 | J67: 9950609040 | K67: Foundation 8-10 | L67: 12 | M67: Afternoon | N67: 2024-01-30 | O67: 2025-01-24 | P67: R-116 | Q67: Hybrid | R67: Mon-Wed-Fri | S67: Chemistry | T67: Anil Sharma | U67: 2024-02-02 | V67: 2024-02-02 | W67: 44771 | X67: 43191 | Y67: 1580 | Z67: 1738 | AA67: No | AC67: Partial | AD67: Cash | AE67: 4 | AF67: 44 | AG67: 73 | AH67: Average | AI67: 85 | AJ67: 20 | AK67: 16 | AL67: Sick leave | AM67: 80 | AN67: No | AO67: 3 | AP67: 5 | AQ67: 2024-03-06 | AR67: 2024-03-29 | AS67: Yes | AT67: Instagram Ad | AU67: Amit Deshmukh | AV67: Active | AX67: =IF(LEFT(A67,2)="AU","Aundh",IF(LEFT(A67,2)="KO","Kondhwa","Sinhgad Road")) -> Kondhwa
A68: KO-017 | B68: Kedar Deshpande | C68: 2006-04-01 | D68: Male | E68: 9837640512 | F68: ira.sharma17@gmail.com | G68: 109, Kondhwa Pune | H68: Vibgyor High School | I68: 87 | J68: 9983413708 | K68: JEE | L68: 6 | M68: Morning | N68: 2024-01-21 | O68: 2024-07-19 | P68: R-118 | Q68: Offline | R68: Tue-Thu-Sat | S68: English | T68: Vikram Joshi | U68: 2024-05-14 | V68: 2024-05-08 | W68: 23886 | X68: 23471 | Y68: 415 | Z68: 1110 | AA68: No | AC68: Partial | AD68: Cash | AE68: 6 | AF68: 69 | AG68: 83 | AH68: Needs Improvement | AI68: 95 | AJ68: 22 | AK68: 16 | AL68: Sick leave | AM68: 72 | AN68: Yes | AO68: 5 | AP68: 5 | AQ68: 2024-06-06 | AR68: 2024-06-26 | AS68: Yes | AT68: Facebook Ad | AU68: Rahul Mehta | AV68: Active | AX68: =IF(LEFT(A68,2)="AU","Aundh",IF(LEFT(A68,2)="KO","Kondhwa","Sinhgad Road")) -> Kondhwa
A69: KO-018 | B69: Mandar Patwardhan | C69: 2005-03-18 | D69: Male | E69: 9892994642 | F69: ayaan.kumar18@gmail.com | G69: 142, Kondhwa Pune | H69: National School | I69: 94 | J69: 9984736836 | K69: NEET | L69: 6 | M69: Evening | N69: 2024-03-26 | O69: 2024-09-22 | P69: R-120 | Q69: Offline | R69: Mon-Wed-Fri | S69: English | T69: Ravi Kumar | U69: 2024-02-24 | V69: 2024-02-17 | W69: 45617 | X69: 45592 | Y69: 25 | Z69: 114 | AA69: No | AC69: Partial | AD69: Cash | AE69: 5 | AF69: 68 | AG69: 69 | AH69: Good | AI69: 63 | AJ69: 36 | AK69: 34 | AL69: Family function | AM69: 94 | AN69: No | AO69: 2 | AP69: 1 | AQ69: 2024-03-19 | AR69: 2024-04-12 | AS69: No | AT69: Walk-in | AU69: Amit Deshmukh | AV69: Active | AX69: =IF(LEFT(A69,2)="AU","Aundh",IF(LEFT(A69,2)="KO","Kondhwa","Sinhgad Road")) -> Kondhwa
A70: KO-019 | B70: Anaya Patil | C70: 2006-03-23 | D70: Other | E70: 9885650439 | F70: anaya.patil19@gmail.com | G70: 996, Kondhwa Pune | H70: Pearl Drop School | I70: 94 | J70: 9965936930 | K70: NEET | L70: 6 | M70: Evening | N70: 2024-01-02 | O70: 2024-06-30 | P70: R-103 | Q70: Hybrid | R70: Mon-Wed-Fri | S70: English | T70: Ravi Kumar | U70: 2024-03-04 | V70: 2024-02-26 | W70: 49351 | X70: 48701 | Y70: 650 | Z70: 2068 | AA70: No | AC70: Partial | AD70: Cash | AE70: 2 | AF70: 76 | AG70: 87 | AH70: Good | AI70: 65 | AJ70: 27 | AK70: 21 | AL70: Sick leave | AM70: 77 | AN70: Yes | AO70: 5 | AP70: 1 | AQ70: 2024-04-28 | AR70: 2024-05-17 | AS70: Yes | AT70: Website | AU70: Amit Deshmukh | AV70: Left | AW70: Switched institute | AX70: =IF(LEFT(A70,2)="AU","Aundh",IF(LEFT(A70,2)="KO","Kondhwa","Sinhgad Road")) -> Kondhwa
A71: KO-020 | B71: Siya Sharma | C71: 2005-12-27 | D71: Female | E71: 9865292883 | F71: siya.sharma20@gmail.com | G71: 225, Kondhwa Pune | H71: National School | I71: 86 | J71: 9960976895 | K71: Crash Course | L71: 6 | M71: Afternoon | N71: 2024-02-25 | O71: 2024-08-23 | P71: R-110 | Q71: Online | R71: Mon-Wed-Fri | S71: Maths | T71: Anil Sharma | U71: 2024-02-25 | V71: 2024-02-21 | W71: 17301 | X71: 16524 | Y71: 777 | Z71: 3434 | AA71: No | AC71: Partial | AD71: Cash | AE71: 6 | AF71: 69 | AG71: 89 | AH71: Needs Improvement | AI71: 67 | AJ71: 30 | AK71: 18 | AM71: 60 | AN71: Yes | AO71: 1 | AP71: 5 | AQ71: 2024-04-01 | AR71: 2024-04-27 | AS71: Yes | AT71: Walk-in | AU71: Amit Deshmukh | AV71: Active | AX71: =IF(LEFT(A71,2)="AU","Aundh",IF(LEFT(A71,2)="KO","Kondhwa","Sinhgad Road")) -> Kondhwa
A72: KO-021 | B72: Siya Desai | C72: 2005-03-08 | D72: Female | E72: 9845914193 | F72: siya.desai21@gmail.com | G72: 729, Kondhwa Pune | H72: National School | I72: 78 | J72: 9921504638 | K72: Foundation 8-10 | L72: 3 | M72: Morning | N72: 2024-01-01 | O72: 2024-03-31 | P72: R-106 | Q72: Online | R72: Mon-Wed-Fri | S72: Biology | T72: Vikram Joshi | U72: 2024-04-18 | V72: 2024-04-11 | W72: 19459 | X72: 17117 | Y72: 2342 | Z72: 3454 | AA72: No | AC72: Partial | AD72: Bank Transfer | AE72: 4 | AF72: 46 | AG72: 97 | AH72: Good | AI72: 97 | AJ72: 56 | AK72: 32 | AM72: 57 | AN72: No | AO72: 3 | AP72: 2 | AQ72: 2024-06-07 | AR72: 2024-06-18 | AS72: Yes | AT72: Instagram Ad | AU72: Amit Deshmukh | AV72: Active | AX72: =IF(LEFT(A72,2)="AU","Aundh",IF(LEFT(A72,2)="KO","Kondhwa","Sinhgad Road")) -> Kondhwa
A73: KO-022 | B73: Vivaan Joshi | C73: 2006-04-12 | D73: Female | E73: 9823040733 | F73: vivaan.joshi22@gmail.com | G73: 201, Kondhwa Pune | H73: City School | I73: 80 | J73: 9960370931 | K73: JEE | L73: 6 | M73: Evening | N73: 2024-01-18 | O73: 2024-07-16 | P73: R-105 | Q73: Online | R73: Mon-Wed-Fri | S73: Physics | T73: Sneha Patil | U73: 2024-03-22 | V73: 2024-03-13 | W73: 20924 | X73: 19348 | Y73: 1576 | Z73: 3300 | AA73: No | AC73: Partial | AD73: Cash | AE73: 3 | AF73: 48 | AG73: 99 | AH73: Good | AI73: 98 | AJ73: 30 | AK73: 19 | AM73: 63 | AN73: No | AO73: 5 | AP73: 3 | AQ73: 2024-05-05 | AR73: 2024-05-27 | AS73: No | AT73: Referral | AU73: Amit Deshmukh | AV73: Left | AW73: Switched institute | AX73: =IF(LEFT(A73,2)="AU","Aundh",IF(LEFT(A73,2)="KO","Kondhwa","Sinhgad Road")) -> Kondhwa
A74: KO-023 | B74: Ninad Sardesai | C74: 2006-06-13 | D74: Female | E74: 9844764313 | F74: ayaan.patil23@gmail.com | G74: 765, Kondhwa Pune | H74: City School | I74: 67 | J74: 9928374323 | K74: Crash Course | L74: 3 | M74: Evening | N74: 2024-03-15 | O74: 2024-06-13 | P74: R-116 | Q74: Offline | R74: Tue-Thu-Sat | S74: Physics | T74: Preeti Desai | U74: 2024-05-22 | V74: 2024-05-22 | W74: 47341 | X74: 46395 | Y74: 946 | Z74: 1891 | AA74: No | AC74: Partial | AD74: UPI | AE74: 2 | AF74: 70 | AG74: 89 | AH74: Average | AI74: 80 | AJ74: 44 | AK74: 28 | AL74: Sick leave | AM74: 63 | AN74: No | AO74: 1 | AP74: 2 | AQ74: 2024-07-18 | AR74: 2024-08-03 | AS74: No | AT74: Referral | AU74: Amit Deshmukh | AV74: Active | AX74: =IF(LEFT(A74,2)="AU","Aundh",IF(LEFT(A74,2)="KO","Kondhwa","Sinhgad Road")) -> Kondhwa
A75: KO-024 | B75: Reyansh Kumar | C75: 2006-04-20 | D75: Other | E75: 9890541119 | F75: reyansh.kumar24@gmail.com | G75: 254, Kondhwa Pune | H75: Pearl Drop School | I75: 87 | J75: 9949929000 | K75: JEE | L75: 3 | M75: Evening | N75: 2024-03-10 | O75: 2024-06-08 | P75: R-109 | Q75: Hybrid | R75: Mon-Wed-Fri | S75: Biology | T75: Anil Sharma | U75: 2024-03-01 | V75: 2024-02-24 | W75: 26352 | X75: 25125 | Y75: 1227 | Z75: 2445 | AA75: Yes | AB75: 2024-03-31 | AC75: Partial | AD75: UPI | AE75: 2 | AF75: 54 | AG75: 73 | AH75: Average | AI75: 64 | AJ75: 23 | AK75: 20 | AL75: Sick leave | AM75: 86 | AN75: Yes | AO75: 5 | AP75: 4 | AQ75: 2024-04-18 | AR75: 2024-04-28 | AS75: Yes | AT75: Instagram Ad | AU75: Nidhi Shah | AV75: Left | AW75: Lost interest | AX75: =IF(LEFT(A75,2)="AU","Aundh",IF(LEFT(A75,2)="KO","Kondhwa","Sinhgad Road")) -> Kondhwa
A76: KO-025 | B76: Prathamesh Kulkarni | C76: 2005-11-07 | D76: Male | E76: 9846010242 | F76: ayaan.patil25@gmail.com | G76: 867, Kondhwa Pune | H76: Modern College | I76: 64 | J76: 9964086262 | K76: Crash Course | L76: 6 | M76: Evening | N76: 2024-01-17 | O76: 2024-07-15 | P76: R-113 | Q76: Online | R76: Tue-Thu-Sat | S76: Maths | T76: Vikram Joshi | U76: 2024-05-09 | V76: 2024-05-09 | W76: 42875 | X76: 42345 | Y76: 530 | Z76: 4954 | AA76: No | AC76: Partial | AD76: Bank Transfer | AE76: 10 | AF76: 55 | AG76: 92 | AH76: Good | AI76: 79 | AJ76: 51 | AK76: 34 | AM76: 66 | AN76: Yes | AO76: 3 | AP76: 1 | AQ76: 2024-06-18 | AR76: 2024-07-07 | AS76: Yes | AT76: Facebook Ad | AU76: Amit Deshmukh | AV76: Active | AX76: =IF(LEFT(A76,2)="AU","Aundh",IF(LEFT(A76,2)="KO","Kondhwa","Sinhgad Road")) -> Kondhwa
A77: KO-026 | B77: Kabir Kumar | C77: 2005-04-26 | D77: Male | E77: 9879412684 | F77: kabir.kumar26@gmail.com | G77: 844, Kondhwa Pune | H77: National School | I77: 75 | J77: 9992220005 | K77: NEET | L77: 3 | M77: Morning | N77: 2024-03-22 | O77: 2024-06-20 | P77: R-113 | Q77: Offline | R77: Mon-Wed-Fri | S77: Physics | T77: Vikram Joshi | U77: 2024-04-17 | V77: 2024-04-12 | W77: 42522 | X77: 40345 | Y77: 2177 | Z77: 4432 | AA77: Yes | AB77: 2024-05-17 | AC77: Partial | AD77: Bank Transfer | AE77: 3 | AF77: 90 | AG77: 91 | AH77: Needs Improvement | AI77: 95 | AJ77: 45 | AK77: 45 | AL77: Sick leave | AM77: 100 | AN77: Yes | AO77: 4 | AP77: 4 | AQ77: 2024-05-14 | AR77: 2024-06-10 | AS77: Yes | AT77: Facebook Ad | AU77: Amit Deshmukh | AV77: Active | AX77: =IF(LEFT(A77,2)="AU","Aundh",IF(LEFT(A77,2)="KO","Kondhwa","Sinhgad Road")) -> Kondhwa
A78: KO-027 | B78: Meera Joshi | C78: 2005-12-05 | D78: Other | E78: 9883455453 | F78: meera.joshi27@gmail.com | G78: 379, Kondhwa Pune | H78: Vibgyor High School | I78: 83 | J78: 9992250304 | K78: Crash Course | L78: 6 | M78: Evening | N78: 2024-01-07 | O78: 2024-07-05 | P78: R-117 | Q78: Offline | R78: Tue-Thu-Sat | S78: English | T78: Sneha Patil | U78: 2024-04-22 | V78: 2024-04-22 | W78: 15553 | X78: 13040 | Y78: 2513 | Z78: 3819 | AA78: Yes | AB78: 2024-05-22 | AC78: Partial | AD78: Cash | AE78: 7 | AF78: 42 | AG78: 93 | AH78: Good | AI78: 69 | AJ78: 59 | AK78: 17 | AL78: Family function | AM78: 28 | AN78: Yes | AO78: 3 | AP78: 3 | AQ78: 2024-06-04 | AR78: 2024-06-21 | AS78: Yes | AT78: Referral | AU78: Rahul Mehta | AV78: Active | AX78: =IF(LEFT(A78,2)="AU","Aundh",IF(LEFT(A78,2)="KO","Kondhwa","Sinhgad Road")) -> Kondhwa
A79: KO-028 | B79: Rahul Shinde | C79: 2005-11-09 | D79: Other | E79: 9849208957 | F79: ayaan.desai28@gmail.com | G79: 730, Kondhwa Pune | H79: City School | I79: 63 | J79: 9925812635 | K79: NEET | L79: 6 | M79: Afternoon | N79: 2024-02-07 | O79: 2024-08-05 | P79: R-105 | Q79: Offline | R79: Mon-Wed-Fri | S79: Physics | T79: Sneha Patil | U79: 2024-03-12 | V79: 2024-03-09 | W79: 44415 | X79: 41446 | Y79: 2969 | Z79: 3247 | AA79: No | AC79: Partial | AD79: Card | AE79: 8 | AF79: 48 | AG79: 60 | AH79: Needs Improvement | AI79: 63 | AJ79: 55 | AK79: 29 | AM79: 52 | AN79: Yes | AO79: 2 | AP79: 4 | AQ79: 2024-04-17 | AR79: 2024-05-03 | AS79: Yes | AT79: Facebook Ad | AU79: Rahul Mehta | AV79: Left | AW79: Too far | AX79: =IF(LEFT(A79,2)="AU","Aundh",IF(LEFT(A79,2)="KO","Kondhwa","Sinhgad Road")) -> Kondhwa
A80: KO-029 | B80: Ritesh Surve | C80: 2005-09-15 | D80: Male | E80: 9813572188 | F80: vivaan.sharma29@gmail.com | G80: 457, Kondhwa Pune | H80: National School | I80: 63 | J80: 9946975129 | K80: Foundation 8-10 | L80: 12 | M80: Evening | N80: 2024-04-06 | O80: 2025-04-01 | P80: R-113 | Q80: Hybrid | R80: Tue-Thu-Sat | S80: Biology | T80: Sneha Patil | U80: 2024-02-27 | V80: 2024-02-26 | W80: 28843 | X80: 27816 | Y80: 1027 | Z80: 2145 | AA80: Yes | AB80: 2024-03-28 | AC80: Partial | AD80: Card | AE80: 4 | AF80: 87 | AG80: 89 | AH80: Needs Improvement | AI80: 78 | AJ80: 58 | AK80: 34 | AL80: Sick leave | AM80: 58 | AN80: No | AO80: 1 | AP80: 1 | AQ80: 2024-04-04 | AR80: 2024-05-04 | AS80: No | AT80: Website | AU80: Amit Deshmukh | AV80: Left | AW80: Too far | AX80: =IF(LEFT(A80,2)="AU","Aundh",IF(LEFT(A80,2)="KO","Kondhwa","Sinhgad Road")) -> Kondhwa
A81: KO-030 | B81: Sanket Kanade | C81: 2006-03-22 | D81: Other | E81: 9818710767 | F81: kabir.desai30@gmail.com | G81: 173, Kondhwa Pune | H81: Modern College | I81: 85 | J81: 9942556025 | K81: Foundation 8-10 | L81: 3 | M81: Afternoon | N81: 2024-02-04 | O81: 2024-05-04 | P81: R-102 | Q81: Offline | R81: Tue-Thu-Sat | S81: Chemistry | T81: Sneha Patil | U81: 2024-05-27 | V81: 2024-05-19 | W81: 41233 | X81: 40131 | Y81: 1102 | Z81: 1170 | AA81: No | AC81: Partial | AD81: Cash | AE81: 9 | AF81: 66 | AG81: 99 | AH81: Needs Improvement | AI81: 75 | AJ81: 28 | AK81: 24 | AL81: Family function | AM81: 85 | AN81: No | AO81: 4 | AP81: 3 | AQ81: 2024-06-24 | AR81: 2024-07-16 | AS81: Yes | AT81: Website | AU81: Amit Deshmukh | AV81: Active | AX81: =IF(LEFT(A81,2)="AU","Aundh",IF(LEFT(A81,2)="KO","Kondhwa","Sinhgad Road")) -> Kondhwa
A82: KO-031 | B82: Kabir Sharma | C82: 2006-08-15 | D82: Male | E82: 9823091195 | F82: kabir.sharma31@gmail.com | G82: 368, Kondhwa Pune | H82: City School | I82: 62 | J82: 9998579774 | K82: NEET | L82: 6 | M82: Afternoon | N82: 2024-02-01 | O82: 2024-07-30 | P82: R-104 | Q82: Hybrid | R82: Mon-Wed-Fri | S82: Chemistry | T82: Preeti Desai | U82: 2024-02-03 | V82: 2024-02-02 | W82: 19610 | X82: 17405 | Y82: 2205 | Z82: 2990 | AA82: Yes | AB82: 2024-03-04 | AC82: Partial | AD82: Cash | AE82: 4 | AF82: 40 | AG82: 92 | AH82: Needs Improvement | AI82: 62 | AJ82: 22 | AK82: 15 | AL82: Sick leave | AM82: 68 | AN82: No | AO82: 1 | AP82: 4 | AQ82: 2024-02-25 | AR82: 2024-03-07 | AS82: Yes | AT82: Website | AU82: Nidhi Shah | AV82: Active | AX82: =IF(LEFT(A82,2)="AU","Aundh",IF(LEFT(A82,2)="KO","Kondhwa","Sinhgad Road")) -> Kondhwa
A83: KO-032 | B83: Aarav Joshi | C83: 2005-08-24 | D83: Female | E83: 9823163100 | F83: aarav.joshi32@gmail.com | G83: 570, Kondhwa Pune | H83: City School | I83: 95 | J83: 9951456148 | K83: Foundation 8-10 | L83: 3 | M83: Afternoon | N83: 2024-01-23 | O83: 2024-04-22 | P83: R-117 | Q83: Offline | R83: Tue-Thu-Sat | S83: English | T83: Ravi Kumar | U83: 2024-05-26 | V83: 2024-05-24 | W83: 27420 | X83: 25321 | Y83: 2099 | Z83: 4452 | AA83: Yes | AB83: 2024-06-25 | AC83: Partial | AD83: Card | AE83: 7 | AF83: 84 | AG83: 84 | AH83: Needs Improvement | AI83: 86 | AJ83: 34 | AK83: 28 | AL83: Sick leave | AM83: 82 | AN83: Yes | AO83: 1 | AP83: 3 | AQ83: 2024-07-05 | AR83: 2024-07-16 | AS83: No | AT83: Website | AU83: Rahul Mehta | AV83: Active | AX83: =IF(LEFT(A83,2)="AU","Aundh",IF(LEFT(A83,2)="KO","Kondhwa","Sinhgad Road")) -> Kondhwa
A84: KO-033 | B84: Shantanu Phadke | C84: 2005-02-14 | D84: Other | E84: 9845663219 | F84: ayaan.desai33@gmail.com | G84: 770, Kondhwa Pune | H84: Vibgyor High School | I84: 62 | J84: 9995810839 | K84: Crash Course | L84: 12 | M84: Evening | N84: 2024-01-07 | O84: 2025-01-01 | P84: R-112 | Q84: Offline | R84: Mon-Wed-Fri | S84: Chemistry | T84: Anil Sharma | U84: 2024-05-26 | V84: 2024-05-16 | W84: 15888 | X84: 15810 | Y84: 78 | Z84: 616 | AA84: Yes | AB84: 2024-06-25 | AC84: Partial | AD84: UPI | AE84: 3 | AF84: 68 | AG84: 90 | AH84: Good | AI84: 96 | AJ84: 22 | AK84: 19 | AL84: Family function | AM84: 86 | AN84: Yes | AO84: 1 | AP84: 3 | AQ84: 2024-07-04 | AR84: 2024-07-17 | AS84: No | AT84: Referral | AU84: Nidhi Shah | AV84: Left | AW84: Too far | AX84: =IF(LEFT(A84,2)="AU","Aundh",IF(LEFT(A84,2)="KO","Kondhwa","Sinhgad Road")) -> Kondhwa
A85: KO-034 | B85: Ayaan Patil | C85: 2006-03-18 | D85: Other | E85: 9813245131 | F85: ayaan.patil34@gmail.com | G85: 189, Kondhwa Pune | H85: Pearl Drop School | I85: 64 | J85: 9989493829 | K85: JEE | L85: 12 | M85: Morning | N85: 2024-02-28 | O85: 2025-02-22 | P85: R-102 | Q85: Offline | R85: Mon-Wed-Fri | S85: Biology | T85: Preeti Desai | U85: 2024-04-05 | V85: 2024-03-29 | W85: 19311 | X85: 16449 | Y85: 2862 | Z85: 4409 | AA85: Yes | AB85: 2024-05-05 | AC85: Partial | AD85: Bank Transfer | AE85: 6 | AF85: 57 | AG85: 99 | AH85: Average | AI85: 78 | AJ85: 37 | AK85: 21 | AM85: 56 | AN85: Yes | AO85: 2 | AP85: 3 | AQ85: 2024-05-21 | AR85: 2024-06-12 | AS85: No | AT85: Instagram Ad | AU85: Nidhi Shah | AV85: Left | AW85: Lost interest | AX85: =IF(LEFT(A85,2)="AU","Aundh",IF(LEFT(A85,2)="KO","Kondhwa","Sinhgad Road")) -> Kondhwa
A86: KO-035 | B86: Kabir Desai | C86: 2005-11-22 | D86: Male | E86: 9880297576 | F86: kabir.desai35@gmail.com | G86: 677, Kondhwa Pune | H86: City School | I86: 68 | J86: 9975351562 | K86: NEET | L86: 12 | M86: Morning | N86: 2024-04-10 | O86: 2025-04-05 | P86: R-111 | Q86: Online | R86: Mon-Wed-Fri | S86: Maths | T86: Sneha Patil | U86: 2024-04-12 | V86: 2024-04-09 | W86: 20458 | X86: 19978 | Y86: 480 | Z86: 2660 | AA86: No | AC86: Partial | AD86: Card | AE86: 3 | AF86: 88 | AG86: 93 | AH86: Good | AI86: 61 | AJ86: 35 | AK86: 19 | AM86: 54 | AN86: Yes | AO86: 4 | AP86: 1 | AQ86: 2024-05-04 | AR86: 2024-05-20 | AS86: No | AT86: Facebook Ad | AU86: Amit Deshmukh | AV86: Active | AX86: =IF(LEFT(A86,2)="AU","Aundh",IF(LEFT(A86,2)="KO","Kondhwa","Sinhgad Road")) -> Kondhwa
A87: KO-036 | B87: Shreyas Dixit | C87: 2006-03-16 | D87: Other | E87: 9878481588 | F87: ira.desai36@gmail.com | G87: 461, Kondhwa Pune | H87: National School | I87: 65 | J87: 9987589202 | K87: NEET | L87: 12 | M87: Afternoon | N87: 2024-04-08 | O87: 2025-04-03 | P87: R-102 | Q87: Online | R87: Tue-Thu-Sat | S87: Maths | T87: Vikram Joshi | U87: 2024-04-16 | V87: 2024-04-13 | W87: 29622 | X87: 29427 | Y87: 195 | Z87: 1746 | AA87: No | AC87: Partial | AD87: UPI | AE87: 2 | AF87: 58 | AG87: 94 | AH87: Average | AI87: 64 | AJ87: 52 | AK87: 26 | AL87: Family function | AM87: 50 | AN87: Yes | AO87: 3 | AP87: 5 | AQ87: 2024-05-17 | AR87: 2024-06-12 | AS87: No | AT87: Facebook Ad | AU87: Rahul Mehta | AV87: Active | AX87: =IF(LEFT(A87,2)="AU","Aundh",IF(LEFT(A87,2)="KO","Kondhwa","Sinhgad Road")) -> Kondhwa
A88: KO-037 | B88: Reyansh Patil | C88: 2005-06-16 | D88: Other | E88: 9854656175 | F88: reyansh.patil37@gmail.com | G88: 285, Kondhwa Pune | H88: Pearl Drop School | I88: 93 | J88: 9936768133 | K88: Foundation 8-10 | L88: 3 | M88: Afternoon | N88: 2024-02-26 | O88: 2024-05-26 | P88: R-116 | Q88: Offline | R88: Tue-Thu-Sat | S88: Maths | T88: Preeti Desai | U88: 2024-04-02 | V88: 2024-03-27 | W88: 25776 | X88: 25030 | Y88: 746 | Z88: 2823 | AA88: No | AC88: Partial | AD88: Card | AE88: 8 | AF88: 42 | AG88: 95 | AH88: Needs Improvement | AI88: 82 | AJ88: 32 | AK88: 32 | AL88: Family function | AM88: 100 | AN88: No | AO88: 2 | AP88: 4 | AQ88: 2024-05-09 | AR88: 2024-05-29 | AS88: No | AT88: Referral | AU88: Rahul Mehta | AV88: Left | AW88: Lost interest | AX88: =IF(LEFT(A88,2)="AU","Aundh",IF(LEFT(A88,2)="KO","Kondhwa","Sinhgad Road")) -> Kondhwa
A89: KO-038 | B89: Ira Desai | C89: 2005-01-10 | D89: Male | E89: 9891926020 | F89: ira.desai38@gmail.com | G89: 224, Kondhwa Pune | H89: Modern College | I89: 88 | J89: 9918248808 | K89: Foundation 8-10 | L89: 6 | M89: Afternoon | N89: 2024-03-06 | O89: 2024-09-02 | P89: R-111 | Q89: Online | R89: Mon-Wed-Fri | S89: English | T89: Ravi Kumar | U89: 2024-03-18 | V89: 2024-03-13 | W89: 42342 | X89: 40311 | Y89: 2031 | Z89: 4137 | AA89: Yes | AB89: 2024-04-17 | AC89: Partial | AD89: Cash | AE89: 6 | AF89: 48 | AG89: 86 | AH89: Needs Improvement | AI89: 73 | AJ89: 28 | AK89: 15 | AL89: Sick leave | AM89: 53 | AN89: No | AO89: 2 | AP89: 3 | AQ89: 2024-05-09 | AR89: 2024-05-21 | AS89: No | AT89: Walk-in | AU89: Nidhi Shah | AV89: Active | AX89: =IF(LEFT(A89,2)="AU","Aundh",IF(LEFT(A89,2)="KO","Kondhwa","Sinhgad Road")) -> Kondhwa
A90: KO-039 | B90: Kabir Joshi | C90: 2005-12-01 | D90: Female | E90: 9843471255 | F90: kabir.joshi39@gmail.com | G90: 277, Kondhwa Pune | H90: Modern College | I90: 67 | J90: 9946705761 | K90: NEET | L90: 6 | M90: Afternoon | N90: 2024-01-06 | O90: 2024-07-04 | P90: R-113 | Q90: Online | R90: Mon-Wed-Fri | S90: English | T90: Preeti Desai | U90: 2024-04-19 | V90: 2024-04-09 | W90: 29354 | X90: 28991 | Y90: 363 | Z90: 2575 | AA90: Yes | AB90: 2024-05-19 | AC90: Partial | AD90: Card | AE90: 2 | AF90: 44 | AG90: 77 | AH90: Needs Improvement | AI90: 96 | AJ90: 39 | AK90: 28 | AL90: Family function | AM90: 71 | AN90: No | AO90: 1 | AP90: 4 | AQ90: 2024-06-13 | AR90: 2024-07-03 | AS90: No | AT90: Website | AU90: Amit Deshmukh | AV90: Left | AW90: Lost interest | AX90: =IF(LEFT(A90,2)="AU","Aundh",IF(LEFT(A90,2)="KO","Kondhwa","Sinhgad Road")) -> Kondhwa
A91: KO-040 | B91: Kabir Patil | C91: 2005-12-19 | D91: Other | E91: 9828907536 | F91: kabir.patil40@gmail.com | G91: 980, Kondhwa Pune | H91: City School | I91: 64 | J91: 9997928087 | K91: Crash Course | L91: 3 | M91: Evening | N91: 2024-02-15 | O91: 2024-05-15 | P91: R-104 | Q91: Hybrid | R91: Tue-Thu-Sat | S91: Physics | T91: Vikram Joshi | U91: 2024-03-12 | V91: 2024-03-05 | W91: 40169 | X91: 40126 | Y91: 43 | Z91: 745 | AA91: No | AC91: Partial | AD91: Cash | AE91: 8 | AF91: 59 | AG91: 62 | AH91: Good | AI91: 75 | AJ91: 42 | AK91: 36 | AL91: Family function | AM91: 85 | AN91: Yes | AO91: 5 | AP91: 5 | AQ91: 2024-05-05 | AR91: 2024-05-21 | AS91: No | AT91: Referral | AU91: Amit Deshmukh | AV91: Left | AW91: Too far | AX91: =IF(LEFT(A91,2)="AU","Aundh",IF(LEFT(A91,2)="KO","Kondhwa","Sinhgad Road")) -> Kondhwa
A92: KO-041 | B92: Ira Sharma | C92: 2005-08-09 | D92: Other | E92: 9858231993 | F92: ira.sharma41@gmail.com | G92: 917, Kondhwa Pune | H92: Modern College | I92: 69 | J92: 9923659135 | K92: MHT-CET | L92: 3 | M92: Morning | N92: 2024-03-25 | O92: 2024-06-23 | P92: R-104 | Q92: Hybrid | R92: Tue-Thu-Sat | S92: Maths | T92: Ravi Kumar | U92: 2024-03-21 | V92: 2024-03-18 | W92: 43998 | X92: 41712 | Y92: 2286 | Z92: 2947 | AA92: No | AC92: Partial | AD92: Card | AE92: 4 | AF92: 45 | AG92: 86 | AH92: Average | AI92: 79 | AJ92: 27 | AK92: 22 | AL92: Sick leave | AM92: 81 | AN92: Yes | AO92: 4 | AP92: 2 | AQ92: 2024-05-03 | AR92: 2024-05-30 | AS92: No | AT92: Walk-in | AU92: Amit Deshmukh | AV92: Left | AW92: Switched institute | AX92: =IF(LEFT(A92,2)="AU","Aundh",IF(LEFT(A92,2)="KO","Kondhwa","Sinhgad Road")) -> Kondhwa
A93: KO-042 | B93: Anaya Kumar | C93: 2005-09-09 | D93: Other | E93: 9837196046 | F93: anaya.kumar42@gmail.com | G93: 321, Kondhwa Pune | H93: Pearl Drop School | I93: 70 | J93: 9982250950 | K93: Foundation 8-10 | L93: 6 | M93: Afternoon | N93: 2024-03-23 | O93: 2024-09-19 | P93: R-116 | Q93: Hybrid | R93: Tue-Thu-Sat | S93: Chemistry | T93: Ravi Kumar | U93: 2024-03-07 | V93: 2024-03-06 | W93: 42034 | X93: 41968 | Y93: 66 | Z93: 89 | AA93: No | AC93: Partial | AD93: Card | AE93: 1 | AF93: 43 | AG93: 75 | AH93: Average | AI93: 96 | AJ93: 57 | AK93: 39 | AL93: Family function | AM93: 68 | AN93: Yes | AO93: 3 | AP93: 4 | AQ93: 2024-04-13 | AR93: 2024-05-08 | AS93: Yes | AT93: Referral | AU93: Rahul Mehta | AV93: Left | AW93: Switched institute | AX93: =IF(LEFT(A93,2)="AU","Aundh",IF(LEFT(A93,2)="KO","Kondhwa","Sinhgad Road")) -> Kondhwa
A94: KO-043 | B94: Ira Joshi | C94: 2006-04-06 | D94: Male | E94: 9823703480 | F94: ira.joshi43@gmail.com | G94: 647, Kondhwa Pune | H94: City School | I94: 63 | J94: 9915335627 | K94: Crash Course | L94: 6 | M94: Evening | N94: 2024-04-07 | O94: 2024-10-04 | P94: R-113 | Q94: Online | R94: Tue-Thu-Sat | S94: Chemistry | T94: Anil Sharma | U94: 2024-04-24 | V94: 2024-04-24 | W94: 40019 | X94: 38945 | Y94: 1074 | Z94: 2647 | AA94: No | AC94: Partial | AD94: Bank Transfer | AE94: 6 | AF94: 83 | AG94: 88 | AH94: Average | AI94: 81 | AJ94: 43 | AK94: 37 | AL94: Sick leave | AM94: 86 | AN94: Yes | AO94: 5 | AP94: 5 | AQ94: 2024-05-29 | AR94: 2024-06-12 | AS94: No | AT94: Website | AU94: Rahul Mehta | AV94: Left | AW94: Too far | AX94: =IF(LEFT(A94,2)="AU","Aundh",IF(LEFT(A94,2)="KO","Kondhwa","Sinhgad Road")) -> Kondhwa
A95: KO-044 | B95: Vivaan Patil | C95: 2006-02-05 | D95: Other | E95: 9894231097 | F95: vivaan.patil44@gmail.com | G95: 793, Kondhwa Pune | H95: Vibgyor High School | I95: 86 | J95: 9921053780 | K95: MHT-CET | L95: 3 | M95: Afternoon | N95: 2024-01-07 | O95: 2024-04-06 | P95: R-116 | Q95: Offline | R95: Tue-Thu-Sat | S95: Maths | T95: Vikram Joshi | U95: 2024-02-10 | V95: 2024-02-01 | W95: 17440 | X95: 16885 | Y95: 555 | Z95: 624 | AA95: Yes | AB95: 2024-03-11 | AC95: Partial | AD95: Bank Transfer | AE95: 6 | AF95: 60 | AG95: 62 | AH95: Average | AI95: 97 | AJ95: 22 | AK95: 15 | AL95: Sick leave | AM95: 68 | AN95: No | AO95: 1 | AP95: 5 | AQ95: 2024-03-14 | AR95: 2024-03-25 | AS95: No | AT95: Walk-in | AU95: Nidhi Shah | AV95: Left | AW95: Switched institute | AX95: =IF(LEFT(A95,2)="AU","Aundh",IF(LEFT(A95,2)="KO","Kondhwa","Sinhgad Road")) -> Kondhwa
A96: KO-045 | B96: Vivaan Sharma | C96: 2005-01-13 | D96: Female | E96: 9816422378 | F96: vivaan.sharma45@gmail.com | G96: 907, Kondhwa Pune | H96: Modern College | I96: 75 | J96: 9939556989 | K96: Crash Course | L96: 12 | M96: Evening | N96: 2024-04-10 | O96: 2025-04-05 | P96: R-113 | Q96: Offline | R96: Mon-Wed-Fri | S96: Maths | T96: Sneha Patil | U96: 2024-03-13 | V96: 2024-03-04 | W96: 16030 | X96: 15752 | Y96: 278 | Z96: 678 | AA96: No | AC96: Partial | AD96: UPI | AE96: 5 | AF96: 55 | AG96: 92 | AH96: Average | AI96: 63 | AJ96: 43 | AK96: 40 | AL96: Family function | AM96: 93 | AN96: No | AO96: 5 | AP96: 4 | AQ96: 2024-05-02 | AR96: 2024-05-28 | AS96: Yes | AT96: Website | AU96: Rahul Mehta | AV96: Left | AW96: Too far | AX96: =IF(LEFT(A96,2)="AU","Aundh",IF(LEFT(A96,2)="KO","Kondhwa","Sinhgad Road")) -> Kondhwa
A97: KO-046 | B97: Meera Sharma | C97: 2005-08-13 | D97: Other | E97: 9814668143 | F97: meera.sharma46@gmail.com | G97: 241, Kondhwa Pune | H97: Pearl Drop School | I97: 88 | J97: 9963154851 | K97: NEET | L97: 3 | M97: Morning | N97: 2024-03-05 | O97: 2024-06-03 | P97: R-111 | Q97: Offline | R97: Tue-Thu-Sat | S97: Chemistry | T97: Vikram Joshi | U97: 2024-05-20 | V97: 2024-05-20 | W97: 25558 | X97: 23782 | Y97: 1776 | Z97: 3810 | AA97: No | AC97: Partial | AD97: UPI | AE97: 6 | AF97: 46 | AG97: 93 | AH97: Good | AI97: 92 | AJ97: 52 | AK97: 29 | AL97: Family function | AM97: 55 | AN97: Yes | AO97: 2 | AP97: 3 | AQ97: 2024-07-06 | AR97: 2024-07-31 | AS97: Yes | AT97: Facebook Ad | AU97: Rahul Mehta | AV97: Left | AW97: Lost interest | AX97: =IF(LEFT(A97,2)="AU","Aundh",IF(LEFT(A97,2)="KO","Kondhwa","Sinhgad Road")) -> Kondhwa
A98: KO-047 | B98: Ayaan Kumar | C98: 2005-11-29 | D98: Male | E98: 9814859663 | F98: ayaan.kumar47@gmail.com | G98: 845, Kondhwa Pune | H98: Vibgyor High School | I98: 71 | J98: 9993595692 | K98: JEE | L98: 3 | M98: Afternoon | N98: 2024-02-07 | O98: 2024-05-07 | P98: R-108 | Q98: Hybrid | R98: Tue-Thu-Sat | S98: Chemistry | T98: Ravi Kumar | U98: 2024-04-25 | V98: 2024-04-20 | W98: 43187 | X98: 40324 | Y98: 2863 | Z98: 2874 | AA98: Yes | AB98: 2024-05-25 | AC98: Partial | AD98: Card | AE98: 6 | AF98: 70 | AG98: 82 | AH98: Needs Improvement | AI98: 81 | AJ98: 23 | AK98: 18 | AM98: 78 | AN98: No | AO98: 5 | AP98: 5 | AQ98: 2024-06-04 | AR98: 2024-06-20 | AS98: Yes | AT98: Facebook Ad | AU98: Rahul Mehta | AV98: Active | AX98: =IF(LEFT(A98,2)="AU","Aundh",IF(LEFT(A98,2)="KO","Kondhwa","Sinhgad Road")) -> Kondhwa
A99: KO-048 | B99: Riya Joshi | C99: 2006-05-20 | D99: Other | E99: 9899304911 | F99: riya.joshi48@gmail.com | G99: 379, Kondhwa Pune | H99: National School | I99: 60 | J99: 9954627171 | K99: MHT-CET | L99: 6 | M99: Evening | N99: 2024-02-28 | O99: 2024-08-26 | P99: R-114 | Q99: Online | R99: Tue-Thu-Sat | S99: Chemistry | T99: Ravi Kumar | U99: 2024-03-04 | V99: 2024-02-27 | W99: 49566 | X99: 46900 | Y99: 2666 | Z99: 3546 | AA99: No | AC99: Partial | AD99: Bank Transfer | AE99: 6 | AF99: 55 | AG99: 55 | AH99: Average | AI99: 100 | AJ99: 31 | AK99: 15 | AL99: Sick leave | AM99: 48 | AN99: No | AO99: 1 | AP99: 1 | AQ99: 2024-05-03 | AR99: 2024-05-21 | AS99: Yes | AT99: Facebook Ad | AU99: Rahul Mehta | AV99: Active | AX99: =IF(LEFT(A99,2)="AU","Aundh",IF(LEFT(A99,2)="KO","Kondhwa","Sinhgad Road")) -> Kondhwa
A100: KO-049 | B100: Siya Joshi | C100: 2006-02-02 | D100: Male | E100: 9816712949 | F100: siya.joshi49@gmail.com | G100: 422, Kondhwa Pune | H100: Modern College | I100: 78 | J100: 9925701113 | K100: Crash Course | L100: 12 | M100: Morning | N100: 2024-04-06 | O100: 2025-04-01 | P100: R-117 | Q100: Online | R100: Mon-Wed-Fri | S100: Biology | T100: Vikram Joshi | U100: 2024-05-13 | V100: 2024-05-07 | W100: 21587 | X100: 20315 | Y100: 1272 | Z100: 2486 | AA100: Yes | AB100: 2024-06-12 | AC100: Partial | AD100: Card | AE100: 5 | AF100: 88 | AG100: 95 | AH100: Average | AI100: 94 | AJ100: 51 | AK100: 25 | AL100: Sick leave | AM100: 49 | AN100: No | AO100: 5 | AP100: 5 | AQ100: 2024-06-21 | AR100: 2024-07-20 | AS100: Yes | AT100: Instagram Ad | AU100: Rahul Mehta | AV100: Active | AX100: =IF(LEFT(A100,2)="AU","Aundh",IF(LEFT(A100,2)="KO","Kondhwa","Sinhgad Road")) -> Kondhwa
...

Sheet Sheet1
A1: Performance | B1: Retention Risk (based on Dropout status & feedback) | C1: Latest test marks | D1: First test marks | E1: Improvement Rate | F1: Payment Timeliness
A2: =IF(Aundh!I2>85, "Excellent", IF(Aundh!I2<5, "Good", "Average")) -> Average | B2: =IF(Aundh!AV1="Left", "High", IF(Aundh!AP1<=2, "Medium", "Low")) -> Low | C2: =RANDBETWEEN(25,100) -> 62 | D2: =RANDBETWEEN(25,100) -> 60 | E2: =INT(((C2 - D2)/D2*100))&"%" -> 3% | F2: =IF(TODAY() > Aundh!AB2, "Overdue", "On Time") -> Overdue
A3: =IF(Aundh!I3>85, "Excellent", IF(Aundh!I3<5, "Good", "Average")) -> Excellent | B3: =IF(Aundh!AV2="Left", "High", IF(Aundh!AP2<=2, "Medium", "Low")) -> High | C3: =RANDBETWEEN(25,100) -> 61 | D3: =RANDBETWEEN(25,100) -> 100 | E3: =INT(((C3 - D3)/D3*100))&"%" -> -39% | F3: =IF(TODAY() > Aundh!AB3, "Overdue", "On Time") -> Overdue
A4: =IF(Aundh!I4>85, "Excellent", IF(Aundh!I4<5, "Good", "Average")) -> Average | B4: =IF(Aundh!AV3="Left", "High", IF(Aundh!AP3<=2, "Medium", "Low")) -> High | C4: =RANDBETWEEN(25,100) -> 93 | D4: =RANDBETWEEN(25,100) -> 27 | E4: =INT(((C4 - D4)/D4*100))&"%" -> 244% | F4: =IF(TODAY() > Aundh!AB4, "Overdue", "On Time") -> Overdue
A5: =IF(Aundh!I5>85, "Excellent", IF(Aundh!I5<5, "Good", "Average")) -> Average | B5: =IF(Aundh!AV4="Left", "High", IF(Aundh!AP4<=2, "Medium", "Low")) -> High | C5: =RANDBETWEEN(25,100) -> 34 | D5: =RANDBETWEEN(25,100) -> 43 | E5: =INT(((C5 - D5)/D5*100))&"%" -> -21% | F5: =IF(TODAY() > Aundh!AB5, "Overdue", "On Time") -> Overdue
A6: =IF(Aundh!I6>85, "Excellent", IF(Aundh!I6<5, "Good", "Average")) -> Average | B6: =IF(Aundh!AV5="Left", "High", IF(Aundh!AP5<=2, "Medium", "Low")) -> High | C6: =RANDBETWEEN(25,100) -> 56 | D6: =RANDBETWEEN(25,100) -> 52 | E6: =INT(((C6 - D6)/D6*100))&"%" -> 7% | F6: =IF(TODAY() > Aundh!AB6, "Overdue", "On Time") -> Overdue
A7: =IF(Aundh!I7>85, "Excellent", IF(Aundh!I7<5, "Good", "Average")) -> Average | B7: =IF(Aundh!AV6="Left", "High", IF(Aundh!AP6<=2, "Medium", "Low")) -> High | C7: =RANDBETWEEN(25,100) -> 87 | D7: =RANDBETWEEN(25,100) -> 27 | E7: =INT(((C7 - D7)/D7*100))&"%" -> 222% | F7: =IF(TODAY() > Aundh!AB7, "Overdue", "On Time") -> Overdue
A8: =IF(Aundh!I8>85, "Excellent", IF(Aundh!I8<5, "Good", "Average")) -> Excellent | B8: =IF(Aundh!AV7="Left", "High", IF(Aundh!AP7<=2, "Medium", "Low")) -> High | C8: =RANDBETWEEN(25,100) -> 71 | D8: =RANDBETWEEN(25,100) -> 88 | E8: =INT(((C8 - D8)/D8*100))&"%" -> -20% | F8: =IF(TODAY() > Aundh!AB8, "Overdue", "On Time") -> Overdue
A9: =IF(Aundh!I9>85, "Excellent", IF(Aundh!I9<5, "Good", "Average")) -> Average | B9: =IF(Aundh!AV8="Left", "High", IF(Aundh!AP8<=2, "Medium", "Low")) -> Low | C9: =RANDBETWEEN(25,100) -> 61 | D9: =RANDBETWEEN(25,100) -> 93 | E9: =INT(((C9 - D9)/D9*100))&"%" -> -35% | F9: =IF(TODAY() > Aundh!AB9, "Overdue", "On Time") -> Overdue
A10: =IF(Aundh!I10>85, "Excellent", IF(Aundh!I10<5, "Good", "Average")) -> Average | B10: =IF(Aundh!AV9="Left", "High", IF(Aundh!AP9<=2, "Medium", "Low")) -> Medium | C10: =RANDBETWEEN(25,100) -> 53 | D10: =RANDBETWEEN(25,100) -> 53 | E10: =INT(((C10 - D10)/D10*100))&"%" -> 0% | F10: =IF(TODAY() > Aundh!AB10, "Overdue", "On Time") -> Overdue
A11: =IF(Aundh!I11>85, "Excellent", IF(Aundh!I11<5, "Good", "Average")) -> Average | B11: =IF(Aundh!AV10="Left", "High", IF(Aundh!AP10<=2, "Medium", "Low")) -> High | C11: =RANDBETWEEN(25,100) -> 78 | D11: =RANDBETWEEN(25,100) -> 65 | E11: =INT(((C11 - D11)/D11*100))&"%" -> 20% | F11: =IF(TODAY() > Aundh!AB11, "Overdue", "On Time") -> Overdue
A12: =IF(Aundh!I12>85, "Excellent", IF(Aundh!I12<5, "Good", "Average")) -> Average | B12: =IF(Aundh!AV11="Left", "High", IF(Aundh!AP11<=2, "Medium", "Low")) -> High | C12: =RANDBETWEEN(25,100) -> 77 | D12: =RANDBETWEEN(25,100) -> 66 | E12: =INT(((C12 - D12)/D12*100))&"%" -> 16% | F12: =IF(TODAY() > Aundh!AB12, "Overdue", "On Time") -> Overdue
A13: =IF(Aundh!I13>85, "Excellent", IF(Aundh!I13<5, "Good", "Average")) -> Average | B13: =IF(Aundh!AV12="Left", "High", IF(Aundh!AP12<=2, "Medium", "Low")) -> High | C13: =RANDBETWEEN(25,100) -> 25 | D13: =RANDBETWEEN(25,100) -> 47 | E13: =INT(((C13 - D13)/D13*100))&"%" -> -47% | F13: =IF(TODAY() > Aundh!AB13, "Overdue", "On Time") -> Overdue
... A51: =IF(Aundh!I51>85, "Excellent", IF(Aundh!I51<5, "Good", "Average")) -> Average | B51: =IF(Aundh!AV50="Left", "High", IF(Aundh!AP50<=2, "Medium", "Low")) -> Low | C51: =RANDBETWEEN(25,100) -> 61 | D51: =RANDBETWEEN(25,100) -> 74 | E51: =INT(((C51 - D51)/D51*100))&"%" -> -18% | F51: =IF(TODAY() > Aundh!AB51, "Overdue", "On Time") -> Overdue

Sheet Kondhwa
A1: Student ID | B1: Student Name | C1: Date of Birth | D1: Gender | E1: Parent Contact Number | F1: Student Email | G1: Address | H1: School/College Name | I1: Previous Academic Performance (%) | J1: Emergency Contact | K1: Course | L1: Course Duration (Months) | M1: Batch | N1: Batch Start Date | O1: Batch End Date | P1: Classroom/Room No. | Q1: Mode | R1: Session Days | S1: Subject | T1: Teacher | U1: Enrollment Date | V1: Registration Date | W1: Total Course Fees | X1: Amount Paid | Y1: Pending Amount | Z1: Discount Given | AA1: Installment Plan | AB1: Next Payment Due Date | AC1: Payment Status | AD1: Payment Method | AE1: Number of Tests Taken | AF1: Average Test Score | AG1: Top Test Score | AH1: Progress Comments | AI1: Homework Completion Rate (%) | AJ1: Total Classes Conducted | AK1: Classes Attended | AL1: Leave Notes/Remarks | AM1: Attendance (%) | AN1: Attendance Alerts Sent | AO1: Parent Feedback | AP1: Student Feedback | AQ1: Last Feedback Date | AR1: Follow-up Date | AS1: WhatsApp Opt-in | AT1: Lead Source | AU1: Counselor/Admission Handled By | AV1: Dropout Status | AW1: Reason for Leaving
A2: KO-001 | B2: aarav sharma | C2: 2006-01-24 | D2: Male | E2: 9820516378 | F2: ira.sharma1@gmail.com | G2: 135, Kondhwa Pune | H2: City School | I2: 75 | J2: 9960630401 | K2: JEE | L2: 3 | M2: Evening | N2: 2024-03-29 | O2: 2024-06-27 | P2: R-116 | Q2: Online | R2: Mon-Wed-Fri | S2: Maths | T2: Vikram Joshi | U2: 2024-04-07 | V2: 2024-03-28 | W2: 19153 | X2: 18645 | Y2: 508 | Z2: 533 | AA2: No | AC2: Partial | AD2: UPI | AE2: 4 | AF2: 80 | AG2: 85 | AH2: Good | AI2: 87 | AJ2: 28 | AK2: 21 | AL2: Family function | AM2: 75 | AN2: Yes | AO2: 5 | AP2: 3 | AQ2: 2024-04-29 | AR2: 2024-05-10 | AS2: No | AT2: Referral | AU2: Amit Deshmukh | AV2: Active
A3: KO-002 | B3: Aditya Kadam | C3: 2006-03-17 | D3: Female | E3: 9878822987 | F3: ayaan.kumar2@gmail.com | G3: 854, Kondhwa Pune | H3: Modern College | I3: 68 | J3: 9923127405 | K3: Crash Course | L3: 6 | M3: Afternoon | N3: 2024-01-21 | O3: 2024-07-19 | P3: R-107 | Q3: Online | R3: Tue-Thu-Sat | S3: English | T3: Sneha Patil | U3: 2024-03-13 | V3: 2024-03-05 | W3: 37083 | X3: 35376 | Y3: 1707 | Z3: 1810 | AA3: Yes | AB3: 2024-04-12 | AC3: Partial | AD3: Bank Transfer | AE3: 1 | AF3: 45 | AG3: 49 | AH3: Good | AI3: 91 | AJ3: 32 | AK3: 24 | AM3: 75 | AN3: Yes | AO3: 5 | AP3: 5 | AQ3: 2024-04-15 | AR3: 2024-05-12 | AS3: Yes | AT3: Walk-in | AU3: Nidhi Shah | AV3: Active
A4: KO-003 | B4: Aniket Jadhav | C4: 2005-12-11 | D4: Female | E4: 9883855337 | F4: kabir.desai3@gmail.com | G4: 938, Kondhwa Pune | H4: National School | I4: 71 | J4: 9937531545 | K4: NEET | L4: 6 | M4: Morning | N4: 2024-02-09 | O4: 2024-08-07 | P4: R-112 | Q4: Online | R4: Mon-Wed-Fri | S4: English | T4: Ravi Kumar | U4: 2024-03-09 | V4: 2024-03-09 | W4: 27152 | X4: 27006 | Y4: 146 | Z4: 201 | AA4: Yes | AB4: 2024-04-08 | AC4: Partial | AD4: UPI | AE4: 7 | AF4: 67 | AG4: 83 | AH4: Good | AI4: 70 | AJ4: 44 | AK4: 33 | AL4: Sick leave | AM4: 75 | AN4: No | AO4: 1 | AP4: 3 | AQ4: 2024-05-01 | AR4: 2024-05-28 | AS4: Yes | AT4: Website | AU4: Amit Deshmukh | AV4: Active
A5: KO-004 | B5: Meera Kumar | C5: 2005-01-23 | D5: Other | E5: 9813465115 | F5: meera.kumar4@gmail.com | G5: 632, Kondhwa Pune | H5: Vibgyor High School | I5: 73 | J5: 9962086928 | K5: Foundation 8-10 | L5: 12 | M5: Evening | N5: 2024-01-31 | O5: 2025-01-25 | P5: R-104 | Q5: Offline | R5: Mon-Wed-Fri | S5: Physics | T5: Ravi Kumar | U5: 2024-03-06 | V5: 2024-02-25 | W5: 43597 | X5: 42766 | Y5: 831 | Z5: 4331 | AA5: No | AC5: Partial | AD5: Card | AE5: 3 | AF5: 80 | AG5: 89 | AH5: Good | AI5: 65 | AJ5: 44 | AK5: 44 | AL5: Family function | AM5: 100 | AN5: No | AO5: 4 | AP5: 4 | AQ5: 2024-04-21 | AR5: 2024-05-02 | AS5: Yes | AT5: Website | AU5: Rahul Mehta | AV5: Left | AW5: Switched institute
A6: KO-005 | B6: Ira Kumar | C6: 2005-12-08 | D6: Female | E6: 9840533164 | F6: ira.kumar5@gmail.com | G6: 108, Kondhwa Pune | H6: Vibgyor High School | I6: 83 | J6: 9956227162 | K6: MHT-CET | L6: 12 | M6: Morning | N6: 2024-02-09 | O6: 2025-02-03 | P6: R-101 | Q6: Hybrid | R6: Mon-Wed-Fri | S6: English | T6: Preeti Desai | U6: 2024-03-12 | V6: 2024-03-11 | W6: 40999 | X6: 40345 | Y6: 654 | Z6: 737 | AA6: Yes | AB6: 2024-04-11 | AC6: Partial | AD6: UPI | AE6: 4 | AF6: 65 | AG6: 67 | AH6: Good | AI6: 71 | AJ6: 20 | AK6: 20 | AM6: 100 | AN6: Yes | AO6: 5 | AP6: 5 | AQ6: 2024-04-26 | AR6: 2024-05-23 | AS6: No | AT6: Referral | AU6: Nidhi Shah | AV6: Active
A7: KO-006 | B7: Atharva Gaikwad | C7: 2006-03-01 | D7: Male | E7: 9866100060 | F7: kabir.joshi6@gmail.com | G7: 773, Kondhwa Pune | H7: City School | I7: 84 | J7: 9919487688 | K7: Crash Course | L7: 6 | M7: Evening | N7: 2024-02-14 | O7: 2024-08-12 | P7: R-106 | Q7: Offline | R7: Tue-Thu-Sat | S7: Physics | T7: Sneha Patil | U7: 2024-02-04 | V7: 2024-01-28 | W7: 43066 | X7: 41360 | Y7: 1706 | Z7: 4896 | AA7: Yes | AB7: 2024-03-05 | AC7: Partial | AD7: Card | AE7: 8 | AF7: 70 | AG7: 83 | AH7: Good | AI7: 76 | AJ7: 60 | AK7: 37 | AL7: Family function | AM7: 61 | AN7: Yes | AO7: 2 | AP7: 3 | AQ7: 2024-03-19 | AR7: 2024-04-12 | AS7: Yes | AT7: Walk-in | AU7: Amit Deshmukh | AV7: Active
A8: KO-007 | B8: Chinmay Deo | C8: 2005-12-31 | D8: Other | E8: 9847917980 | F8: aarav.joshi7@gmail.com | G8: 436, Kondhwa Pune | H8: Modern College | I8: 82 | J8: 9918783761 | K8: JEE | L8: 3 | M8: Morning | N8: 2024-02-09 | O8: 2024-05-09 | P8: R-119 | Q8: Hybrid | R8: Mon-Wed-Fri | S8: Biology | T8: Vikram Joshi | U8: 2024-02-06 | V8: 2024-02-06 | W8: 36223 | X8: 34524 | Y8: 1699 | Z8: 2380 | AA8: No | AC8: Partial | AD8: Card | AE8: 7 | AF8: 71 | AG8: 97 | AH8: Needs Improvement | AI8: 97 | AJ8: 56 | AK8: 35 | AL8: Family function | AM8: 62 | AN8: Yes | AO8: 3 | AP8: 1 | AQ8: 2024-03-18 | AR8: 2024-04-06 | AS8: Yes | AT8: Facebook Ad | AU8: Nidhi Shah | AV8: Active
A9: KO-008 | B9: Aarav Patil | C9: 2005-01-05 | D9: Other | E9: 9815707436 | F9: aarav.patil8@gmail.com | G9: 568, Kondhwa Pune | H9: Modern College | I9: 75 | J9: 9974940573 | K9: NEET | L9: 6 | M9: Afternoon | N9: 2024-02-15 | O9: 2024-08-13 | P9: R-114 | Q9: Hybrid | R9: Mon-Wed-Fri | S9: English | T9: Vikram Joshi | U9: 2024-03-21 | V9: 2024-03-16 | W9: 32353 | X9: 29995 | Y9: 2358 | Z9: 2960 | AA9: Yes | AB9: 2024-04-20 | AC9: Partial | AD9: Card | AE9: 3 | AF9: 54 | AG9: 69 | AH9: Needs Improvement | AI9: 65 | AJ9: 53 | AK9: 33 | AL9: Sick leave | AM9: 62 | AN9: No | AO9: 5 | AP9: 1 | AQ9: 2024-05-09 | AR9: 2024-05-21 | AS9: No | AT9: Referral | AU9: Rahul Mehta | AV9: Active
A10: KO-009 | B10: Ira Patil | C10: 2006-03-08 | D10: Other | E10: 9811132840 | F10: ira.patil9@gmail.com | G10: 341, Kondhwa Pune | H10: City School | I10: 63 | J10: 9931242109 | K10: Foundation 8-10 | L10: 3 | M10: Evening | N10: 2024-04-01 | O10: 2024-06-30 | P10: R-106 | Q10: Offline | R10: Tue-Thu-Sat | S10: Chemistry | T10: Vikram Joshi | U10: 2024-04-09 | V10: 2024-04-08 | W10: 21182 | X10: 19925 | Y10: 1257 | Z10: 3889 | AA10: No | AC10: Partial | AD10: UPI | AE10: 10 | AF10: 82 | AG10: 98 | AH10: Average | AI10: 86 | AJ10: 35 | AK10: 32 | AL10: Family function | AM10: 91 | AN10: Yes | AO10: 2 | AP10: 4 | AQ10: 2024-06-03 | AR10: 2024-06-24 | AS10: Yes | AT10: Walk-in | AU10: Rahul Mehta | AV10: Left | AW10: Too far
A11: KO-010 | B11: Reyansh Joshi | C11: 2005-04-30 | D11: Female | E11: 9838109437 | F11: reyansh.joshi10@gmail.com | G11: 491, Kondhwa Pune | H11: City School | I11: 92 | J11: 9915632601 | K11: MHT-CET | L11: 6 | M11: Afternoon | N11: 2024-01-09 | O11: 2024-07-07 | P11: R-114 | Q11: Offline | R11: Tue-Thu-Sat | S11: Chemistry | T11: Anil Sharma | U11: 2024-05-26 | V11: 2024-05-16 | W11: 40487 | X11: 40461 | Y11: 26 | Z11: 2041 | AA11: No | AC11: Partial | AD11: UPI | AE11: 5 | AF11: 84 | AG11: 88 | AH11: Average | AI11: 80 | AJ11: 38 | AK11: 30 | AL11: Family function | AM11: 78 | AN11: No | AO11: 4 | AP11: 1 | AQ11: 2024-07-12 | AR11: 2024-08-09 | AS11: No | AT11: Referral | AU11: Amit Deshmukh | AV11: Left | AW11: Lost interest
A12: KO-011 | B12: Digvijay Mohite | C12: 2005-04-07 | D12: Other | E12: 9897268494 | F12: anaya.kumar11@gmail.com | G12: 505, Kondhwa Pune | H12: Vibgyor High School | I12: 71 | J12: 9947129787 | K12: MHT-CET | L12: 3 | M12: Morning | N12: 2024-01-27 | O12: 2024-04-26 | P12: R-106 | Q12: Hybrid | R12: Tue-Thu-Sat | S12: Physics | T12: Anil Sharma | U12: 2024-03-23 | V12: 2024-03-17 | W12: 29023 | X12: 28414 | Y12: 609 | Z12: 1370 | AA12: No | AC12: Partial | AD12: Bank Transfer | AE12: 6 | AF12: 87 | AG12: 92 | AH12: Good | AI12: 98 | AJ12: 24 | AK12: 22 | AL12: Sick leave | AM12: 91 | AN12: Yes | AO12: 1 | AP12: 5 | AQ12: 2024-04-20 | AR12: 2024-05-20 | AS12: Yes | AT12: Instagram Ad | AU12: Rahul Mehta | AV12: Active
A13: KO-012 | B13: Durvesh Raut | C13: 2006-02-27 | D13: Other | E13: 9842419650 | F13: kabir.kumar12@gmail.com | G13: 752, Kondhwa Pune | H13: Pearl Drop School | I13: 80 | J13: 9971241216 | K13: NEET | L13: 12 | M13: Morning | N13: 2024-03-23 | O13: 2025-03-18 | P13: R-105 | Q13: Offline | R13: Tue-Thu-Sat | S13: Chemistry | T13: Ravi Kumar | U13: 2024-02-25 | V13: 2024-02-20 | W13: 49929 | X13: 49526 | Y13: 403 | Z13: 3120 | AA13: No | AC13: Partial | AD13: Card | AE13: 6 | AF13: 78 | AG13: 94 | AH13: Needs Improvement | AI13: 61 | AJ13: 45 | AK13: 17 | AL13: Sick leave | AM13: 37 | AN13: No | AO13: 5 | AP13: 4 | AQ13: 2024-04-19 | AR13: 2024-05-04 | AS13: Yes | AT13: Instagram Ad | AU13: Amit Deshmukh | AV13: Left | AW13: Too far
A14: KO-013 | B14: Ayaan Joshi | C14: 2006-05-08 | D14: Female | E14: 9888835695 | F14: ayaan.joshi13@gmail.com | G14: 483, Kondhwa Pune | H14: City School | I14: 88 | J14: 9994913704 | K14: JEE | L14: 6 | M14: Afternoon | N14: 2024-02-26 | O14: 2024-08-24 | P14: R-102 | Q14: Online | R14: Mon-Wed-Fri | S14: Maths | T14: Ravi Kumar | U14: 2024-03-04 | V14: 2024-03-03 | W14: 24675 | X14: 23682 | Y14: 993 | Z14: 4194 | AA14: Yes | AB14: 2024-04-03 | AC14: Partial | AD14: Card | AE14: 10 | AF14: 87 | AG14: 90 | AH14: Needs Improvement | AI14: 91 | AJ14: 36 | AK14: 15 | AM14: 41 | AN14: No | AO14: 5 | AP14: 3 | AQ14: 2024-04-20 | AR14: 2024-05-05 | AS14: No | AT14: Facebook Ad | AU14: Amit Deshmukh | AV14: Active
A15: KO-014 | B15: Gandhar Kulkarni | C15: 2006-04-06 | D15: Other | E15: 9838598523 | F15: vivaan.joshi14@gmail.com | G15: 918, Kondhwa Pune | H15: National School | I15: 85 | J15: 9991414065 | K15: Foundation 8-10 | L15: 3 | M15: Evening | N15: 2024-02-03 | O15: 2024-05-03 | P15: R-103 | Q15: Hybrid | R15: Mon-Wed-Fri | S15: English | T15: Sneha Patil | U15: 2024-05-30 | V15: 2024-05-30 | W15: 45065 | X15: 40719 | Y15: 4346 | Z15: 4930 | AA15: Yes | AB15: 2024-06-29 | AC15: Partial | AD15: Cash | AE15: 7 | AF15: 76 | AG15: 99 | AH15: Average | AI15: 63 | AJ15: 51 | AK15: 20 | AM15: 100 | AN15: Yes | AO15: 3 | AP15: 5 | AQ15: 2024-07-17 | AR15: 2024-08-04 | AS15: Yes | AT15: Website | AU15: Nidhi Shah | AV15: Active
A16: KO-015 | B16: Hrishikesh Gokhale | C16: 2005-11-12 | D16: Other | E16: 9813103166 | F16: ira.sharma15@gmail.com | G16: 765, Kondhwa Pune | H16: National School | I16: 79 | J16: 9957663747 | K16: MHT-CET | L16: 12 | M16: Evening | N16: 2024-02-09 | O16: 2025-02-03 | P16: R-105 | Q16: Online | R16: Tue-Thu-Sat | S16: Biology | T16: Anil Sharma | U16: 2024-02-12 | V16: 2024-02-04 | W16: 35116 | X16: 32648 | Y16: 2468 | Z16: 3991 | AA16: Yes | AB16: 2024-03-13 | AC16: Partial | AD16: Bank Transfer | AE16: 8 | AF16: 90 | AG16: 96 | AH16: Good | AI16: 80 | AJ16: 36 | AK16: 36 | AL16: Family function | AM16: 100 | AN16: Yes | AO16: 3 | AP16: 5 | AQ16: 2024-03-25 | AR16: 2024-04-08 | AS16: No | AT16: Facebook Ad | AU16: Amit Deshmukh | AV16: Left | AW16: Lost interest
A17: KO-016 | B17: Jayant Apte | C17: 2006-03-14 | D17: Female | E17: 9882431812 | F17: aarav.joshi16@gmail.com | G17: 659, Kondhwa Pune | H17: Modern College | I17: 80 | J17: 9950609040 | K17: Foundation 8-10 | L17: 12 | M17: Afternoon | N17: 2024-01-30 | O17: 2025-01-24 | P17: R-116 | Q17: Hybrid | R17: Mon-Wed-Fri | S17: Chemistry | T17: Anil Sharma | U17: 2024-02-02 | V17: 2024-02-02 | W17: 44771 | X17: 43191 | Y17: 1580 | Z17: 1738 | AA17: No | AC17: Partial | AD17: Cash | AE17: 4 | AF17: 44 | AG17: 73 | AH17: Average | AI17: 85 | AJ17: 20 | AK17: 16 | AL17: Sick leave | AM17: 80 | AN17: No | AO17: 3 | AP17: 5 | AQ17: 2024-03-06 | AR17: 2024-03-29 | AS17: Yes | AT17: Instagram Ad | AU17: Amit Deshmukh | AV17: Active
A18: KO-017 | B18: Kedar Deshpande | C18: 2006-04-01 | D18: Male | E18: 9837640512 | F18: ira.sharma17@gmail.com | G18: 109, Kondhwa Pune | H18: Vibgyor High School | I18: 87 | J18: 9983413708 | K18: JEE | L18: 6 | M18: Morning | N18: 2024-01-21 | O18: 2024-07-19 | P18: R-118 | Q18: Offline | R18: Tue-Thu-Sat | S18: English | T18: Vikram Joshi | U18: 2024-05-14 | V18: 2024-05-08 | W18: 23886 | X18: 23471 | Y18: 415 | Z18: 1110 | AA18: No | AC18: Partial | AD18: Cash | AE18: 6 | AF18: 69 | AG18: 83 | AH18: Needs Improvement | AI18: 95 | AJ18: 22 | AK18: 16 | AL18: Sick leave | AM18: 72 | AN18: Yes | AO18: 5 | AP18: 5 | AQ18: 2024-06-06 | AR18: 2024-06-26 | AS18: Yes | AT18: Facebook Ad | AU18: Rahul Mehta | AV18: Active
A19: KO-018 | B19: Mandar Patwardhan | C19: 2005-03-18 | D19: Male | E19: 9892994642 | F19: ayaan.kumar18@gmail.com | G19: 142, Kondhwa Pune | H19: National School | I19: 94 | J19: 9984736836 | K19: NEET | L19: 6 | M19: Evening | N19: 2024-03-26 | O19: 2024-09-22 | P19: R-120 | Q19: Offline | R19: Mon-Wed-Fri | S19: English | T19: Ravi Kumar | U19: 2024-02-24 | V19: 2024-02-17 | W19: 45617 | X19: 45592 | Y19: 25 | Z19: 114 | AA19: No | AC19: Partial | AD19: Cash | AE19: 5 | AF19: 68 | AG19: 69 | AH19: Good | AI19: 63 | AJ19: 36 | AK19: 34 | AL19: Family function | AM19: 94 | AN19: No | AO19: 2 | AP19: 1 | AQ19: 2024-03-19 | AR19: 2024-04-12 | AS19: No | AT19: Walk-in | AU19: Amit Deshmukh | AV19: Active
A20: KO-019 | B20: Anaya Patil | C20: 2006-03-23 | D20: Other | E20: 9885650439 | F20: anaya.patil19@gmail.com | G20: 996, Kondhwa Pune | H20: Pearl Drop School | I20: 94 | J20: 9965936930 | K20: NEET | L20: 6 | M20: Evening | N20: 2024-01-02 | O20: 2024-06-30 | P20: R-103 | Q20: Hybrid | R20: Mon-Wed-Fri | S20: English | T20: Ravi Kumar | U20: 2024-03-04 | V20: 2024-02-26 | W20: 49351 | X20: 48701 | Y20: 650 | Z20: 2068 | AA20: No | AC20: Partial | AD20: Cash | AE20: 2 | AF20: 76 | AG20: 87 | AH20: Good | AI20: 65 | AJ20: 27 | AK20: 21 | AL20: Sick leave | AM20: 77 | AN20: Yes | AO20: 5 | AP20: 1 | AQ20: 2024-04-28 | AR20: 2024-05-17 | AS20: Yes | AT20: Website | AU20: Amit Deshmukh | AV20: Left | AW20: Switched institute
A21: KO-020 | B21: Siya Sharma | C21: 2005-12-27 | D21: Female | E21: 9865292883 | F21: siya.sharma20@gmail.com | G21: 225, Kondhwa Pune | H21: National School | I21: 86 | J21: 9960976895 | K21: Crash Course | L21: 6 | M21: Afternoon | N21: 2024-02-25 | O21: 2024-08-23 | P21: R-110 | Q21: Online | R21: Mon-Wed-Fri | S21: Maths | T21: Anil Sharma | U21: 2024-02-25 | V21: 2024-02-21 | W21: 17301 | X21: 16524 | Y21: 777 | Z21: 3434 | AA21: No | AC21: Partial | AD21: Cash | AE21: 6 | AF21: 69 | AG21: 89 | AH21: Needs Improvement | AI21: 67 | AJ21: 30 | AK21: 18 | AM21: 60 | AN21: Yes | AO21: 1 | AP21: 5 | AQ21: 2024-04-01 | AR21: 2024-04-27 | AS21: Yes | AT21: Walk-in | AU21: Amit Deshmukh | AV21: Active
A22: KO-021 | B22: Siya Desai | C22: 2005-03-08 | D22: Female | E22: 9845914193 | F22: siya.desai21@gmail.com | G22: 729, Kondhwa Pune | H22: National School | I22: 78 | J22: 9921504638 | K22: Foundation 8-10 | L22: 3 | M22: Morning | N22: 2024-01-01 | O22: 2024-03-31 | P22: R-106 | Q22: Online | R22: Mon-Wed-Fri | S22: Biology | T22: Vikram Joshi | U22: 2024-04-18 | V22: 2024-04-11 | W22: 19459 | X22: 17117 | Y22: 2342 | Z22: 3454 | AA22: No | AC22: Partial | AD22: Bank Transfer | AE22: 4 | AF22: 46 | AG22: 97 | AH22: Good | AI22: 97 | AJ22: 56 | AK22: 32 | AM22: 57 | AN22: No | AO22: 3 | AP22: 2 | AQ22: 2024-06-07 | AR22: 2024-06-18 | AS22: Yes | AT22: Instagram Ad | AU22: Amit Deshmukh | AV22: Active
A23: KO-022 | B23: Vivaan Joshi | C23: 2006-04-12 | D23: Female | E23: 9823040733 | F23: vivaan.joshi22@gmail.com | G23: 201, Kondhwa Pune | H23: City School | I23: 80 | J23: 9960370931 | K23: JEE | L23: 6 | M23: Evening | N23: 2024-01-18 | O23: 2024-07-16 | P23: R-105 | Q23: Online | R23: Mon-Wed-Fri | S23: Physics | T23: Sneha Patil | U23: 2024-03-22 | V23: 2024-03-13 | W23: 20924 | X23: 19348 | Y23: 1576 | Z23: 3300 | AA23: No | AC23: Partial | AD23: Cash | AE23: 3 | AF23: 48 | AG23: 99 | AH23: Good | AI23: 98 | AJ23: 30 | AK23: 19 | AM23: 63 | AN23: No | AO23: 5 | AP23: 3 | AQ23: 2024-05-05 | AR23: 2024-05-27 | AS23: No | AT23: Referral | AU23: Amit Deshmukh | AV23: Left | AW23: Switched institute
A24: KO-023 | B24: Ninad Sardesai | C24: 2006-06-13 | D24: Female | E24: 9844764313 | F24: ayaan.patil23@gmail.com | G24: 765, Kondhwa Pune | H24: City School | I24: 67 | J24: 9928374323 | K24: Crash Course | L24: 3 | M24: Evening | N24: 2024-03-15 | O24: 2024-06-13 | P24: R-116 | Q24: Offline | R24: Tue-Thu-Sat | S24: Physics | T24: Preeti Desai | U24: 2024-05-22 | V24: 2024-05-22 | W24: 47341 | X24: 46395 | Y24: 946 | Z24: 1891 | AA24: No | AC24: Partial | AD24: UPI | AE24: 2 | AF24: 70 | AG24: 89 | AH24: Average | AI24: 80 | AJ24: 44 | AK24: 28 | AL24: Sick leave | AM24: 63 | AN24: No | AO24: 1 | AP24: 2 | AQ24: 2024-07-18 | AR24: 2024-08-03 | AS24: No | AT24: Referral | AU24: Amit Deshmukh | AV24: Active
A25: KO-024 | B25: Reyansh Kumar | C25: 2006-04-20 | D25: Other | E25: 9890541119 | F25: reyansh.kumar24@gmail.com | G25: 254, Kondhwa Pune | H25: Pearl Drop School | I25: 87 | J25: 9949929000 | K25: JEE | L25: 3 | M25: Evening | N25: 2024-03-10 | O25: 2024-06-08 | P25: R-109 | Q25: Hybrid | R25: Mon-Wed-Fri | S25: Biology | T25: Anil Sharma | U25: 2024-03-01 | V25: 2024-02-24 | W25: 26352 | X25: 25125 | Y25: 1227 | Z25: 2445 | AA25: Yes | AB25: 2024-03-31 | AC25: Partial | AD25: UPI | AE25: 2 | AF25: 54 | AG25: 73 | AH25: Average | AI25: 64 | AJ25: 23 | AK25: 20 | AL25: Sick leave | AM25: 86 | AN25: Yes | AO25: 5 | AP25: 4 | AQ25: 2024-04-18 | AR25: 2024-04-28 | AS25: Yes | AT25: Instagram Ad | AU25: Nidhi Shah | AV25: Left | AW25: Lost interest
A26: KO-025 | B26: Prathamesh Kulkarni | C26: 2005-11-07 | D26: Male | E26: 9846010242 | F26: ayaan.patil25@gmail.com | G26: 867, Kondhwa Pune | H26: Modern College | I26: 64 | J26: 9964086262 | K26: Crash Course | L26: 6 | M26: Evening | N26: 2024-01-17 | O26: 2024-07-15 | P26: R-113 | Q26: Online | R26: Tue-Thu-Sat | S26: Maths | T26: Vikram Joshi | U26: 2024-05-09 | V26: 2024-05-09 | W26: 42875 | X26: 42345 | Y26: 530 | Z26: 4954 | AA26: No | AC26: Partial | AD26: Bank Transfer | AE26: 10 | AF26: 55 | AG26: 92 | AH26: Good | AI26: 79 | AJ26: 51 | AK26: 34 | AM26: 66 | AN26: Yes | AO26: 3 | AP26: 1 | AQ26: 2024-06-18 | AR26: 2024-07-07 | AS26: Yes | AT26: Facebook Ad | AU26: Amit Deshmukh | AV26: Active
A27: KO-026 | B27: Kabir Kumar | C27: 2005-04-26 | D27: Male | E27: 9879412684 | F27: kabir.kumar26@gmail.com | G27: 844, Kondhwa Pune | H27: National School | I27: 75 | J27: 9992220005 | K27: NEET | L27: 3 | M27: Morning | N27: 2024-03-22 | O27: 2024-06-20 | P27: R-113 | Q27: Offline | R27: Mon-Wed-Fri | S27: Physics | T27: Vikram Joshi | U27: 2024-04-17 | V27: 2024-04-12 | W27: 42522 | X27: 40345 | Y27: 2177 | Z27: 4432 | AA27: Yes | AB27: 2024-05-17 | AC27: Partial | AD27: Bank Transfer | AE27: 3 | AF27: 90 | AG27: 91 | AH27: Needs Improvement | AI27: 95 | AJ27: 45 | AK27: 45 | AL27: Sick leave | AM27: 100 | AN27: Yes | AO27: 4 | AP27: 4 | AQ27: 2024-05-14 | AR27: 2024-06-10 | AS27: Yes | AT27: Facebook Ad | AU27: Amit Deshmukh | AV27: Active
A28: KO-027 | B28: Meera Joshi | C28: 2005-12-05 | D28: Other | E28: 9883455453 | F28: meera.joshi27@gmail.com | G28: 379, Kondhwa Pune | H28: Vibgyor High School | I28: 83 | J28: 9992250304 | K28: Crash Course | L28: 6 | M28: Evening | N28: 2024-01-07 | O28: 2024-07-05 | P28: R-117 | Q28: Offline | R28: Tue-Thu-Sat | S28: English | T28: Sneha Patil | U28: 2024-04-22 | V28: 2024-04-22 | W28: 15553 | X28: 13040 | Y28: 2513 | Z28: 3819 | AA28: Yes | AB28: 2024-05-22 | AC28: Partial | AD28: Cash | AE28: 7 | AF28: 42 | AG28: 93 | AH28: Good | AI28: 69 | AJ28: 59 | AK28: 17 | AL28: Family function | AM28: 28 | AN28: Yes | AO28: 3 | AP28: 3 | AQ28: 2024-06-04 | AR28: 2024-06-21 | AS28: Yes | AT28: Referral | AU28: Rahul Mehta | AV28: Active
A29: KO-028 | B29: Rahul Shinde | C29: 2005-11-09 | D29: Other | E29: 9849208957 | F29: ayaan.desai28@gmail.com | G29: 730, Kondhwa Pune | H29: City School | I29: 63 | J29: 9925812635 | K29: NEET | L29: 6 | M29: Afternoon | N29: 2024-02-07 | O29: 2024-08-05 | P29: R-105 | Q29: Offline | R29: Mon-Wed-Fri | S29: Physics | T29: Sneha Patil | U29: 2024-03-12 | V29: 2024-03-09 | W29: 44415 | X29: 41446 | Y29: 2969 | Z29: 3247 | AA29: No | AC29: Partial | AD29: Card | AE29: 8 | AF29: 48 | AG29: 60 | AH29: Needs Improvement | AI29: 63 | AJ29: 55 | AK29: 29 | AM29: 52 | AN29: Yes | AO29: 2 | AP29: 4 | AQ29: 2024-04-17 | AR29: 2024-05-03 | AS29: Yes | AT29: Facebook Ad | AU29: Rahul Mehta | AV29: Left | AW29: Too far
A30: KO-029 | B30: Ritesh Surve | C30: 2005-09-15 | D30: Male | E30: 9813572188 | F30: vivaan.sharma29@gmail.com | G30: 457, Kondhwa Pune | H30: National School | I30: 63 | J30: 9946975129 | K30: Foundation 8-10 | L30: 12 | M30: Evening | N30: 2024-04-06 | O30: 2025-04-01 | P30: R-113 | Q30: Hybrid | R30: Tue-Thu-Sat | S30: Biology | T30: Sneha Patil | U30: 2024-02-27 | V30: 2024-02-26 | W30: 28843 | X30: 27816 | Y30: 1027 | Z30: 2145 | AA30: Yes | AB30: 2024-03-28 | AC30: Partial | AD30: Card | AE30: 4 | AF30: 87 | AG30: 89 | AH30: Needs Improvement | AI30: 78 | AJ30: 58 | AK30: 34 | AL30: Sick leave | AM30: 58 | AN30: No | AO30: 1 | AP30: 1 | AQ30: 2024-04-04 | AR30: 2024-05-04 | AS30: No | AT30: Website | AU30: Amit Deshmukh | AV30: Left | AW30: Too far
A31: KO-030 | B31: Sanket Kanade | C31: 2006-03-22 | D31: Other | E31: 9818710767 | F31: kabir.desai30@gmail.com | G31: 173, Kondhwa Pune | H31: Modern College | I31: 85 | J31: 9942556025 | K31: Foundation 8-10 | L31: 3 | M31: Afternoon | N31: 2024-02-04 | O31: 2024-05-04 | P31: R-102 | Q31: Offline | R31: Tue-Thu-Sat | S31: Chemistry | T31: Sneha Patil | U31: 2024-05-27 | V31: 2024-05-19 | W31: 41233 | X31: 40131 | Y31: 1102 | Z31: 1170 | AA31: No | AC31: Partial | AD31: Cash | AE31: 9 | AF31: 66 | AG31: 99 | AH31: Needs Improvement | AI31: 75 | AJ31: 28 | AK31: 24 | AL31: Family function | AM31: 85 | AN31: No | AO31: 4 | AP31: 3 | AQ31: 2024-06-24 | AR31: 2024-07-16 | AS31: Yes | AT31: Website | AU31: Amit Deshmukh | AV31: Active
A32: KO-031 | B32: Kabir Sharma | C32: 2006-08-15 | D32: Male | E32: 9823091195 | F32: kabir.sharma31@gmail.com | G32: 368, Kondhwa Pune | H32: City School | I32: 62 | J32: 9998579774 | K32: NEET | L32: 6 | M32: Afternoon | N32: 2024-02-01 | O32: 2024-07-30 | P32: R-104 | Q32: Hybrid | R32: Mon-Wed-Fri | S32: Chemistry | T32: Preeti Desai | U32: 2024-02-03 | V32: 2024-02-02 | W32: 19610 | X32: 17405 | Y32: 2205 | Z32: 2990 | AA32: Yes | AB32: 2024-03-04 | AC32: Partial | AD32: Cash | AE32: 4 | AF32: 40 | AG32: 92 | AH32: Needs Improvement | AI32: 62 | AJ32: 22 | AK32: 15 | AL32: Sick leave | AM32: 68 | AN32: No | AO32: 1 | AP32: 4 | AQ32: 2024-02-25 | AR32: 2024-03-07 | AS32: Yes | AT32: Website | AU32: Nidhi Shah | AV32: Active
A33: KO-032 | B33: Aarav Joshi | C33: 2005-08-24 | D33: Female | E33: 9823163100 | F33: aarav.joshi32@gmail.com | G33: 570, Kondhwa Pune | H33: City School | I33: 95 | J33: 9951456148 | K33: Foundation 8-10 | L33: 3 | M33: Afternoon | N33: 2024-01-23 | O33: 2024-04-22 | P33: R-117 | Q33: Offline | R33: Tue-Thu-Sat | S33: English | T33: Ravi Kumar | U33: 2024-05-26 | V33: 2024-05-24 | W33: 27420 | X33: 25321 | Y33: 2099 | Z33: 4452 | AA33: Yes | AB33: 2024-06-25 | AC33: Partial | AD33: Card | AE33: 7 | AF33: 84 | AG33: 84 | AH33: Needs Improvement | AI33: 86 | AJ33: 34 | AK33: 28 | AL33: Sick leave | AM33: 82 | AN33: Yes | AO33: 1 | AP33: 3 | AQ33: 2024-07-05 | AR33: 2024-07-16 | AS33: No | AT33: Website | AU33: Rahul Mehta | AV33: Active
A34: KO-033 | B34: Shantanu Phadke | C34: 2005-02-14 | D34: Other | E34: 9845663219 | F34: ayaan.desai33@gmail.com | G34: 770, Kondhwa Pune | H34: Vibgyor High School | I34: 62 | J34: 9995810839 | K34: Crash Course | L34: 12 | M34: Evening | N34: 2024-01-07 | O34: 2025-01-01 | P34: R-112 | Q34: Offline | R34: Mon-Wed-Fri | S34: Chemistry | T34: Anil Sharma | U34: 2024-05-26 | V34: 2024-05-16 | W34: 15888 | X34: 15810 | Y34: 78 | Z34: 616 | AA34: Yes | AB34: 2024-06-25 | AC34: Partial | AD34: UPI | AE34: 3 | AF34: 68 | AG34: 90 | AH34: Good | AI34: 96 | AJ34: 22 | AK34: 19 | AL34: Family function | AM34: 86 | AN34: Yes | AO34: 1 | AP34: 3 | AQ34: 2024-07-04 | AR34: 2024-07-17 | AS34: No | AT34: Referral | AU34: Nidhi Shah | AV34: Left | AW34: Too far
A35: KO-034 | B35: Ayaan Patil | C35: 2006-03-18 | D35: Other | E35: 9813245131 | F35: ayaan.patil34@gmail.com | G35: 189, Kondhwa Pune | H35: Pearl Drop School | I35: 64 | J35: 9989493829 | K35: JEE | L35: 12 | M35: Morning | N35: 2024-02-28 | O35: 2025-02-22 | P35: R-102 | Q35: Offline | R35: Mon-Wed-Fri | S35: Biology | T35: Preeti Desai | U35: 2024-04-05 | V35: 2024-03-29 | W35: 19311 | X35: 16449 | Y35: 2862 | Z35: 4409 | AA35: Yes | AB35: 2024-05-05 | AC35: Partial | AD35: Bank Transfer | AE35: 6 | AF35: 57 | AG35: 99 | AH35: Average | AI35: 78 | AJ35: 37 | AK35: 21 | AM35: 56 | AN35: Yes | AO35: 2 | AP35: 3 | AQ35: 2024-05-21 | AR35: 2024-06-12 | AS35: No | AT35: Instagram Ad | AU35: Nidhi Shah | AV35: Left | AW35: Lost interest
A36: KO-035 | B36: Kabir Desai | C36: 2005-11-22 | D36: Male | E36: 9880297576 | F36: kabir.desai35@gmail.com | G36: 677, Kondhwa Pune | H36: City School | I36: 68 | J36: 9975351562 | K36: NEET | L36: 12 | M36: Morning | N36: 2024-04-10 | O36: 2025-04-05 | P36: R-111 | Q36: Online | R36: Mon-Wed-Fri | S36: Maths | T36: Sneha Patil | U36: 2024-04-12 | V36: 2024-04-09 | W36: 20458 | X36: 19978 | Y36: 480 | Z36: 2660 | AA36: No | AC36: Partial | AD36: Card | AE36: 3 | AF36: 88 | AG36: 93 | AH36: Good | AI36: 61 | AJ36: 35 | AK36: 19 | AM36: 54 | AN36: Yes | AO36: 4 | AP36: 1 | AQ36: 2024-05-04 | AR36: 2024-05-20 | AS36: No | AT36: Facebook Ad | AU36: Amit Deshmukh | AV36: Active
A37: KO-036 | B37: Shreyas Dixit | C37: 2006-03-16 | D37: Other | E37: 9878481588 | F37: ira.desai36@gmail.com | G37: 461, Kondhwa Pune | H37: National School | I37: 65 | J37: 9987589202 | K37: NEET | L37: 12 | M37: Afternoon | N37: 2024-04-08 | O37: 2025-04-03 | P37: R-102 | Q37: Online | R37: Tue-Thu-Sat | S37: Maths | T37: Vikram Joshi | U37: 2024-04-16 | V37: 2024-04-13 | W37: 29622 | X37: 29427 | Y37: 195 | Z37: 1746 | AA37: No | AC37: Partial | AD37: UPI | AE37: 2 | AF37: 58 | AG37: 94 | AH37: Average | AI37: 64 | AJ37: 52 | AK37: 26 | AL37: Family function | AM37: 50 | AN37: Yes | AO37: 3 | AP37: 5 | AQ37: 2024-05-17 | AR37: 2024-06-12 | AS37: No | AT37: Facebook Ad | AU37: Rahul Mehta | AV37: Active
A38: KO-037 | B38: Reyansh Patil | C38: 2005-06-16 | D38: Other | E38: 9854656175 | F38: reyansh.patil37@gmail.com | G38: 285, Kondhwa Pune | H38: Pearl Drop School | I38: 93 | J38: 9936768133 | K38: Foundation 8-10 | L38: 3 | M38: Afternoon | N38: 2024-02-26 | O38: 2024-05-26 | P38: R-116 | Q38: Offline | R38: Tue-Thu-Sat | S38: Maths | T38: Preeti Desai | U38: 2024-04-02 | V38: 2024-03-27 | W38: 25776 | X38: 25030 | Y38: 746 | Z38: 2823 | AA38: No | AC38: Partial | AD38: Card | AE38: 8 | AF38: 42 | AG38: 95 | AH38: Needs Improvement | AI38: 82 | AJ38: 32 | AK38: 32 | AL38: Family function | AM38: 100 | AN38: No | AO38: 2 | AP38: 4 | AQ38: 2024-05-09 | AR38: 2024-05-29 | AS38: No | AT38: Referral | AU38: Rahul Mehta | AV38: Left | AW38: Lost interest
A39: KO-038 | B39: Ira Desai | C39: 2005-01-10 | D39: Male | E39: 9891926020 | F39: ira.desai38@gmail.com | G39: 224, Kondhwa Pune | H39: Modern College | I39: 88 | J39: 9918248808 | K39: Foundation 8-10 | L39: 6 | M39: Afternoon | N39: 2024-03-06 | O39: 2024-09-02 | P39: R-111 | Q39: Online | R39: Mon-Wed-Fri | S39: English | T39: Ravi Kumar | U39: 2024-03-18 | V39: 2024-03-13 | W39: 42342 | X39: 40311 | Y39: 2031 | Z39: 4137 | AA39: Yes | AB39: 2024-04-17 | AC39: Partial | AD39: Cash | AE39: 6 | AF39: 48 | AG39: 86 | AH39: Needs Improvement | AI39: 73 | AJ39: 28 | AK39: 15 | AL39: Sick leave | AM39: 53 | AN39: No | AO39: 2 | AP39: 3 | AQ39: 2024-05-09 | AR39: 2024-05-21 | AS39: No | AT39: Walk-in | AU39: Nidhi Shah | AV39: Active
A40: KO-039 | B40: Kabir Joshi | C40: 2005-12-01 | D40: Female | E40: 9843471255 | F40: kabir.joshi39@gmail.com | G40: 277, Kondhwa Pune | H40: Modern College | I40: 67 | J40: 9946705761 | K40: NEET | L40: 6 | M40: Afternoon | N40: 2024-01-06 | O40: 2024-07-04 | P40: R-113 | Q40: Online | R40: Mon-Wed-Fri | S40: English | T40: Preeti Desai | U40: 2024-04-19 | V40: 2024-04-09 | W40: 29354 | X40: 28991 | Y40: 363 | Z40: 2575 | AA40: Yes | AB40: 2024-05-19 | AC40: Partial | AD40: Card | AE40: 2 | AF40: 44 | AG40: 77 | AH40: Needs Improvement | AI40: 96 | AJ40: 39 | AK40: 28 | AL40: Family function | AM40: 71 | AN40: No | AO40: 1 | AP40: 4 | AQ40: 2024-06-13 | AR40: 2024-07-03 | AS40: No | AT40: Website | AU40: Amit Deshmukh | AV40: Left | AW40: Lost interest
A41: KO-040 | B41: Kabir Patil | C41: 2005-12-19 | D41: Other | E41: 9828907536 | F41: kabir.patil40@gmail.com | G41: 980, Kondhwa Pune | H41: City School | I41: 64 | J41: 9997928087 | K41: Crash Course | L41: 3 | M41: Evening | N41: 2024-02-15 | O41: 2024-05-15 | P41: R-104 | Q41: Hybrid | R41: Tue-Thu-Sat | S41: Physics | T41: Vikram Joshi | U41: 2024-03-12 | V41: 2024-03-05 | W41: 40169 | X41: 40126 | Y41: 43 | Z41: 745 | AA41: No | AC41: Partial | AD41: Cash | AE41: 8 | AF41: 59 | AG41: 62 | AH41: Good | AI41: 75 | AJ41: 42 | AK41: 36 | AL41: Family function | AM41: 85 | AN41: Yes | AO41: 5 | AP41: 5 | AQ41: 2024-05-05 | AR41: 2024-05-21 | AS41: No | AT41: Referral | AU41: Amit Deshmukh | AV41: Left | AW41: Too far
A42: KO-041 | B42: Ira Sharma | C42: 2005-08-09 | D42: Other | E42: 9858231993 | F42: ira.sharma41@gmail.com | G42: 917, Kondhwa Pune | H42: Modern College | I42: 69 | J42: 9923659135 | K42: MHT-CET | L42: 3 | M42: Morning | N42: 2024-03-25 | O42: 2024-06-23 | P42: R-104 | Q42: Hybrid | R42: Tue-Thu-Sat | S42: Maths | T42: Ravi Kumar | U42: 2024-03-21 | V42: 2024-03-18 | W42: 43998 | X42: 41712 | Y42: 2286 | Z42: 2947 | AA42: No | AC42: Partial | AD42: Card | AE42: 4 | AF42: 45 | AG42: 86 | AH42: Average | AI42: 79 | AJ42: 27 | AK42: 22 | AL42: Sick leave | AM42: 81 | AN42: Yes | AO42: 4 | AP42: 2 | AQ42: 2024-05-03 | AR42: 2024-05-30 | AS42: No | AT42: Walk-in | AU42: Amit Deshmukh | AV42: Left | AW42: Switched institute
A43: KO-042 | B43: Anaya Kumar | C43: 2005-09-09 | D43: Other | E43: 9837196046 | F43: anaya.kumar42@gmail.com | G43: 321, Kondhwa Pune | H43: Pearl Drop School | I43: 70 | J43: 9982250950 | K43: Foundation 8-10 | L43: 6 | M43: Afternoon | N43: 2024-03-23 | O43: 2024-09-19 | P43: R-116 | Q43: Hybrid | R43: Tue-Thu-Sat | S43: Chemistry | T43: Ravi Kumar | U43: 2024-03-07 | V43: 2024-03-06 | W43: 42034 | X43: 41968 | Y43: 66 | Z43: 89 | AA43: No | AC43: Partial | AD43: Card | AE43: 1 | AF43: 43 | AG43: 75 | AH43: Average | AI43: 96 | AJ43: 57 | AK43: 39 | AL43: Family function | AM43: 68 | AN43: Yes | AO43: 3 | AP43: 4 | AQ43: 2024-04-13 | AR43: 2024-05-08 | AS43: Yes | AT43: Referral | AU43: Rahul Mehta | AV43: Left | AW43: Switched institute
A44: KO-043 | B44: Ira Joshi | C44: 2006-04-06 | D44: Male | E44: 9823703480 | F44: ira.joshi43@gmail.com | G44: 647, Kondhwa Pune | H44: City School | I44: 63 | J44: 9915335627 | K44: Crash Course | L44: 6 | M44: Evening | N44: 2024-04-07 | O44: 2024-10-04 | P44: R-113 | Q44: Online | R44: Tue-Thu-Sat | S44: Chemistry | T44: Anil Sharma | U44: 2024-04-24 | V44: 2024-04-24 | W44: 40019 | X44: 38945 | Y44: 1074 | Z44: 2647 | AA44: No | AC44: Partial | AD44: Bank Transfer | AE44: 6 | AF44: 83 | AG44: 88 | AH44: Average | AI44: 81 | AJ44: 43 | AK44: 37 | AL44: Sick leave | AM44: 86 | AN44: Yes | AO44: 5 | AP44: 5 | AQ44: 2024-05-29 | AR44: 2024-06-12 | AS44: No | AT44: Website | AU44: Rahul Mehta | AV44: Left | AW44: Too far
A45: KO-044 | B45: Vivaan Patil | C45: 2006-02-05 | D45: Other | E45: 9894231097 | F45: vivaan.patil44@gmail.com | G45: 793, Kondhwa Pune | H45: Vibgyor High School | I45: 86 | J45: 9921053780 | K45: MHT-CET | L45: 3 | M45: Afternoon | N45: 2024-01-07 | O45: 2024-04-06 | P45: R-116 | Q45: Offline | R45: Tue-Thu-Sat | S45: Maths | T45: Vikram Joshi | U45: 2024-02-10 | V45: 2024-02-01 | W45: 17440 | X45: 16885 | Y45: 555 | Z45: 624 | AA45: Yes | AB45: 2024-03-11 | AC45: Partial | AD45: Bank Transfer | AE45: 6 | AF45: 60 | AG45: 62 | AH45: Average | AI45: 97 | AJ45: 22 | AK45: 15 | AL45: Sick leave | AM45: 68 | AN45: No | AO45: 1 | AP45: 5 | AQ45: 2024-03-14 | AR45: 2024-03-25 | AS45: No | AT45: Walk-in | AU45: Nidhi Shah | AV45: Left | AW45: Switched institute
A46: KO-045 | B46: Vivaan Sharma | C46: 2005-01-13 | D46: Female | E46: 9816422378 | F46: vivaan.sharma45@gmail.com | G46: 907, Kondhwa Pune | H46: Modern College | I46: 75 | J46: 9939556989 | K46: Crash Course | L46: 12 | M46: Evening | N46: 2024-04-10 | O46: 2025-04-05 | P46: R-113 | Q46: Offline | R46: Mon-Wed-Fri | S46: Maths | T46: Sneha Patil | U46: 2024-03-13 | V46: 2024-03-04 | W46: 16030 | X46: 15752 | Y46: 278 | Z46: 678 | AA46: No | AC46: Partial | AD46: UPI | AE46: 5 | AF46: 55 | AG46: 92 | AH46: Average | AI46: 63 | AJ46: 43 | AK46: 40 | AL46: Family function | AM46: 93 | AN46: No | AO46: 5 | AP46: 4 | AQ46: 2024-05-02 | AR46: 2024-05-28 | AS46: Yes | AT46: Website | AU46: Rahul Mehta | AV46: Left | AW46: Too far
A47: KO-046 | B47: Meera Sharma | C47: 2005-08-13 | D47: Other | E47: 9814668143 | F47: meera.sharma46@gmail.com | G47: 241, Kondhwa Pune | H47: Pearl Drop School | I47: 88 | J47: 9963154851 | K47: NEET | L47: 3 | M47: Morning | N47: 2024-03-05 | O47: 2024-06-03 | P47: R-111 | Q47: Offline | R47: Tue-Thu-Sat | S47: Chemistry | T47: Vikram Joshi | U47: 2024-05-20 | V47: 2024-05-20 | W47: 25558 | X47: 23782 | Y47: 1776 | Z47: 3810 | AA47: No | AC47: Partial | AD47: UPI | AE47: 6 | AF47: 46 | AG47: 93 | AH47: Good | AI47: 92 | AJ47: 52 | AK47: 29 | AL47: Family function | AM47: 55 | AN47: Yes | AO47: 2 | AP47: 3 | AQ47: 2024-07-06 | AR47: 2024-07-31 | AS47: Yes | AT47: Facebook Ad | AU47: Rahul Mehta | AV47: Left | AW47: Lost interest
A48: KO-047 | B48: Ayaan Kumar | C48: 2005-11-29 | D48: Male | E48: 9814859663 | F48: ayaan.kumar47@gmail.com | G48: 845, Kondhwa Pune | H48: Vibgyor High School | I48: 71 | J48: 9993595692 | K48: JEE | L48: 3 | M48: Afternoon | N48: 2024-02-07 | O48: 2024-05-07 | P48: R-108 | Q48: Hybrid | R48: Tue-Thu-Sat | S48: Chemistry | T48: Ravi Kumar | U48: 2024-04-25 | V48: 2024-04-20 | W48: 43187 | X48: 40324 | Y48: 2863 | Z48: 2874 | AA48: Yes | AB48: 2024-05-25 | AC48: Partial | AD48: Card | AE48: 6 | AF48: 70 | AG48: 82 | AH48: Needs Improvement | AI48: 81 | AJ48: 23 | AK48: 18 | AM48: 78 | AN48: No | AO48: 5 | AP48: 5 | AQ48: 2024-06-04 | AR48: 2024-06-20 | AS48: Yes | AT48: Facebook Ad | AU48: Rahul Mehta | AV48: Active
A49: KO-048 | B49: Riya Joshi | C49: 2006-05-20 | D49: Other | E49: 9899304911 | F49: riya.joshi48@gmail.com | G49: 379, Kondhwa Pune | H49: National School | I49: 60 | J49: 9954627171 | K49: MHT-CET | L49: 6 | M49: Evening | N49: 2024-02-28 | O49: 2024-08-26 | P49: R-114 | Q49: Online | R49: Tue-Thu-Sat | S49: Chemistry | T49: Ravi Kumar | U49: 2024-03-04 | V49: 2024-02-27 | W49: 49566 | X49: 46900 | Y49: 2666 | Z49: 3546 | AA49: No | AC49: Partial | AD49: Bank Transfer | AE49: 6 | AF49: 55 | AG49: 55 | AH49: Average | AI49: 100 | AJ49: 31 | AK49: 15 | AL49: Sick leave | AM49: 48 | AN49: No | AO49: 1 | AP49: 1 | AQ49: 2024-05-03 | AR49: 2024-05-21 | AS49: Yes | AT49: Facebook Ad | AU49: Rahul Mehta | AV49: Active
A50: KO-049 | B50: Siya Joshi | C50: 2006-02-02 | D50: Male | E50: 9816712949 | F50: siya.joshi49@gmail.com | G50: 422, Kondhwa Pune | H50: Modern College | I50: 78 | J50: 9925701113 | K50: Crash Course | L50: 12 | M50: Morning | N50: 2024-04-06 | O50: 2025-04-01 | P50: R-117 | Q50: Online | R50: Mon-Wed-Fri | S50: Biology | T50: Vikram Joshi | U50: 2024-05-13 | V50: 2024-05-07 | W50: 21587 | X50: 20315 | Y50: 1272 | Z50: 2486 | AA50: Yes | AB50: 2024-06-12 | AC50: Partial | AD50: Card | AE50: 5 | AF50: 88 | AG50: 95 | AH50: Average | AI50: 94 | AJ50: 51 | AK50: 25 | AL50: Sick leave | AM50: 49 | AN50: No | AO50: 5 | AP50: 5 | AQ50: 2024-06-21 | AR50: 2024-07-20 | AS50: Yes | AT50: Instagram Ad | AU50: Rahul Mehta | AV50: Active
A51: KO-050 | B51: Ayaan Desai | C51: 2006-05-19 | D51: Other | E51: 9882021369 | F51: ayaan.desai50@gmail.com | G51: 626, Kondhwa Pune | H51: National School | I51: 92 | J51: 9985755500 | K51: Crash Course | L51: 6 | M51: Afternoon | N51: 2024-04-08 | O51: 2024-10-05 | P51: R-112 | Q51: Hybrid | R51: Tue-Thu-Sat | S51: Biology | T51: Vikram Joshi | U51: 2024-04-20 | V51: 2024-04-17 | W51: 40772 | X51: 39048 | Y51: 1724 | Z51: 4472 | AA51: No | AC51: Partial | AD51: Card | AE51: 7 | AF51: 69 | AG51: 83 | AH51: Average | AI51: 73 | AJ51: 33 | AK51: 17 | AM51: 51 | AN51: No | AO51: 2 | AP51: 2 | AQ51: 2024-05-30 | AR51: 2024-06-24 | AS51: No | AT51: Facebook Ad | AU51: Nidhi Shah | AV51: Left | AW51: Lost interest

Sheet Sinhgad_Road
A1: Student ID | B1: Student Name | C1: Date of Birth | D1: Gender | E1: Parent Contact Number | F1: Student Email | G1: Address | H1: School/College Name | I1: Previous Academic Performance (%) | J1: Emergency Contact | K1: Course | L1: Course Duration (Months) | M1: Batch | N1: Batch Start Date | O1: Batch End Date | P1: Classroom/Room No. | Q1: Mode | R1: Session Days | S1: Subject | T1: Teacher | U1: Enrollment Date | V1: Registration Date | W1: Total Course Fees | X1: Amount Paid | Y1: Pending Amount | Z1: Discount Given | AA1: Installment Plan | AB1: Next Payment Due Date | AC1: Payment Status | AD1: Payment Method | AE1: Number of Tests Taken | AF1: Average Test Score | AG1: Top Test Score | AH1: Progress Comments | AI1: Homework Completion Rate (%) | AJ1: Total Classes Conducted | AK1: Classes Attended | AL1: Leave Notes/Remarks | AM1: Attendance (%) | AN1: Attendance Alerts Sent | AO1: Parent Feedback | AP1: Student Feedback | AQ1: Last Feedback Date | AR1: Follow-up Date | AS1: WhatsApp Opt-in | AT1: Lead Source | AU1: Counselor/Admission Handled By | AV1: Dropout Status | AW1: Reason for Leaving
A2: SI-001 | B2: daksh sharma | C2: 2005-05-06 | D2: Male | E2: 9819654233 | F2: siya.kumar1@gmail.com | G2: 407, Sinhgad Road Pune | H2: Modern College | I2: 61 | J2: 9999303760 | K2: NEET | L2: 12 | M2: Morning | N2: 2024-04-04 | O2: 2025-03-30 | P2: R-106 | Q2: Online | R2: Tue-Thu-Sat | S2: English | T2: Ravi Kumar | U2: 2024-05-30 | V2: 2024-05-21 | W2: 24902 | X2: 23823 | Y2: 1079 | Z2: 2762 | AA2: No | AC2: Partial | AD2: Bank Transfer | AE2: 1 | AF2: 89 | AG2: 90 | AH2: Average | AI2: 85 | AJ2: 40 | AK2: 38 | AL2: Sick leave | AM2: 100 | AN2: Yes | AO2: 4 | AP2: 5 | AQ2: 2024-07-16 | AR2: 2024-08-10 | AS2: No | AT2: Instagram Ad | AU2: Nidhi Shah | AV2: Active
A3: SI-002 | B3: prem patil | C3: 2005-03-22 | D3: Other | E3: 9854519975 | F3: vivaan.patil2@gmail.com | G3: 786, Sinhgad Road Pune | H3: Modern College | I3: 68 | J3: 9949087556 | K3: JEE | L3: 6 | M3: Evening | N3: 2024-01-09 | O3: 2024-07-07 | P3: R-101 | Q3: Hybrid | R3: Mon-Wed-Fri | S3: Physics | T3: Sneha Patil | U3: 2024-04-01 | V3: 2024-03-24 | W3: 24283 | X3: 21996 | Y3: 2287 | Z3: 4413 | AA3: Yes | AB3: 2024-05-01 | AC3: Partial | AD3: Bank Transfer | AE3: 1 | AF3: 42 | AG3: 79 | AH3: Needs Improvement | AI3: 94 | AJ3: 30 | AK3: 25 | AL3: Sick leave | AM3: 100 | AN3: Yes | AO3: 3 | AP3: 1 | AQ3: 2024-05-24 | AR3: 2024-06-04 | AS3: No | AT3: Facebook Ad | AU3: Amit Deshmukh | AV3: Active
A4: SI-003 | B4: Ayaan Joshi | C4: 2005-08-07 | D4: Female | E4: 9872020824 | F4: ayaan.joshi3@gmail.com | G4: 493, Sinhgad Road Pune | H4: Sinhgad Spring Dale School | I4: 88 | J4: 9963885419 | K4: NEET | L4: 3 | M4: Evening | N4: 2024-02-19 | O4: 2024-05-19 | P4: R-103 | Q4: Online | R4: Mon-Wed-Fri | S4: English | T4: Ravi Kumar | U4: 2024-03-09 | V4: 2024-03-03 | W4: 26489 | X4: 26292 | Y4: 197 | Z4: 2244 | AA4: No | AC4: Partial | AD4: UPI | AE4: 10 | AF4: 44 | AG4: 83 | AH4: Average | AI4: 79 | AJ4: 60 | AK4: 20 | AM4: 100 | AN4: No | AO4: 2 | AP4: 2 | AQ4: 2024-03-31 | AR4: 2024-04-17 | AS4: No | AT4: Referral | AU4: Nidhi Shah | AV4: Left | AW4: Switched institute
A5: SI-004 | B5: ram sharma | C5: 2005-03-03 | D5: Other | E5: 9851138162 | F5: siya.kumar4@gmail.com | G5: 169, Sinhgad Road Pune | H5: National School | I5: 95 | J5: 9957484013 | K5: MHT-CET | L5: 12 | M5: Evening | N5: 2024-03-07 | O5: 2025-03-02 | P5: R-116 | Q5: Hybrid | R5: Mon-Wed-Fri | S5: Biology | T5: Ravi Kumar | U5: 2024-03-27 | V5: 2024-03-17 | W5: 24249 | X5: 24206 | Y5: 43 | Z5: 121 | AA5: No | AC5: Partial | AD5: Cash | AE5: 5 | AF5: 71 | AG5: 81 | AH5: Good | AI5: 92 | AJ5: 28 | AK5: 18 | AM5: 64 | AN5: No | AO5: 3 | AP5: 1 | AQ5: 2024-05-14 | AR5: 2024-05-25 | AS5: No | AT5: Referral | AU5: Rahul Mehta | AV5: Left | AW5: Lost interest
A6: SI-005 | B6: Anaya Joshi | C6: 2005-08-08 | D6: Male | E6: 9850327880 | F6: anaya.joshi5@gmail.com | G6: 190, Sinhgad Road Pune | H6: DSK School | I6: 72 | J6: 9991330187 | K6: JEE | L6: 6 | M6: Evening | N6: 2024-02-05 | O6: 2024-08-03 | P6: R-111 | Q6: Offline | R6: Tue-Thu-Sat | S6: Physics | T6: Anil Sharma | U6: 2024-02-20 | V6: 2024-02-18 | W6: 19931 | X6: 19557 | Y6: 374 | Z6: 1222 | AA6: Yes | AB6: 2024-03-21 | AC6: Partial | AD6: Card | AE6: 3 | AF6: 44 | AG6: 99 | AH6: Good | AI6: 90 | AJ6: 24 | AK6: 22 | AM6: 91 | AN6: No | AO6: 5 | AP6: 5 | AQ6: 2024-03-30 | AR6: 2024-04-26 | AS6: No | AT6: Facebook Ad | AU6: Nidhi Shah | AV6: Left | AW6: Switched institute
A7: SI-006 | B7: ayra sharma | C7: 2006-03-22 | D7: Other | E7: 9887574602 | F7: ira.sharma6@gmail.com | G7: 277, Sinhgad Road Pune | H7: Modern College | I7: 94 | J7: 9991783332 | K7: JEE | L7: 3 | M7: Morning | N7: 2024-03-02 | O7: 2024-05-31 | P7: R-103 | Q7: Hybrid | R7: Mon-Wed-Fri | S7: Maths | T7: Anil Sharma | U7: 2024-04-23 | V7: 2024-04-13 | W7: 41308 | X7: 40228 | Y7: 1080 | Z7: 3391 | AA7: No | AC7: Partial | AD7: Cash | AE7: 9 | AF7: 61 | AG7: 100 | AH7: Good | AI7: 99 | AJ7: 50 | AK7: 39 | AL7: Family function | AM7: 78 | AN7: Yes | AO7: 3 | AP7: 1 | AQ7: 2024-06-03 | AR7: 2024-06-18 | AS7: Yes | AT7: Instagram Ad | AU7: Nidhi Shah | AV7: Active
A8: SI-007 | B8: Kabir Desai | C8: 2005-01-05 | D8: Male | E8: 9815738463 | F8: kabir.desai7@gmail.com | G8: 707, Sinhgad Road Pune | H8: National School | I8: 76 | J8: 9943419625 | K8: MHT-CET | L8: 6 | M8: Evening | N8: 2024-02-03 | O8: 2024-08-01 | P8: R-120 | Q8: Online | R8: Tue-Thu-Sat | S8: Maths | T8: Vikram Joshi | U8: 2024-05-24 | V8: 2024-05-24 | W8: 18265 | X8: 14570 | Y8: 3695 | Z8: 3727 | AA8: No | AC8: Partial | AD8: Cash | AE8: 4 | AF8: 66 | AG8: 85 | AH8: Good | AI8: 86 | AJ8: 54 | AK8: 19 | AL8: Sick leave | AM8: 35 | AN8: Yes | AO8: 2 | AP8: 3 | AQ8: 2024-06-14 | AR8: 2024-06-30 | AS8: Yes | AT8: Instagram Ad | AU8: Nidhi Shah | AV8: Left | AW8: Too far
A9: SI-008 | B9: Anaya Desai | C9: 2005-02-26 | D9: Other | E9: 9852477396 | F9: anaya.desai8@gmail.com | G9: 460, Sinhgad Road Pune | H9: Sinhgad Spring Dale School | I9: 68 | J9: 9990416999 | K9: Crash Course | L9: 3 | M9: Evening | N9: 2024-02-27 | O9: 2024-05-27 | P9: R-101 | Q9: Online | R9: Mon-Wed-Fri | S9: Physics | T9: Sneha Patil | U9: 2024-04-26 | V9: 2024-04-18 | W9: 27915 | X9: 27782 | Y9: 133 | Z9: 137 | AA9: Yes | AB9: 2024-05-26 | AC9: Partial | AD9: Cash | AE9: 9 | AF9: 42 | AG9: 42 | AH9: Needs Improvement | AI9: 87 | AJ9: 45 | AK9: 34 | AM9: 75 | AN9: No | AO9: 4 | AP9: 4 | AQ9: 2024-05-20 | AR9: 2024-06-10 | AS9: No | AT9: Walk-in | AU9: Nidhi Shah | AV9: Active
A10: SI-009 | B10: Meera Patil | C10: 2005-09-19 | D10: Male | E10: 9896135314 | F10: meera.patil9@gmail.com | G10: 136, Sinhgad Road Pune | H10: Sinhgad Spring Dale School | I10: 94 | J10: 9973692562 | K10: Foundation 8-10 | L10: 12 | M10: Evening | N10: 2024-03-09 | O10: 2025-03-04 | P10: R-101 | Q10: Hybrid | R10: Tue-Thu-Sat | S10: Biology | T10: Anil Sharma | U10: 2024-02-19 | V10: 2024-02-19 | W10: 18513 | X10: 18478 | Y10: 35 | Z10: 40 | AA10: No | AC10: Partial | AD10: Cash | AE10: 3 | AF10: 44 | AG10: 91 | AH10: Average | AI10: 80 | AJ10: 41 | AK10: 37 | AM10: 90 | AN10: Yes | AO10: 5 | AP10: 3 | AQ10: 2024-03-14 | AR10: 2024-03-31 | AS10: Yes | AT10: Walk-in | AU10: Amit Deshmukh | AV10: Left | AW10: Switched institute
A11: SI-010 | B11: pratik kumar | C11: 2005-11-05 | D11: Other | E11: 9834393252 | F11: kabir.desai10@gmail.com | G11: 861, Sinhgad Road Pune | H11: DSK School | I11: 62 | J11: 9945326500 | K11: Crash Course | L11: 3 | M11: Morning | N11: 2024-02-08 | O11: 2024-05-08 | P11: R-106 | Q11: Hybrid | R11: Tue-Thu-Sat | S11: Physics | T11: Ravi Kumar | U11: 2024-02-12 | V11: 2024-02-08 | W11: 34735 | X11: 32586 | Y11: 2149 | Z11: 2851 | AA11: No | AC11: Partial | AD11: Bank Transfer | AE11: 1 | AF11: 69 | AG11: 78 | AH11: Average | AI11: 85 | AJ11: 53 | AK11: 31 | AL11: Family function | AM11: 58 | AN11: No | AO11: 3 | AP11: 2 | AQ11: 2024-03-23 | AR11: 2024-04-03 | AS11: Yes | AT11: Facebook Ad | AU11: Nidhi Shah | AV11: Active
A12: SI-011 | B12: Aarav Desai | C12: 2005-07-01 | D12: Other | E12: 9839053404 | F12: aarav.desai11@gmail.com | G12: 673, Sinhgad Road Pune | H12: Sinhgad Spring Dale School | I12: 63 | J12: 9941218608 | K12: Foundation 8-10 | L12: 6 | M12: Afternoon | N12: 2024-02-17 | O12: 2024-08-15 | P12: R-106 | Q12: Offline | R12: Mon-Wed-Fri | S12: Biology | T12: Vikram Joshi | U12: 2024-05-01 | V12: 2024-05-01 | W12: 25073 | X12: 22507 | Y12: 2566 | Z12: 2622 | AA12: No | AC12: Partial | AD12: UPI | AE12: 6 | AF12: 81 | AG12: 81 | AH12: Needs Improvement | AI12: 94 | AJ12: 31 | AK12: 19 | AL12: Sick leave | AM12: 61 | AN12: Yes | AO12: 5 | AP12: 4 | AQ12: 2024-06-23 | AR12: 2024-07-19 | AS12: No | AT12: Referral | AU12: Rahul Mehta | AV12: Left | AW12: Lost interest
A13: SI-012 | B13: pratik more | C13: 2005-10-23 | D13: Female | E13: 9838303938 | F13: siya.kumar12@gmail.com | G13: 345, Sinhgad Road Pune | H13: City School | I13: 74 | J13: 9921786051 | K13: Crash Course | L13: 3 | M13: Morning | N13: 2024-03-25 | O13: 2024-06-23 | P13: R-103 | Q13: Hybrid | R13: Mon-Wed-Fri | S13: Maths | T13: Preeti Desai | U13: 2024-02-01 | V13: 2024-01-25 | W13: 47190 | X13: 43083 | Y13: 4107 | Z13: 4422 | AA13: Yes | AB13: 2024-03-02 | AC13: Partial | AD13: UPI | AE13: 7 | AF13: 60 | AG13: 77 | AH13: Average | AI13: 97 | AJ13: 27 | AK13: 24 | AL13: Family function | AM13: 88 | AN13: No | AO13: 5 | AP13: 1 | AQ13: 2024-03-19 | AR13: 2024-04-18 | AS13: No | AT13: Walk-in | AU13: Amit Deshmukh | AV13: Left | AW13: Switched institute
A14: SI-013 | B14: shubham pawar | C14: 2006-08-10 | D14: Female | E14: 9847100440 | F14: siya.desai13@gmail.com | G14: 281, Sinhgad Road Pune | H14: National School | I14: 91 | J14: 9982344379 | K14: Crash Course | L14: 3 | M14: Morning | N14: 2024-03-25 | O14: 2024-06-23 | P14: R-115 | Q14: Offline | R14: Mon-Wed-Fri | S14: Maths | T14: Vikram Joshi | U14: 2024-03-06 | V14: 2024-02-26 | W14: 20036 | X14: 19390 | Y14: 646 | Z14: 2832 | AA14: Yes | AB14: 2024-04-05 | AC14: Partial | AD14: UPI | AE14: 5 | AF14: 86 | AG14: 90 | AH14: Good | AI14: 70 | AJ14: 31 | AK14: 21 | AM14: 67 | AN14: No | AO14: 2 | AP14: 4 | AQ14: 2024-04-15 | AR14: 2024-05-11 | AS14: No | AT14: Instagram Ad | AU14: Rahul Mehta | AV14: Left | AW14: Lost interest
A15: SI-014 | B15: Riya Kumar | C15: 2006-01-10 | D15: Female | E15: 9879498422 | F15: riya.kumar14@gmail.com | G15: 176, Sinhgad Road Pune | H15: National School | I15: 87 | J15: 9981354153 | K15: MHT-CET | L15: 6 | M15: Morning | N15: 2024-02-15 | O15: 2024-08-13 | P15: R-101 | Q15: Online | R15: Tue-Thu-Sat | S15: English | T15: Vikram Joshi | U15: 2024-02-16 | V15: 2024-02-16 | W15: 34689 | X15: 32835 | Y15: 1854 | Z15: 2454 | AA15: No | AC15: Partial | AD15: Bank Transfer | AE15: 10 | AF15: 41 | AG15: 58 | AH15: Good | AI15: 73 | AJ15: 27 | AK15: 26 | AM15: 96 | AN15: No | AO15: 1 | AP15: 3 | AQ15: 2024-04-12 | AR15: 2024-05-03 | AS15: Yes | AT15: Instagram Ad | AU15: Nidhi Shah | AV15: Active
A16: SI-015 | B16: disen Patil | C16: 2005-02-15 | D16: Male | E16: 9817355503 | F16: vivaan.patil15@gmail.com | G16: 995, Sinhgad Road Pune | H16: Sinhgad Spring Dale School | I16: 92 | J16: 9972990272 | K16: Foundation 8-10 | L16: 6 | M16: Afternoon | N16: 2024-01-06 | O16: 2024-07-04 | P16: R-110 | Q16: Online | R16: Mon-Wed-Fri | S16: Physics | T16: Anil Sharma | U16: 2024-04-02 | V16: 2024-03-29 | W16: 40538 | X16: 39809 | Y16: 729 | Z16: 2035 | AA16: No | AC16: Partial | AD16: UPI | AE16: 9 | AF16: 47 | AG16: 63 | AH16: Average | AI16: 78 | AJ16: 48 | AK16: 27 | AL16: Family function | AM16: 56 | AN16: Yes | AO16: 5 | AP16: 4 | AQ16: 2024-04-23 | AR16: 2024-05-16 | AS16: No | AT16: Walk-in | AU16: Rahul Mehta | AV16: Active
A17: SI-016 | B17: arya sharma | C17: 2005-09-25 | D17: Female | E17: 9872576983 | F17: riya.sharma16@gmail.com | G17: 511, Sinhgad Road Pune | H17: Sinhgad Spring Dale School | I17: 62 | J17: 9993892032 | K17: MHT-CET | L17: 12 | M17: Afternoon | N17: 2024-01-16 | O17: 2025-01-10 | P17: R-118 | Q17: Offline | R17: Mon-Wed-Fri | S17: Biology | T17: Preeti Desai | U17: 2024-03-07 | V17: 2024-03-06 | W17: 37355 | X17: 36312 | Y17: 1043 | Z17: 1260 | AA17: No | AC17: Partial | AD17: Cash | AE17: 4 | AF17: 67 | AG17: 81 | AH17: Needs Improvement | AI17: 87 | AJ17: 59 | AK17: 31 | AL17: Sick leave | AM17: 52 | AN17: No | AO17: 5 | AP17: 5 | AQ17: 2024-04-03 | AR17: 2024-04-30 | AS17: Yes | AT17: Facebook Ad | AU17: Nidhi Shah | AV17: Left | AW17: Lost interest
A18: SI-017 | B18: Riya Joshi | C18: 2006-06-20 | D18: Other | E18: 9811483857 | F18: riya.joshi17@gmail.com | G18: 535, Sinhgad Road Pune | H18: Modern College | I18: 60 | J18: 9928049448 | K18: JEE | L18: 6 | M18: Morning | N18: 2024-02-20 | O18: 2024-08-18 | P18: R-109 | Q18: Offline | R18: Mon-Wed-Fri | S18: English | T18: Anil Sharma | U18: 2024-02-29 | V18: 2024-02-21 | W18: 31539 | X18: 30952 | Y18: 587 | Z18: 4920 | AA18: No | AC18: Partial | AD18: Bank Transfer | AE18: 9 | AF18: 70 | AG18: 84 | AH18: Good | AI18: 69 | AJ18: 53 | AK18: 18 | AL18: Sick leave | AM18: 33 | AN18: Yes | AO18: 4 | AP18: 3 | AQ18: 2024-04-12 | AR18: 2024-05-12 | AS18: Yes | AT18: Walk-in | AU18: Nidhi Shah | AV18: Active
A19: SI-018 | B19: Riya Sharma | C19: 2005-02-23 | D19: Other | E19: 9854940389 | F19: riya.sharma18@gmail.com | G19: 287, Sinhgad Road Pune | H19: DSK School | I19: 81 | J19: 9979388748 | K19: NEET | L19: 6 | M19: Afternoon | N19: 2024-01-24 | O19: 2024-07-22 | P19: R-115 | Q19: Offline | R19: Mon-Wed-Fri | S19: Chemistry | T19: Vikram Joshi | U19: 2024-05-18 | V19: 2024-05-12 | W19: 21085 | X19: 17789 | Y19: 3296 | Z19: 4095 | AA19: No | AC19: Partial | AD19: Cash | AE19: 1 | AF19: 68 | AG19: 83 | AH19: Needs Improvement | AI19: 61 | AJ19: 49 | AK19: 47 | AM19: 95 | AN19: No | AO19: 4 | AP19: 2 | AQ19: 2024-06-29 | AR19: 2024-07-27 | AS19: Yes | AT19: Facebook Ad | AU19: Nidhi Shah | AV19: Active
A20: SI-019 | B20: bhavya desai | C20: 2005-03-27 | D20: Male | E20: 9891366851 | F20: siya.desai19@gmail.com | G20: 909, Sinhgad Road Pune | H20: Sinhgad Spring Dale School | I20: 75 | J20: 9998802648 | K20: Crash Course | L20: 3 | M20: Afternoon | N20: 2024-01-07 | O20: 2024-04-06 | P20: R-103 | Q20: Online | R20: Tue-Thu-Sat | S20: Chemistry | T20: Vikram Joshi | U20: 2024-03-07 | V20: 2024-02-26 | W20: 34781 | X20: 31694 | Y20: 3087 | Z20: 3160 | AA20: Yes | AB20: 2024-04-06 | AC20: Partial | AD20: Card | AE20: 8 | AF20: 41 | AG20: 53 | AH20: Average | AI20: 63 | AJ20: 47 | AK20: 29 | AL20: Family function | AM20: 61 | AN20: Yes | AO20: 2 | AP20: 3 | AQ20: 2024-04-05 | AR20: 2024-04-25 | AS20: No | AT20: Instagram Ad | AU20: Rahul Mehta | AV20: Active
A21: SI-020 | B21: Anaya Kumar | C21: 2006-03-09 | D21: Other | E21: 9875164592 | F21: anaya.kumar20@gmail.com | G21: 381, Sinhgad Road Pune | H21: DSK School | I21: 61 | J21: 9989749038 | K21: Crash Course | L21: 6 | M21: Morning | N21: 2024-03-28 | O21: 2024-09-24 | P21: R-114 | Q21: Hybrid | R21: Tue-Thu-Sat | S21: Maths | T21: Anil Sharma | U21: 2024-05-29 | V21: 2024-05-22 | W21: 43431 | X21: 42958 | Y21: 473 | Z21: 2083 | AA21: Yes | AB21: 2024-06-28 | AC21: Partial | AD21: UPI | AE21: 4 | AF21: 50 | AG21: 79 | AH21: Good | AI21: 78 | AJ21: 43 | AK21: 22 | AL21: Sick leave | AM21: 51 | AN21: No | AO21: 1 | AP21: 5 | AQ21: 2024-07-14 | AR21: 2024-07-31 | AS21: Yes | AT21: Instagram Ad | AU21: Amit Deshmukh | AV21: Left | AW21: Lost interest
A22: SI-021 | B22: sarthak sharma | C22: 2005-02-27 | D22: Other | E22: 9836858086 | F22: vivaan.desai21@gmail.com | G22: 618, Sinhgad Road Pune | H22: DSK School | I22: 82 | J22: 9980356746 | K22: NEET | L22: 3 | M22: Morning | N22: 2024-02-16 | O22: 2024-05-16 | P22: R-117 | Q22: Offline | R22: Mon-Wed-Fri | S22: Chemistry | T22: Ravi Kumar | U22: 2024-03-04 | V22: 2024-03-01 | W22: 16271 | X22: 16067 | Y22: 204 | Z22: 293 | AA22: Yes | AB22: 2024-04-03 | AC22: Partial | AD22: UPI | AE22: 1 | AF22: 83 | AG22: 86 | AH22: Average | AI22: 99 | AJ22: 47 | AK22: 39 | AL22: Sick leave | AM22: 82 | AN22: Yes | AO22: 5 | AP22: 4 | AQ22: 2024-04-29 | AR22: 2024-05-21 | AS22: Yes | AT22: Facebook Ad | AU22: Rahul Mehta | AV22: Active
A23: SI-022 | B23: Ayaan Sharma | C23: 2005-01-15 | D23: Female | E23: 9846521612 | F23: ayaan.sharma22@gmail.com | G23: 201, Sinhgad Road Pune | H23: City School | I23: 74 | J23: 9943011585 | K23: Crash Course | L23: 12 | M23: Evening | N23: 2024-02-20 | O23: 2025-02-14 | P23: R-105 | Q23: Offline | R23: Mon-Wed-Fri | S23: English | T23: Vikram Joshi | U23: 2024-05-04 | V23: 2024-05-04 | W23: 37022 | X23: 35158 | Y23: 1864 | Z23: 3743 | AA23: No | AC23: Partial | AD23: Bank Transfer | AE23: 6 | AF23: 75 | AG23: 83 | AH23: Average | AI23: 77 | AJ23: 50 | AK23: 21 | AL23: Sick leave | AM23: 42 | AN23: Yes | AO23: 2 | AP23: 3 | AQ23: 2024-06-26 | AR23: 2024-07-25 | AS23: No | AT23: Referral | AU23: Amit Deshmukh | AV23: Left | AW23: Switched institute
A24: SI-023 | B24: Reyansh Sharma | C24: 2005-10-13 | D24: Female | E24: 9892653069 | F24: reyansh.sharma23@gmail.com | G24: 222, Sinhgad Road Pune | H24: Sinhgad Spring Dale School | I24: 64 | J24: 9988244718 | K24: NEET | L24: 12 | M24: Evening | N24: 2024-03-15 | O24: 2025-03-10 | P24: R-115 | Q24: Offline | R24: Mon-Wed-Fri | S24: Maths | T24: Preeti Desai | U24: 2024-03-18 | V24: 2024-03-18 | W24: 21174 | X24: 19848 | Y24: 1326 | Z24: 2831 | AA24: No | AC24: Partial | AD24: Cash | AE24: 5 | AF24: 73 | AG24: 82 | AH24: Needs Improvement | AI24: 98 | AJ24: 27 | AK24: 17 | AM24: 62 | AN24: No | AO24: 1 | AP24: 2 | AQ24: 2024-05-09 | AR24: 2024-06-07 | AS24: Yes | AT24: Walk-in | AU24: Nidhi Shah | AV24: Left | AW24: Switched institute
A25: SI-024 | B25: Kabir Kumar | C25: 2005-06-05 | D25: Female | E25: 9873972535 | F25: kabir.kumar24@gmail.com | G25: 740, Sinhgad Road Pune | H25: City School | I25: 63 | J25: 9942170665 | K25: NEET | L25: 12 | M25: Morning | N25: 2024-03-16 | O25: 2025-03-11 | P25: R-108 | Q25: Offline | R25: Tue-Thu-Sat | S25: Chemistry | T25: Ravi Kumar | U25: 2024-03-22 | V25: 2024-03-12 | W25: 26544 | X25: 23051 | Y25: 3493 | Z25: 4997 | AA25: No | AC25: Partial | AD25: UPI | AE25: 3 | AF25: 84 | AG25: 95 | AH25: Needs Improvement | AI25: 83 | AJ25: 40 | AK25: 37 | AM25: 92 | AN25: No | AO25: 3 | AP25: 5 | AQ25: 2024-04-24 | AR25: 2024-05-16 | AS25: Yes | AT25: Referral | AU25: Nidhi Shah | AV25: Left | AW25: Lost interest
A26: SI-025 | B26: Siya Kumar | C26: 2006-02-01 | D26: Other | E26: 9883872941 | F26: siya.kumar25@gmail.com | G26: 795, Sinhgad Road Pune | H26: National School | I26: 72 | J26: 9986053889 | K26: Foundation 8-10 | L26: 3 | M26: Afternoon | N26: 2024-01-27 | O26: 2024-04-26 | P26: R-106 | Q26: Online | R26: Tue-Thu-Sat | S26: Physics | T26: Vikram Joshi | U26: 2024-04-02 | V26: 2024-04-02 | W26: 24055 | X26: 23749 | Y26: 306 | Z26: 787 | AA26: No | AC26: Partial | AD26: Cash | AE26: 6 | AF26: 83 | AG26: 95 | AH26: Good | AI26: 67 | AJ26: 53 | AK26: 52 | AL26: Sick leave | AM26: 100 | AN26: No | AO26: 3 | AP26: 2 | AQ26: 2024-05-08 | AR26: 2024-05-25 | AS26: No | AT26: Website | AU26: Rahul Mehta | AV26: Active
A27: SI-026 | B27: meera jain | C27: 2005-10-23 | D27: Female | E27: 9875749873 | F27: aarav.joshi26@gmail.com | G27: 278, Sinhgad Road Pune | H27: Sinhgad Spring Dale School | I27: 76 | J27: 9993477182 | K27: Crash Course | L27: 3 | M27: Evening | N27: 2024-03-01 | O27: 2024-05-30 | P27: R-117 | Q27: Offline | R27: Mon-Wed-Fri | S27: Chemistry | T27: Sneha Patil | U27: 2024-02-17 | V27: 2024-02-09 | W27: 47763 | X27: 46154 | Y27: 1609 | Z27: 2256 | AA27: Yes | AB27: 2024-03-18 | AC27: Partial | AD27: Cash | AE27: 10 | AF27: 61 | AG27: 95 | AH27: Needs Improvement | AI27: 78 | AJ27: 38 | AK27: 16 | AL27: Sick leave | AM27: 42 | AN27: Yes | AO27: 2 | AP27: 2 | AQ27: 2024-03-26 | AR27: 2024-04-14 | AS27: No | AT27: Facebook Ad | AU27: Amit Deshmukh | AV27: Active
A28: SI-027 | B28: Aarav Joshi | C28: 2006-02-25 | D28: Male | E28: 9838552856 | F28: aarav.joshi27@gmail.com | G28: 730, Sinhgad Road Pune | H28: DSK School | I28: 61 | J28: 9977347763 | K28: NEET | L28: 3 | M28: Morning | N28: 2024-03-04 | O28: 2024-06-02 | P28: R-111 | Q28: Offline | R28: Tue-Thu-Sat | S28: English | T28: Preeti Desai | U28: 2024-05-05 | V28: 2024-04-26 | W28: 33335 | X28: 32260 | Y28: 1075 | Z28: 2385 | AA28: Yes | AB28: 2024-06-04 | AC28: Partial | AD28: UPI | AE28: 7 | AF28: 68 | AG28: 93 | AH28: Average | AI28: 96 | AJ28: 33 | AK28: 22 | AL28: Sick leave | AM28: 66 | AN28: Yes | AO28: 2 | AP28: 1 | AQ28: 2024-06-17 | AR28: 2024-06-27 | AS28: Yes | AT28: Referral | AU28: Amit Deshmukh | AV28: Active
A29: SI-028 | B29: Ayaan Desai | C29: 2005-11-29 | D29: Female | E29: 9849681112 | F29: ayaan.desai28@gmail.com | G29: 453, Sinhgad Road Pune | H29: City School | I29: 87 | J29: 9915629583 | K29: MHT-CET | L29: 6 | M29: Afternoon | N29: 2024-01-09 | O29: 2024-07-07 | P29: R-104 | Q29: Hybrid | R29: Tue-Thu-Sat | S29: Maths | T29: Preeti Desai | U29: 2024-05-29 | V29: 2024-05-24 | W29: 33488 | X29: 30413 | Y29: 3075 | Z29: 3261 | AA29: Yes | AB29: 2024-06-28 | AC29: Partial | AD29: Cash | AE29: 5 | AF29: 69 | AG29: 92 | AH29: Needs Improvement | AI29: 69 | AJ29: 36 | AK29: 33 | AM29: 100 | AN29: No | AO29: 2 | AP29: 3 | AQ29: 2024-06-24 | AR29: 2024-07-11 | AS29: Yes | AT29: Instagram Ad | AU29: Nidhi Shah | AV29: Left | AW29: Lost interest
A30: SI-029 | B30: Reyansh Joshi | C30: 2005-01-18 | D30: Male | E30: 9881568974 | F30: reyansh.joshi29@gmail.com | G30: 531, Sinhgad Road Pune | H30: Sinhgad Spring Dale School | I30: 89 | J30: 9938361320 | K30: NEET | L30: 12 | M30: Afternoon | N30: 2024-02-14 | O30: 2025-02-08 | P30: R-109 | Q30: Offline | R30: Mon-Wed-Fri | S30: Maths | T30: Sneha Patil | U30: 2024-05-16 | V30: 2024-05-10 | W30: 32295 | X30: 32187 | Y30: 108 | Z30: 196 | AA30: Yes | AB30: 2024-06-15 | AC30: Partial | AD30: Card | AE30: 6 | AF30: 80 | AG30: 97 | AH30: Average | AI30: 99 | AJ30: 37 | AK30: 26 | AL30: Sick leave | AM30: 40 | AN30: No | AO30: 4 | AP30: 4 | AQ30: 2024-06-13 | AR30: 2024-07-13 | AS30: No | AT30: Website | AU30: Amit Deshmukh | AV30: Active
A31: SI-030 | B31: Ayaan Kumar | C31: 2006-08-11 | D31: Female | E31: 9868422199 | F31: ayaan.kumar30@gmail.com | G31: 787, Sinhgad Road Pune | H31: Sinhgad Spring Dale School | I31: 70 | J31: 9926436167 | K31: NEET | L31: 12 | M31: Morning | N31: 2024-03-03 | O31: 2025-02-26 | P31: R-111 | Q31: Online | R31: Mon-Wed-Fri | S31: Physics | T31: Anil Sharma | U31: 2024-03-27 | V31: 2024-03-24 | W31: 33476 | X31: 32289 | Y31: 1187 | Z31: 4267 | AA31: Yes | AB31: 2024-04-26 | AC31: Partial | AD31: Bank Transfer | AE31: 6 | AF31: 50 | AG31: 63 | AH31: Needs Improvement | AI31: 96 | AJ31: 24 | AK31: 24 | AM31: 100 | AN31: No | AO31: 1 | AP31: 1 | AQ31: 2024-05-01 | AR31: 2024-05-29 | AS31: Yes | AT31: Walk-in | AU31: Nidhi Shah | AV31: Left | AW31: Too far
A32: SI-031 | B32: Meera Desai | C32: 2006-05-25 | D32: Female | E32: 9813983071 | F32: meera.desai31@gmail.com | G32: 794, Sinhgad Road Pune | H32: City School | I32: 75 | J32: 9926352900 | K32: MHT-CET | L32: 12 | M32: Evening | N32: 2024-01-25 | O32: 2025-01-19 | P32: R-120 | Q32: Online | R32: Tue-Thu-Sat | S32: English | T32: Preeti Desai | U32: 2024-05-01 | V32: 2024-04-21 | W32: 46278 | X32: 45890 | Y32: 388 | Z32: 4438 | AA32: Yes | AB32: 2024-05-31 | AC32: Partial | AD32: Cash | AE32: 7 | AF32: 54 | AG32: 84 | AH32: Needs Improvement | AI32: 83 | AJ32: 58 | AK32: 50 | AL32: Family function | AM32: 86 | AN32: No | AO32: 5 | AP32: 5 | AQ32: 2024-05-31 | AR32: 2024-06-19 | AS32: No | AT32: Instagram Ad | AU32: Nidhi Shah | AV32: Left | AW32: Too far
A33: SI-032 | B33: Siya Sharma | C33: 2005-08-05 | D33: Other | E33: 9818703069 | F33: siya.sharma32@gmail.com | G33: 793, Sinhgad Road Pune | H33: Modern College | I33: 89 | J33: 9950378746 | K33: MHT-CET | L33: 3 | M33: Evening | N33: 2024-01-05 | O33: 2024-04-04 | P33: R-104 | Q33: Hybrid | R33: Mon-Wed-Fri | S33: Physics | T33: Preeti Desai | U33: 2024-03-13 | V33: 2024-03-09 | W33: 26240 | X33: 23932 | Y33: 2308 | Z33: 2659 | AA33: No | AC33: Partial | AD33: Cash | AE33: 5 | AF33: 49 | AG33: 65 | AH33: Average | AI33: 92 | AJ33: 26 | AK33: 25 | AM33: 96 | AN33: No | AO33: 5 | AP33: 1 | AQ33: 2024-04-09 | AR33: 2024-04-25 | AS33: No | AT33: Facebook Ad | AU33: Rahul Mehta | AV33: Left | AW33: Too far
A34: SI-033 | B34: Kabir Patil | C34: 2005-07-24 | D34: Male | E34: 9879935616 | F34: kabir.patil33@gmail.com | G34: 998, Sinhgad Road Pune | H34: Modern College | I34: 70 | J34: 9982505697 | K34: Crash Course | L34: 6 | M34: Afternoon | N34: 2024-02-05 | O34: 2024-08-03 | P34: R-111 | Q34: Offline | R34: Tue-Thu-Sat | S34: Maths | T34: Anil Sharma | U34: 2024-04-06 | V34: 2024-04-02 | W34: 42298 | X34: 42293 | Y34: 5 | Z34: 246 | AA34: No | AC34: Partial | AD34: Bank Transfer | AE34: 9 | AF34: 42 | AG34: 92 | AH34: Average | AI34: 63 | AJ34: 56 | AK34: 52 | AL34: Sick leave | AM34: 92 | AN34: Yes | AO34: 4 | AP34: 2 | AQ34: 2024-05-18 | AR34: 2024-06-15 | AS34: No | AT34: Walk-in | AU34: Rahul Mehta | AV34: Active
A35: SI-034 | B35: Siya Desai | C35: 2005-01-01 | D35: Other | E35: 9821163374 | F35: siya.desai34@gmail.com | G35: 625, Sinhgad Road Pune | H35: National School | I35: 68 | J35: 9942439828 | K35: MHT-CET | L35: 12 | M35: Afternoon | N35: 2024-02-19 | O35: 2025-02-13 | P35: R-108 | Q35: Hybrid | R35: Tue-Thu-Sat | S35: English | T35: Sneha Patil | U35: 2024-03-02 | V35: 2024-02-25 | W35: 19105 | X35: 16632 | Y35: 2473 | Z35: 4817 | AA35: Yes | AB35: 2024-04-01 | AC35: Partial | AD35: Bank Transfer | AE35: 3 | AF35: 82 | AG35: 85 | AH35: Average | AI35: 80 | AJ35: 36 | AK35: 19 | AL35: Sick leave | AM35: 52 | AN35: Yes | AO35: 2 | AP35: 2 | AQ35: 2024-04-27 | AR35: 2024-05-11 | AS35: No | AT35: Instagram Ad | AU35: Amit Deshmukh | AV35: Left | AW35: Lost interest
A36: SI-035 | B36: kabir jain | C36: 2006-05-28 | D36: Other | E36: 9840661080 | F36: kabir.kumar35@gmail.com | G36: 952, Sinhgad Road Pune | H36: City School | I36: 94 | J36: 9983943710 | K36: NEET | L36: 3 | M36: Afternoon | N36: 2024-01-12 | O36: 2024-04-11 | P36: R-120 | Q36: Online | R36: Tue-Thu-Sat | S36: Chemistry | T36: Vikram Joshi | U36: 2024-04-30 | V36: 2024-04-30 | W36: 27390 | X36: 23996 | Y36: 3394 | Z36: 3563 | AA36: Yes | AB36: 2024-05-30 | AC36: Partial | AD36: UPI | AE36: 1 | AF36: 41 | AG36: 76 | AH36: Good | AI36: 89 | AJ36: 59 | AK36: 59 | AL36: Family function | AM36: 50 | AN36: No | AO36: 4 | AP36: 2 | AQ36: 2024-05-29 | AR36: 2024-06-17 | AS36: Yes | AT36: Facebook Ad | AU36: Amit Deshmukh | AV36: Active
A37: SI-036 | B37: Ira Sharma | C37: 2005-07-19 | D37: Female | E37: 9895702574 | F37: ira.sharma36@gmail.com | G37: 741, Sinhgad Road Pune | H37: DSK School | I37: 87 | J37: 9922636786 | K37: Crash Course | L37: 3 | M37: Morning | N37: 2024-01-25 | O37: 2024-04-24 | P37: R-107 | Q37: Online | R37: Mon-Wed-Fri | S37: Chemistry | T37: Preeti Desai | U37: 2024-05-07 | V37: 2024-04-30 | W37: 49812 | X37: 49036 | Y37: 776 | Z37: 3907 | AA37: Yes | AB37: 2024-06-06 | AC37: Partial | AD37: Cash | AE37: 10 | AF37: 50 | AG37: 77 | AH37: Needs Improvement | AI37: 77 | AJ37: 57 | AK37: 28 | AM37: 49 | AN37: No | AO37: 5 | AP37: 1 | AQ37: 2024-05-28 | AR37: 2024-06-17 | AS37: No | AT37: Referral | AU37: Nidhi Shah | AV37: Active
A38: SI-037 | B38: arya joshi | C38: 2005-06-16 | D38: Male | E38: 9845928801 | F38: aarav.joshi37@gmail.com | G38: 559, Sinhgad Road Pune | H38: National School | I38: 78 | J38: 9971190395 | K38: MHT-CET | L38: 6 | M38: Morning | N38: 2024-01-25 | O38: 2024-07-23 | P38: R-113 | Q38: Hybrid | R38: Mon-Wed-Fri | S38: Maths | T38: Ravi Kumar | U38: 2024-04-27 | V38: 2024-04-23 | W38: 33401 | X38: 32134 | Y38: 1267 | Z38: 2830 | AA38: No | AC38: Partial | AD38: Cash | AE38: 4 | AF38: 55 | AG38: 84 | AH38: Needs Improvement | AI38: 60 | AJ38: 46 | AK38: 42 | AL38: Family function | AM38: 91 | AN38: Yes | AO38: 3 | AP38: 2 | AQ38: 2024-06-04 | AR38: 2024-06-18 | AS38: No | AT38: Walk-in | AU38: Nidhi Shah | AV38: Active
A39: SI-038 | B39: dev neeraj | C39: 2005-07-17 | D39: Female | E39: 9829480294 | F39: siya.sharma38@gmail.com | G39: 986, Sinhgad Road Pune | H39: Sinhgad Spring Dale School | I39: 83 | J39: 9916241293 | K39: MHT-CET | L39: 3 | M39: Morning | N39: 2024-01-20 | O39: 2024-04-19 | P39: R-119 | Q39: Offline | R39: Tue-Thu-Sat | S39: Physics | T39: Vikram Joshi | U39: 2024-03-24 | V39: 2024-03-15 | W39: 18755 | X39: 18447 | Y39: 308 | Z39: 977 | AA39: No | AC39: Partial | AD39: Cash | AE39: 8 | AF39: 86 | AG39: 90 | AH39: Average | AI39: 99 | AJ39: 41 | AK39: 17 | AL39: Sick leave | AM39: 41 | AN39: Yes | AO39: 4 | AP39: 2 | AQ39: 2024-05-19 | AR39: 2024-06-11 | AS39: Yes | AT39: Walk-in | AU39: Amit Deshmukh | AV39: Active
